Workbook
Name _p1: #REF!
Name _p1: #REF!
Name CURRENTYEAR: #REF!
Name CURRENTYEAR: #REF!
Name LOOKUPMTH: #REF!
Name LOOKUPMTH: #REF!
Name mi: #REF!
Name mi: #REF!
Name Month: #REF!
Name Month: #REF!
Name PRINT_AREA_MI: #REF!
Name PRINT_AREA_MI: #REF!
Name web: #REF!
Name web: #REF!

Sheet Assumptions&Calculations
A1: AGRICULTURAL AND FISHERIES MACHINERY | D1: Presets
A2: Assumptions: | B2: 2025 | D2: 2022 | E2: 2022-2021 Incremental | F2: 2021 | G2: 2021-2020 Incremental | H2: 2020 | I2: 2020-2019 Incremental | J2: 2019 | K2: 2019-2018 Incremental | L2: 2018 | M2: 2022-2020 Incremental | N2: 2025
A3: Gasoline (Php/L) | B3: 70.25 | D3: 70.7 | E3: =D3-F3 -> 15.15 | F3: =($D3*E$6)/$C$6 -> 55.55 | G3: =F3-H3 -> 10.1 | H3: =($D3*G$6)/$C$6 -> 45.45 | I3: =H3-J3 -> -5.05 | J3: =($D3*I$6)/$C$6 -> 50.5 | K3: =J3-L3 -> 2.525 | L3: =($D3*K$6)/$C$6 -> 47.975 | M3: =E3+G3 -> 25.25
A4: Diesel (Php/L) | B4: 58.3 | D4: 69.7 | E4: =D4-F4 -> 14.935714 | F4: =($D4*E$6)/$C$6 -> 54.764286 | G4: =F4-H4 -> 9.9571429 | H4: =($D4*G$6)/$C$6 -> 44.807143 | I4: =H4-J4 -> -4.9785714 | J4: =($D4*I$6)/$C$6 -> 49.785714 | K4: =J4-L4 -> 2.4892857 | L4: =($D4*K$6)/$C$6 -> 47.296429 | M4: =E4+G4 -> 24.892857
A5: Kerosene (Php/L) | B5: 72.62 | D5: 79.15 | E5: =D5-F5 -> 16.960714 | F5: =($D5*E$6)/$C$6 -> 62.189286 | G5: =F5-H5 -> 11.307143 | H5: =($D5*G$6)/$C$6 -> 50.882143 | I5: =H5-J5 -> -5.6535714 | J5: =($D5*I$6)/$C$6 -> 56.535714 | K5: =J5-L5 -> 2.8267857 | L5: =($D5*K$6)/$C$6 -> 53.708929 | M5: =E5+G5 -> 28.267857
A6: Average Price Graph | C6: 1.4 | E6: 1.1 | G6: 0.9 | I6: 1 | K6: 0.95
A7: MOPS | C7: =AVERAGE(MOPS!D150:D243) -> 158.5231 | E7: =C6*'Daily Exchange Rate'!$O8 -> 74.280402 | G7: =E6*'Daily Exchange Rate'!$O42 -> 54.200123 | I7: =G6*'Daily Exchange Rate'!$O76 -> 44.671827 | K7: =I6*'Daily Exchange Rate'!$O110 -> 51.796884 | L7: =K6*'Daily Exchange Rate'!$O144 -> 50.04248
A8: Subsidy (%) | B8: 1
A9: OPERATION | B9: MACHINERY | C9: Number of Units | D9: ASSUMPTIONS | K9: Cost Per ha | L9: TOTAL VOLUME OF FUEL | O9: TOTAL COST (Php) | R9: TOTAL COST (PHP) | S9: SUBSIDY (PHP) | T9: Land Area (ha/day) | V9: Cost Per ha | W9: Cost per ha-day
D10: Hr/ day | E10: Days/ Operation | F10: Hr/ Operation | G10: FC (L/hr) | H10: L/Operation | I10: Total Cost/ Operation Per Unit | L10: GASOLINE | M10: DIESEL | N10: KEROSENE | O10: GASOLINE | P10: DIESEL | Q10: KEROSENE | X10: Subsidy | Y10: Estimated Total Cost per ha | Z10: Percentage compared to Total Cost per ha | AA10: Percentage compared to average cost per ha-day
A11: Rice | O11: =$B$3*L11 -> 0 | P11: =$B$4*M11 -> 0 | R11: =SUM(O11:Q11) -> 0 | S11: =R11*$B$8 -> 0 | W11: =SUM(W12:W23) -> 3890.7262 | X11: =AVERAGE(W11,W24,W29,W39) -> 3547.818 | Y11: =X11*E42 -> 68065.545 | Z11: =X11/Y11 -> 0.052123552
A12: Land Preparation | B12: 4WD Tractor | C12: ='Total Inventory (Rice)'!C83 -> 24977 | D12: 8 | E12: 22 | F12: =E12*D12 -> 176 | G12: 10 | H12: =G12*F12 -> 1760 | I12: =H12*$B$4 -> 102608 | J12: =I12/E12 -> 4664 | K12: =J12/T12 -> 971.66667 | M12: =G12*F12*C12 -> 43959520 | O12: =$B$3*L12 -> 0 | P12: =$B$4*M12 -> 2562840016 | R12: =SUM(O12:Q12) -> 2562840016 | S12: =R12*$B$8 -> 2562840016 | T12: =0.6*D12 -> 4.8 | U12: =T12/D12 -> 0.6 | V12: =I12/(T12*E12)*$B$8 -> 971.66667 | W12: =AVERAGE(V12:V13) -> 680.16667 | X12: 3000 | Z12: =X12/Y11 -> 0.044075163 | AA12: =Z12/Z11 -> 0.84559016
B13: Hand Tractor | C13: ='Total Inventory (Rice)'!D83 -> 41132 | D13: 8 | E13: 22 | F13: =E13*D13 -> 176 | G13: 1 | H13: =G13*F13 -> 176 | I13: =H13*$B$4 -> 10260.8 | J13: =I13/E13 -> 466.4 | K13: =J13/T13 -> 388.66667 | M13: =G13*F13*C13 -> 7239232 | O13: =$B$3*L13 -> 0 | P13: =$B$4*M13 -> 4.2204723e+08 | R13: =SUM(O13:Q13) -> 4.2204723e+08 | S13: =R13*$B$8 -> 4.2204723e+08 | T13: =0.15*D13 -> 1.2 | U13: =T13/D13 -> 0.15 | V13: =I13/(T13*E13)*$B$8 -> 388.66667 | X13: 5000 | Z13: =X13/Y11 -> 0.073458605 | AA13: =Z13/Z11 -> 1.4093169
A14: Irrigation | B14: Engines | C14: ='Total Inventory (Rice)'!E83 -> 96776 | D14: 10 | E14: 20 | F14: =E14*D14 -> 200 | G14: 1.5 | H14: =G14*F14 -> 300 | I14: =H14*$B$4 -> 17490 | J14: =I14/E14 -> 874.5 | K14: =J14/T14 -> 874.5 | L14: =G14*F14*0.3*C14 -> 8709840 | M14: =G14*F14*0.7*C14 -> 20322960 | O14: =$B$3*L14 -> 611866260 | P14: =$B$4*M14 -> 1184828568 | R14: =SUM(O14:P14) -> 1796694828 | S14: =R14*$B$8 -> 1796694828 | T14: 1 | U14: =T14/D14 -> 0.1 | V14: =I14/(T14*E14)*$B$8 -> 874.5 | W14: =V14 -> 874.5 | X14: 7000 | Z14: =X14/Y11 -> 0.10284205 | AA14: =Z14/Z11 -> 1.9730437
A15: Transplanting | B15: Rice Transplanter (Walking-Type) | C15: ='Total Inventory (Rice)'!H83 -> 6624 | D15: 8 | E15: 22 | F15: =E15*D15 -> 176 | G15: 0.8 | H15: =G15*F15 -> 140.8 | I15: =H15*$B$4 -> 8208.64 | J15: =I15/E15 -> 373.12 | K15: =J15/T15 -> 310.93333 | L15: =G15*F15*C15 -> 932659.2 | O15: =$B$3*L15 -> 65519309 | P15: =$B$4*M15 -> 0 | R15: =SUM(O15:Q15) -> 65519309 | S15: =R15*$B$8 -> 65519309 | T15: =0.15*D15 -> 1.2 | U15: =T15/D15 -> 0.15 | V15: =I15/(T15*E15)*$B$8 -> 310.93333 | W15: =AVERAGE(V15:V17) -> 285.02222 | X15: 10000 | Z15: =X15/Y11 -> 0.14691721 | AA15: =Z15/Z11 -> 2.8186339
B16: Rice Transplanter (Ride-on-Type) | C16: ='Total Inventory (Rice)'!G83 -> 2477 | D16: 8 | E16: 22 | F16: =E16*D16 -> 176 | G16: 1 | H16: =G16*F16 -> 176 | I16: =H16*$B$4 -> 10260.8 | J16: =I16/E16 -> 466.4 | K16: =J16/T16 -> 233.2 | L16: =G16*F16*C16 -> 435952 | O16: =$B$3*L16 -> 30625628 | P16: =$B$4*M16 -> 0 | R16: =SUM(O16:Q16) -> 30625628 | S16: =R16*$B$8 -> 30625628 | T16: =0.25*D16 -> 2 | U16: =T16/D16 -> 0.25 | V16: =I16/(T16*E16)*$B$8 -> 233.2
B17: Precision Seeder and Planter | C17: ='Total Inventory (Rice)'!F83 -> 2623 | D17: 6 | E17: 22 | F17: =E17*D17 -> 132 | G17: 0.8 | H17: =G17*F17 -> 105.6 | I17: =H17*$B$4 -> 6156.48 | J17: =I17/E17 -> 279.84 | K17: =J17/T17 -> 310.93333 | L17: =G17*F17*C17 -> 276988.8 | O17: =$B$3*L17 -> 19458463 | P17: =$B$4*M17 -> 0 | R17: =SUM(O17:Q17) -> 19458463 | S17: =R17*$B$8 -> 19458463 | T17: =0.15*D17 -> 0.9 | U17: =T17/D17 -> 0.15 | V17: =I17/(T17*E17)*$B$8 -> 310.93333
A18: Crop Care | B18: Fertilizer Aplicator | C18: ='Total Inventory (Rice)'!I83 -> 10942 | D18: 8 | E18: 10 | F18: =E18*D18 -> 80 | G18: 0.8 | H18: =G18*F18 -> 64 | I18: =H18*$B$4 -> 3731.2 | J18: =I18/E18 -> 373.12 | K18: =J18/T18 -> 126.05405 | L18: =G18*F18*C18 -> 700288 | O18: =$B$3*L18 -> 49195232 | P18: =$B$4*M18 -> 0 | R18: =SUM(O18:Q18) -> 49195232 | S18: =R18*$B$8 -> 49195232 | T18: =0.37*D18 -> 2.96 | U18: =T18/D18 -> 0.37 | V18: =I18/(T18*E18)*$B$8 -> 126.05405 | W18: =V18 -> 126.05405
A19: Harvesting | B19: Mechanical Reaper | C19: ='Total Inventory (Rice)'!J83 -> 4889 | D19: 8 | E19: 15 | F19: =E19*D19 -> 120 | G19: 0.8 | H19: =G19*F19 -> 96 | I19: =H19*$B$4 -> 5596.8 | J19: =I19/E19 -> 373.12 | K19: =J19/T19 -> 126.05405 | L19: =G19*F19*C19 -> 469344 | O19: =$B$3*L19 -> 32971416 | P19: =$B$4*M19 -> 0 | R19: =SUM(O19:Q19) -> 32971416 | S19: =R19*$B$8 -> 32971416 | T19: =0.37*D19 -> 2.96 | U19: =T19/D19 -> 0.37 | V19: =I19/(T19*E19)*$B$8 -> 126.05405 | W19: =(V19+V21+V20)/2 -> 585.24928
B20: Combine Harvester | C20: ='Total Inventory (Rice)'!K83 -> 9129 | D20: 8 | E20: 40 | F20: =E20*D20 -> 320 | G20: 10 | H20: =G20*F20 -> 3200 | I20: =H20*$B$4 -> 186560 | J20: =I20/E20 -> 4664 | K20: =J20/T20 -> 932.8 | M20: =G20*F20*C20 -> 29212800 | O20: =$B$3*L20 -> 0 | P20: =$B$4*M20 -> 1703106240 | R20: =SUM(O20:Q20) -> 1703106240 | S20: =R20*$B$8 -> 1703106240 | T20: =(0.625*D20) -> 5 | U20: =T20/D20 -> 0.625 | V20: =I20/(T20*E20)*$B$8 -> 932.8
A21: Processing | B21: Thresher | C21: ='Total Inventory (Rice)'!M83 -> 14097 | D21: 8 | E21: 22 | F21: =E21*D21 -> 176 | G21: 1 | H21: =G21*F21 -> 176 | I21: =H21*$B$4 -> 10260.8 | J21: =I21/E21 -> 466.4 | K21: =J21/T21 -> 111.6445 | M21: =G21*F21*C21 -> 2481072 | O21: =$B$3*L21 -> 0 | P21: =$B$4*M21 -> 1.446465e+08 | R21: =SUM(O21:Q21) -> 1.446465e+08 | S21: =R21*$B$8 -> 1.446465e+08 | T21: =(2/3.83)*D21 -> 4.1775457 | U21: =T21/D21 -> 0.52219321 | V21: =I21/(T21*E21)*$B$8 -> 111.6445
A22: Drying | B22: Dryer | C22: ='Total Inventory (Rice)'!L83 -> 1150 | D22: 8 | E22: 30 | F22: =E22*D22 -> 240 | G22: 9 | H22: =G22*F22 -> 2160 | I22: =H22*$B$4 -> 125928 | J22: =I22/E22 -> 4197.6 | K22: =J22/T22 -> 1004.8005 | N22: =G22*F22*C22 -> 2484000 | O22: =$B$3*L22 -> 0 | Q22: =$B$4*N22 -> 144817200 | R22: =SUM(O22:Q22) -> 144817200 | S22: =R22*$B$8 -> 144817200 | T22: =(2/3.83)*D22 -> 4.1775457 | U22: =T22/D22 -> 0.52219321 | V22: =I22/(T22*E22)*$B$8 -> 1004.8005 | W22: =V22 -> 1004.8005
A23: Hauling/ Transport | B23: Truck/ Forklift | C23: ='Total Inventory (Rice)'!N83 -> 5 | D23: 8 | E23: 15 | F23: =E23*D23 -> 120 | G23: 3 | H23: =G23*F23 -> 360 | I23: =H23*$B$4 -> 20988 | J23: =I23/E23 -> 1399.2 | K23: =J23/T23 -> 334.9335 | M23: =G23*F23*C23 -> 1800 | O23: =$B$3*L23 -> 0 | P23: =$B$4*M23 -> 104940 | R23: =SUM(O23:Q23) -> 104940 | S23: =R23*$B$8 -> 104940 | T23: =(2/3.83)*D23 -> 4.1775457 | U23: =T23/D23 -> 0.52219321 | V23: =I23/(T23*E23)*$B$8 -> 334.9335 | W23: =V23 -> 334.9335
A24: Corn | O24: =$B$3*L24 -> 0 | P24: =$B$4*M24 -> 0 | R24: =SUM(O24:Q24) -> 0 | S24: =R24*$B$8 -> 0 | W24: =SUM(W25:W28) -> 4449.0673
A25: Land Preparation | B25: 4WD Tractor | C25: ='Total Inventory (Corn)'!C83 -> 13043 | D25: 8 | E25: 30 | F25: =E25*D25 -> 240 | G25: 20 | H25: =G25*F25 -> 4800 | I25: =H25*$B$4 -> 279840 | J25: =I25/E25 -> 9328 | K25: =J25/T25 -> 1943.3333 | M25: =G25*F25*C25 -> 62606400 | O25: =$B$3*L25 -> 0 | P25: =$B$4*M25 -> 3649953120 | R25: =SUM(O25:Q25) -> 3649953120 | S25: =R25*$B$8 -> 3649953120 | T25: =0.6*D12 -> 4.8 | U25: =T25/D25 -> 0.6 | V25: =I25/(T25*E25)*$B$8 -> 1943.3333 | W25: =V25 -> 1943.3333
A26: Harvesting | B26: Combine Harvesters | C26: ='Total Inventory (Corn)'!D83 -> 2164 | D26: 8 | E26: 22 | F26: =E26*D26 -> 176 | G26: 10 | H26: =G26*F26 -> 1760 | I26: =H26*$B$4 -> 102608 | J26: =I26/E26 -> 4664 | K26: =J26/T26 -> 1166 | M26: =G26*F26*C26 -> 3808640 | O26: =$B$3*L26 -> 0 | P26: =$B$4*M26 -> 222043712 | R26: =SUM(O26:Q26) -> 222043712 | S26: =R26*$B$8 -> 222043712 | T26: =(0.5*D26) -> 4 | U26: =T26/D26 -> 0.5 | V26: =I26/(T26*E26)*$B$8 -> 1166 | W26: =V26 -> 1166
A27: Drying | B27: Dryer | C27: ='Total Inventory (Corn)'!E83 -> 2901 | D27: 8 | E27: 30 | F27: =E27*D27 -> 240 | G27: 9 | H27: =G27*F27 -> 2160 | I27: =H27*$B$4 -> 125928 | J27: =I27/E27 -> 4197.6 | K27: =J27/T27 -> 1004.8005 | M27: =G27*F27*C27 -> 6266160 | O27: =$B$3*L27 -> 0 | P27: =$B$4*M27 -> 365317128 | R27: =SUM(O27:Q27) -> 365317128 | S27: =R27*$B$8 -> 365317128 | T27: =(2/3.83)*D27 -> 4.1775457 | U27: =T27/D27 -> 0.52219321 | V27: =I27/(T27*E27)*$B$8 -> 1004.8005 | W27: =V27 -> 1004.8005
A28: Processing | B28: Pre Processing and Size Reduction Machinery | C28: ='Total Inventory (Corn)'!F83 -> 21007 | D28: 8 | E28: 22 | F28: =E28*D28 -> 176 | G28: 3 | H28: =G28*F28 -> 528 | I28: =H28*$B$4 -> 30782.4 | J28: =I28/E28 -> 1399.2 | K28: =J28/T28 -> 334.9335 | M28: =G28*F28*C28 -> 11091696 | O28: =$B$3*L28 -> 0 | P28: =$B$4*M28 -> 6.4664588e+08 | R28: =SUM(O28:Q28) -> 6.4664588e+08 | S28: =R28*$B$8 -> 6.4664588e+08 | T28: =(2/3.83)*D28 -> 4.1775457 | U28: =T28/D28 -> 0.52219321 | V28: =I28/(T28*E28)*$B$8 -> 334.9335 | W28: =V28 -> 334.9335
A29: HVC | O29: =$B$3*L29 -> 0 | P29: =$B$4*M29 -> 0 | R29: =SUM(O29:Q29) -> 0 | S29: =R29*$B$8 -> 0 | W29: =SUM(W30:W38) -> 3559.584
A30: Land Preparation | B30: 4WD Tractor | C30: ='Total Inventory (HVC)'!C85 -> 23187 | D30: 6 | E30: 10 | F30: =E30*D30 -> 60 | G30: 15 | H30: =G30*F30 -> 900 | I30: =H30*$B$4 -> 52470 | J30: =I30/E30 -> 5247 | K30: =J30/T30 -> 1093.125 | M30: =G30*F30*C30 -> 20868300 | O30: =$B$3*L30 -> 0 | P30: =$B$4*M30 -> 1216621890 | R30: =SUM(O30:Q30) -> 1216621890 | S30: =R30*$B$8 -> 1216621890 | T30: =0.6*D21 -> 4.8 | U30: =T30/D30 -> 0.8 | V30: =I30/(T30*E30)*$B$8 -> 1093.125 | W30: =AVERAGE(V30:V31) -> 740.89583
B31: Hand Tractor | D31: 6 | E31: 10 | F31: =E31*D31 -> 60 | G31: 1 | H31: =G31*F31 -> 60 | I31: =H31*$B$4 -> 3498 | J31: =I31/E31 -> 349.8 | K31: =J31/T31 -> 388.66667 | M31: =G31*F31*C31 -> 0 | O31: =$B$3*L31 -> 0 | P31: =$B$4*M31 -> 0 | R31: =SUM(O31:Q31) -> 0 | S31: =R31*$B$8 -> 0 | T31: =0.15*D31 -> 0.9 | U31: =T31/D31 -> 0.15 | V31: =I31/(T31*E31)*$B$8 -> 388.66667
A32: Planter | B32: Precision Seeder and Planter | C32: ='Total Inventory (HVC)'!E85 -> 5 | D32: 6 | E32: 22 | F32: =E32*D32 -> 132 | G32: 0.8 | H32: =G32*F32 -> 105.6 | I32: =H32*$B$4 -> 6156.48 | J32: =I32/E32 -> 279.84 | K32: =J32/T32 -> 310.93333 | L32: =G32*F32*C32 -> 528 | O32: =$B$3*L32 -> 37092 | P32: =$B$4*M32 -> 0 | R32: =SUM(O32:Q32) -> 37092 | S32: =R32*$B$8 -> 37092 | T32: =0.15*D32 -> 0.9 | U32: =T32/D32 -> 0.15 | V32: =I32/(T32*E32)*$B$8 -> 310.93333 | W32: =V32 -> 310.93333
A33: Crop Care | B33: Fertilizer Aplicator | C33: ='Total Inventory (HVC)'!F85 -> 49320 | D33: 8 | E33: 10 | F33: =E33*D33 -> 80 | G33: 0.8 | H33: =G33*F33 -> 64 | I33: =H33*$B$4 -> 3731.2 | J33: =I33/E33 -> 373.12 | K33: =J33/T33 -> 126.05405 | L33: =G33*F33*C33 -> 3156480 | O33: =$B$3*L33 -> 221742720 | P33: =$B$4*M33 -> 0 | R33: =SUM(O33:Q33) -> 221742720 | S33: =R33*$B$8 -> 221742720 | T33: =0.37*D33 -> 2.96 | U33: =T33/D33 -> 0.37 | V33: =I33/(T33*E33)*$B$8 -> 126.05405 | W33: =V33 -> 126.05405
A34: Harvesting and Processing | B34: Harvesters | C34: ='Total Inventory (HVC)'!G85 -> 15 | D34: 6 | E34: 15 | F34: =E34*D34 -> 90 | G34: 10 | H34: =G34*F34 -> 900 | I34: =H34*$B$4 -> 52470 | J34: =I34/E34 -> 3498 | K34: =J34/T34 -> 1408.2126 | M34: =G34*F34*C34 -> 13500 | O34: =$B$3*L34 -> 0 | P34: =$B$4*M34 -> 787050 | R34: =SUM(O34:Q34) -> 787050 | S34: =R34*$B$8 -> 787050 | T34: =(0.414*D34) -> 2.484 | U34: =T34/D34 -> 0.414 | V34: =I34/(T34*E34)*$B$8 -> 1408.2126
A35: Processing | B35: Processing and Size Reduction Machinery | C35: ='Total Inventory (HVC)'!H85 -> 26185 | D35: 6 | E35: 15 | F35: =E35*D35 -> 90 | G35: 1.5 | H35: =G35*F35 -> 135 | I35: =H35*$B$4 -> 7870.5 | J35: =I35/E35 -> 524.7 | K35: =J35/T35 -> 167.46675 | M35: =G35*F35*C35 -> 3534975 | O35: =$B$3*L35 -> 0 | P35: =$B$4*M35 -> 2.0608904e+08 | R35: =SUM(O35:Q35) -> 2.0608904e+08 | S35: =R35*$B$8 -> 2.0608904e+08 | T35: =(2/3.83)*D35 -> 3.1331593 | U35: =T35/D35 -> 0.52219321 | V35: =I35/(T35*E35)*$B$8 -> 167.46675 | W35: =V35 -> 167.46675
A36: Drying | B36: Thermal Processing | C36: ='Total Inventory (HVC)'!I85 -> 2625 | D36: 8 | E36: 30 | F36: =E36*D36 -> 240 | G36: 9 | H36: =G36*F36 -> 2160 | I36: =H36*$B$4 -> 125928 | J36: =I36/E36 -> 4197.6 | K36: =J36/T36 -> 1004.8005 | N36: =G36*F36*C36 -> 5670000 | O36: =$B$3*L36 -> 0 | P36: =$B$4*M36 -> 0 | Q36: =$B$4*N36 -> 330561000 | R36: =SUM(O36:Q36) -> 330561000 | S36: =R36*$B$8 -> 330561000 | T36: =(2/3.83)*D36 -> 4.1775457 | U36: =T36/D36 -> 0.52219321 | V36: =I36/(T36*E36)*$B$8 -> 1004.8005 | W36: =V36 -> 1004.8005
A37: Irrigation | B37: Engines | C37: ='Total Inventory (HVC)'!D85 -> 325 | D37: 10 | E37: 10 | F37: =E37*D37 -> 100 | G37: 1.5 | H37: =G37*F37 -> 150 | I37: =H37*$B$4 -> 8745 | J37: =I37/E37 -> 874.5 | K37: =J37/T37 -> 874.5 | L37: =G37*F37*0.3*C37 -> 14625 | M37: =G37*F37*0.7*C37 -> 34125 | O37: =$B$3*L37 -> 1027406.2 | P37: =$B$4*M37 -> 1989487.5 | R37: =SUM(O37:P37) -> 3016893.8 | S37: =R37*$B$8 -> 3016893.8 | T37: 1 | U37: =T37/D37 -> 0.1 | V37: =I37/(T37*E37)*$B$8 -> 874.5 | W37: =V37 -> 874.5
A38: Hauling/ Transport | B38: Truck/ Forklift | C38: ='Total Inventory (HVC)'!J85 -> 993 | D38: 8 | E38: 15 | F38: =E38*D38 -> 120 | G38: 3 | H38: =G38*F38 -> 360 | I38: =H38*$B$4 -> 20988 | J38: =I38/E38 -> 1399.2 | K38: =J38/T38 -> 334.9335 | M38: =G38*F38*C38 -> 357480 | O38: =$B$3*L38 -> 0 | P38: =$B$4*M38 -> 20841084 | R38: =SUM(O38:Q38) -> 20841084 | S38: =R38*$B$8 -> 20841084 | T38: =(2/3.83)*D38 -> 4.1775457 | U38: =T38/D38 -> 0.52219321 | V38: =I38/(T38*E38)*$B$8 -> 334.9335 | W38: =V38 -> 334.9335
A39: Sugar | W39: =SUM(W40:W41) -> 2291.8945
A40: Land Preparation | B40: 4WD Tractor | C40: 2911 | D40: 6 | E40: 10 | F40: =E40*D40 -> 60 | G40: 36.41 | H40: =BreakDown!B37 -> 80 | I40: =H40*$B$4 -> 4664 | J40: =I40/E40 -> 466.4 | K40: =J40/T40 -> 62.186667 | M40: =G40*F40*C40 -> 6359370.6 | O40: =$B$3*L40 -> 0 | P40: =$B$4*M40 -> 3.7075131e+08 | R40: =SUM(O40:Q40) -> 3.7075131e+08 | S40: =R40*$B$8 -> 3.7075131e+08 | T40: =1.5*5 -> 7.5 | U40: =T40/D40 -> 1.25 | V40: =I40/(T40*E40)*$B$8 -> 62.186667 | W40: =AVERAGE(V40:V41) -> 784.69371
A41: Hauling/ Transport | B41: Truck | C41: 70547 | D41: 8 | E41: 5 | F41: =D41*E41 -> 40 | G41: =(38/100)*40 -> 15.2 | H41: =BreakDown!B45 -> 540 | I41: =H41*$B$4 -> 31482 | J41: =I41/E41 -> 6296.4 | K41: =J41/T41 -> 1507.2007 | M41: =G41*F41*C41 -> 42892576 | O41: =$B$3*L41 -> 0 | P41: =$B$4*M41 -> 2.5006372e+09 | R41: =SUM(O41:Q41) -> 2.5006372e+09 | S41: =R41*$B$8 -> 2.5006372e+09 | T41: =(2/3.83)*D41 -> 4.1775457 | U41: =T41/D41 -> 0.52219321 | V41: =I41/(T41*E41)*$B$8 -> 1507.2008 | W41: =V41 -> 1507.2008
E42: =AVERAGE(E12:E41) -> 19.185185 | F42: =AVERAGE(F12:F41) -> 148 | R42: =SUM(R11:R41) -> 1.6727072e+10 | S42: =SUM(S11:S41) -> 1.6727072e+10
C43: =SUM(C12:C41) -> 430049

Sheet Summary
A1: REGIONAL FUEL REQUIREMENT PER MONTH | O1: =SUM(O20,O40,O60,O80,O101,O121) -> 1.1048985e+11 | P1: =SUM(P20,P40,P60,P80) -> 1.3201677e+10 | Q1: =O121+O101 -> 7.6619716e+10
A2: RICE | B2: January | C2: February | D2: March | E2: April | F2: May | G2: June | H2: July | I2: August | J2: September | K2: October | L2: November | M2: December | N2: Total Fuel (L) Per Region | O2: Cost (Php) Per Region @ average fuel cost | P2: Cost (Php) Per Region @ incremental cost
A3: CAR | B3: =SUM('Total Fuel per Operation (Rice)'!S$4:S$9) -> 64895.8 | C3: =SUM('Total Fuel per Operation (Rice)'!T$4:T$9) -> 68623 | D3: =SUM('Total Fuel per Operation (Rice)'!U$4:U$9) -> 92490 | E3: =SUM('Total Fuel per Operation (Rice)'!V$4:V$9) -> 111792 | F3: =SUM('Total Fuel per Operation (Rice)'!W$4:W$9) -> 251946 | G3: =SUM('Total Fuel per Operation (Rice)'!X$4:X$9) -> 178107 | H3: =SUM('Total Fuel per Operation (Rice)'!Y$4:Y$9) -> 249908.8 | I3: =SUM('Total Fuel per Operation (Rice)'!Z$4:Z$9) -> 197437 | ... M3: =SUM('Total Fuel per Operation (Rice)'!AD$4:AD$9) -> 279176 | N3: =SUM(B3:M3) -> 2007985.6 | O3: =$N3*AVERAGE('Assumptions&Calculations'!$B$3:$B$5) -> 1.3464882e+08 | P3: =$N3*AVERAGE('Assumptions&Calculations'!$M$3:$M$5) -> 52482528
A4: Region I | B4: =SUM('Total Fuel per Operation (Rice)'!S$10:S$13) -> 4163424 | C4: =SUM('Total Fuel per Operation (Rice)'!T$10:T$13) -> 160688 | D4: =SUM('Total Fuel per Operation (Rice)'!U$10:U$13) -> 10254712 | E4: =SUM('Total Fuel per Operation (Rice)'!V$10:V$13) -> 1026727.8 | F4: =SUM('Total Fuel per Operation (Rice)'!W$10:W$13) -> 1206345 | G4: =SUM('Total Fuel per Operation (Rice)'!X$10:X$13) -> 4163424 | H4: =SUM('Total Fuel per Operation (Rice)'!Y$10:Y$13) -> 160688 | I4: =SUM('Total Fuel per Operation (Rice)'!Z$10:Z$13) -> 0 | ... M4: =SUM('Total Fuel per Operation (Rice)'!AD$10:AD$13) -> 1206345 | N4: =SUM(B4:M4) -> 33623794 | O4: =$N4*AVERAGE('Assumptions&Calculations'!$B$3:$B$5) -> 2.2546995e+09 | P4: =$N4*AVERAGE('Assumptions&Calculations'!$M$3:$M$5) -> 8.7882189e+08
A5: Region II | B5: =SUM('Total Fuel per Operation (Rice)'!S$14:S$18) -> 3389210.4 | C5: =SUM('Total Fuel per Operation (Rice)'!T$14:T$18) -> 1644659 | D5: =SUM('Total Fuel per Operation (Rice)'!U$14:U$18) -> 783584 | E5: =SUM('Total Fuel per Operation (Rice)'!V$14:V$18) -> 4224 | F5: =SUM('Total Fuel per Operation (Rice)'!W$14:W$18) -> 9573640 | G5: =SUM('Total Fuel per Operation (Rice)'!X$14:X$18) -> 9526796.6 | H5: =SUM('Total Fuel per Operation (Rice)'!Y$14:Y$18) -> 2719410.6 | I5: =SUM('Total Fuel per Operation (Rice)'!Z$14:Z$18) -> 3810152 | ... M5: =SUM('Total Fuel per Operation (Rice)'!AD$14:AD$18) -> 4521644.4 | N5: =SUM(B5:M5) -> 54953507 | O5: =$N5*AVERAGE('Assumptions&Calculations'!$B$3:$B$5) -> 3.684999e+09 | P5: =$N5*AVERAGE('Assumptions&Calculations'!$M$3:$M$5) -> 1.4363146e+09
A6: Region III | B6: =SUM('Total Fuel per Operation (Rice)'!S$19:S$25) -> 2307900 | C6: =SUM('Total Fuel per Operation (Rice)'!T$19:T$25) -> 4154144 | D6: =SUM('Total Fuel per Operation (Rice)'!U$19:U$25) -> 705648 | E6: =SUM('Total Fuel per Operation (Rice)'!V$19:V$25) -> 0 | F6: =SUM('Total Fuel per Operation (Rice)'!W$19:W$25) -> 0 | G6: =SUM('Total Fuel per Operation (Rice)'!X$19:X$25) -> 7325360 | H6: =SUM('Total Fuel per Operation (Rice)'!Y$19:Y$25) -> 1794685.6 | I6: =SUM('Total Fuel per Operation (Rice)'!Z$19:Z$25) -> 2307900 | ... M6: =SUM('Total Fuel per Operation (Rice)'!AD$19:AD$25) -> 2411155.6 | N6: =SUM(B6:M6) -> 33191945 | O6: =$N6*AVERAGE('Assumptions&Calculations'!$B$3:$B$5) -> 2.2257412e+09 | P6: =$N6*AVERAGE('Assumptions&Calculations'!$M$3:$M$5) -> 8.6753471e+08
A7: CALABARZON | B7: =SUM('Total Fuel per Operation (Rice)'!S$26:S$30) -> 670858 | C7: =SUM('Total Fuel per Operation (Rice)'!T$26:T$30) -> 1110176 | D7: =SUM('Total Fuel per Operation (Rice)'!U$26:U$30) -> 158272 | E7: =SUM('Total Fuel per Operation (Rice)'!V$26:V$30) -> 0 | F7: =SUM('Total Fuel per Operation (Rice)'!W$26:W$30) -> 0 | G7: =SUM('Total Fuel per Operation (Rice)'!X$26:X$30) -> 1281496 | H7: =SUM('Total Fuel per Operation (Rice)'!Y$26:Y$30) -> 1790075.8 | I7: =SUM('Total Fuel per Operation (Rice)'!Z$26:Z$30) -> 529449.4 | ... M7: =SUM('Total Fuel per Operation (Rice)'!AD$26:AD$30) -> 529449.4 | N7: =SUM(B7:M7) -> 11080654 | O7: =$N7*AVERAGE('Assumptions&Calculations'!$B$3:$B$5) -> 7.4303175e+08 | P7: =$N7*AVERAGE('Assumptions&Calculations'!$M$3:$M$5) -> 2.8961401e+08
A8: MIMAROPA | B8: =SUM('Total Fuel per Operation (Rice)'!S$31:S$35) -> 1159824 | C8: =SUM('Total Fuel per Operation (Rice)'!T$31:T$35) -> 114032 | D8: =SUM('Total Fuel per Operation (Rice)'!U$31:U$35) -> 0 | E8: =SUM('Total Fuel per Operation (Rice)'!V$31:V$35) -> 1159136 | F8: =SUM('Total Fuel per Operation (Rice)'!W$31:W$35) -> 1922404.4 | G8: =SUM('Total Fuel per Operation (Rice)'!X$31:X$35) -> 384279.2 | H8: =SUM('Total Fuel per Operation (Rice)'!Y$31:Y$35) -> 1314270 | I8: =SUM('Total Fuel per Operation (Rice)'!Z$31:Z$35) -> 484720 | ... M8: =SUM('Total Fuel per Operation (Rice)'!AD$31:AD$35) -> 625705 | N8: =SUM(B8:M8) -> 10699891 | O8: =$N8*AVERAGE('Assumptions&Calculations'!$B$3:$B$5) -> 7.1749904e+08 | P8: =$N8*AVERAGE('Assumptions&Calculations'!$M$3:$M$5) -> 2.7966204e+08
A9: Region V | B9: =SUM('Total Fuel per Operation (Rice)'!S$36:S$41) -> 580284.6 | C9: =SUM('Total Fuel per Operation (Rice)'!T$36:T$41) -> 1777156.6 | D9: =SUM('Total Fuel per Operation (Rice)'!U$36:U$41) -> 1033653 | E9: =SUM('Total Fuel per Operation (Rice)'!V$36:V$41) -> 530326.2 | F9: =SUM('Total Fuel per Operation (Rice)'!W$36:W$41) -> 202929 | G9: =SUM('Total Fuel per Operation (Rice)'!X$36:X$41) -> 879288 | H9: =SUM('Total Fuel per Operation (Rice)'!Y$36:Y$41) -> 2038654.2 | I9: =SUM('Total Fuel per Operation (Rice)'!Z$36:Z$41) -> 334124.4 | ... M9: =SUM('Total Fuel per Operation (Rice)'!AD$36:AD$41) -> 500603.4 | N9: =SUM(B9:M9) -> 13271970 | O9: =$N9*AVERAGE('Assumptions&Calculations'!$B$3:$B$5) -> 8.8997404e+08 | P9: =$N9*AVERAGE('Assumptions&Calculations'!$M$3:$M$5) -> 3.4688821e+08
A10: Region VI | B10: =SUM('Total Fuel per Operation (Rice)'!S$42:S$46) -> 838493 | C10: =SUM('Total Fuel per Operation (Rice)'!T$42:T$46) -> 1241024 | D10: =SUM('Total Fuel per Operation (Rice)'!U$42:U$46) -> 212672 | E10: =SUM('Total Fuel per Operation (Rice)'!V$42:V$46) -> 0 | F10: =SUM('Total Fuel per Operation (Rice)'!W$42:W$46) -> 1544632 | G10: =SUM('Total Fuel per Operation (Rice)'!X$42:X$46) -> 257725.4 | H10: =SUM('Total Fuel per Operation (Rice)'!Y$42:Y$46) -> 838493 | I10: =SUM('Total Fuel per Operation (Rice)'!Z$42:Z$46) -> 1241024 | ... M10: =SUM('Total Fuel per Operation (Rice)'!AD$42:AD$46) -> 257725.4 | N10: =SUM(B10:M10) -> 8189092.8 | O10: =$N10*AVERAGE('Assumptions&Calculations'!$B$3:$B$5) -> 5.4913327e+08 | P10: =$N10*AVERAGE('Assumptions&Calculations'!$M$3:$M$5) -> 2.1403754e+08
A11: NIR | B11: =SUM('Total Fuel per Operation (Rice)'!S$47:S$49) -> 123382 | C11: =SUM('Total Fuel per Operation (Rice)'!T$47:T$49) -> 177024 | D11: =SUM('Total Fuel per Operation (Rice)'!U$47:U$49) -> 27456 | E11: =SUM('Total Fuel per Operation (Rice)'!V$47:V$49) -> 0 | F11: =SUM('Total Fuel per Operation (Rice)'!W$47:W$49) -> 644048 | G11: =SUM('Total Fuel per Operation (Rice)'!X$47:X$49) -> 55506.4 | H11: =SUM('Total Fuel per Operation (Rice)'!Y$47:Y$49) -> 75652 | I11: =SUM('Total Fuel per Operation (Rice)'!Z$47:Z$49) -> 244640 | ... M11: =SUM('Total Fuel per Operation (Rice)'!AD$47:AD$49) -> 100469.2 | N11: =SUM(B11:M11) -> 2220524.8 | O11: =$N11*AVERAGE('Assumptions&Calculations'!$B$3:$B$5) -> 1.4890099e+08 | P11: =$N11*AVERAGE('Assumptions&Calculations'!$M$3:$M$5) -> 58037645
A12: Region VII | B12: =SUM('Total Fuel per Operation (Rice)'!S$50:S$51) -> 0 | C12: =SUM('Total Fuel per Operation (Rice)'!T$50:T$51) -> 0 | D12: =SUM('Total Fuel per Operation (Rice)'!U$50:U$51) -> 0 | E12: =SUM('Total Fuel per Operation (Rice)'!V$50:V$51) -> 949928 | F12: =SUM('Total Fuel per Operation (Rice)'!W$50:W$51) -> 78517.8 | G12: =SUM('Total Fuel per Operation (Rice)'!X$50:X$51) -> 59955 | H12: =SUM('Total Fuel per Operation (Rice)'!Y$50:Y$51) -> 100768 | I12: =SUM('Total Fuel per Operation (Rice)'!Z$50:Z$51) -> 1220792 | ... M12: =SUM('Total Fuel per Operation (Rice)'!AD$50:AD$51) -> 270864 | N12: =SUM(B12:M12) -> 2920065.6 | O12: =$N12*AVERAGE('Assumptions&Calculations'!$B$3:$B$5) -> 1.9580987e+08 | P12: =$N12*AVERAGE('Assumptions&Calculations'!$M$3:$M$5) -> 76321476
A13: Region VIII | B13: =SUM('Total Fuel per Operation (Rice)'!S$52:S$57) -> 336891.6 | C13: =SUM('Total Fuel per Operation (Rice)'!T$52:T$57) -> 321509 | D13: =SUM('Total Fuel per Operation (Rice)'!U$52:U$57) -> 716912 | E13: =SUM('Total Fuel per Operation (Rice)'!V$52:V$57) -> 371632 | F13: =SUM('Total Fuel per Operation (Rice)'!W$52:W$57) -> 647048 | G13: =SUM('Total Fuel per Operation (Rice)'!X$52:X$57) -> 1205885.8 | H13: =SUM('Total Fuel per Operation (Rice)'!Y$52:Y$57) -> 336891.6 | I13: =SUM('Total Fuel per Operation (Rice)'!Z$52:Z$57) -> 321509 | ... M13: =SUM('Total Fuel per Operation (Rice)'!AD$52:AD$57) -> 1205885.8 | N13: =SUM(B13:M13) -> 7199756.8 | O13: =$N13*AVERAGE('Assumptions&Calculations'!$B$3:$B$5) -> 4.8279169e+08 | P13: =$N13*AVERAGE('Assumptions&Calculations'!$M$3:$M$5) -> 1.8817936e+08
A14: Region IX | B14: =SUM('Total Fuel per Operation (Rice)'!S$58:S$60) -> 432822 | C14: =SUM('Total Fuel per Operation (Rice)'!T$58:T$60) -> 493552 | D14: =SUM('Total Fuel per Operation (Rice)'!U$58:U$60) -> 87648 | E14: =SUM('Total Fuel per Operation (Rice)'!V$58:V$60) -> 0 | F14: =SUM('Total Fuel per Operation (Rice)'!W$58:W$60) -> 1148736 | G14: =SUM('Total Fuel per Operation (Rice)'!X$58:X$60) -> 127211.6 | H14: =SUM('Total Fuel per Operation (Rice)'!Y$58:Y$60) -> 77910 | I14: =SUM('Total Fuel per Operation (Rice)'!Z$58:Z$60) -> 778368 | ... M14: =SUM('Total Fuel per Operation (Rice)'!AD$58:AD$60) -> 93963.6 | N14: =SUM(B14:M14) -> 4640419.2 | O14: =$N14*AVERAGE('Assumptions&Calculations'!$B$3:$B$5) -> 3.1117104e+08 | P14: =$N14*AVERAGE('Assumptions&Calculations'!$M$3:$M$5) -> 1.2128619e+08
A15: Region X | B15: =SUM('Total Fuel per Operation (Rice)'!S$61:S$65) -> 1117885 | C15: =SUM('Total Fuel per Operation (Rice)'!T$61:T$65) -> 1319856 | D15: =SUM('Total Fuel per Operation (Rice)'!U$61:U$65) -> 77808 | E15: =SUM('Total Fuel per Operation (Rice)'!V$61:V$65) -> 0 | F15: =SUM('Total Fuel per Operation (Rice)'!W$61:W$65) -> 4431552 | G15: =SUM('Total Fuel per Operation (Rice)'!X$61:X$65) -> 465158.4 | H15: =SUM('Total Fuel per Operation (Rice)'!Y$61:Y$65) -> 364560 | I15: =SUM('Total Fuel per Operation (Rice)'!Z$61:Z$65) -> 2089216 | ... M15: =SUM('Total Fuel per Operation (Rice)'!AD$61:AD$65) -> 381981.2 | N15: =SUM(B15:M15) -> 15273709 | O15: =$N15*AVERAGE('Assumptions&Calculations'!$B$3:$B$5) -> 1.024204e+09 | P15: =$N15*AVERAGE('Assumptions&Calculations'!$M$3:$M$5) -> 3.9920747e+08
A16: Region XI | B16: =SUM('Total Fuel per Operation (Rice)'!S$66:S$70) -> 291183 | C16: =SUM('Total Fuel per Operation (Rice)'!T$66:T$70) -> 1008816 | D16: =SUM('Total Fuel per Operation (Rice)'!U$66:U$70) -> 101952 | E16: =SUM('Total Fuel per Operation (Rice)'!V$66:V$70) -> 1250440 | F16: =SUM('Total Fuel per Operation (Rice)'!W$66:W$70) -> 543789 | G16: =SUM('Total Fuel per Operation (Rice)'!X$66:X$70) -> 165475 | H16: =SUM('Total Fuel per Operation (Rice)'!Y$66:Y$70) -> 1003884 | I16: =SUM('Total Fuel per Operation (Rice)'!Z$66:Z$70) -> 262016 | ... M16: =SUM('Total Fuel per Operation (Rice)'!AD$66:AD$70) -> 184469 | N16: =SUM(B16:M16) -> 6991960 | O16: =$N16*AVERAGE('Assumptions&Calculations'!$B$3:$B$5) -> 4.6885753e+08 | P16: =$N16*AVERAGE('Assumptions&Calculations'!$M$3:$M$5) -> 1.8274819e+08
A17: Region XII | B17: =SUM('Total Fuel per Operation (Rice)'!S$71:S$74) -> 220872 | C17: =SUM('Total Fuel per Operation (Rice)'!T$71:T$74) -> 0 | D17: =SUM('Total Fuel per Operation (Rice)'!U$71:U$74) -> 0 | E17: =SUM('Total Fuel per Operation (Rice)'!V$71:V$74) -> 3871088 | F17: =SUM('Total Fuel per Operation (Rice)'!W$71:W$74) -> 484437.6 | G17: =SUM('Total Fuel per Operation (Rice)'!X$71:X$74) -> 665268 | H17: =SUM('Total Fuel per Operation (Rice)'!Y$71:Y$74) -> 2650304 | I17: =SUM('Total Fuel per Operation (Rice)'!Z$71:Z$74) -> 220872 | ... M17: =SUM('Total Fuel per Operation (Rice)'!AD$71:AD$74) -> 2650304 | N17: =SUM(B17:M17) -> 15783939 | O17: =$N17*AVERAGE('Assumptions&Calculations'!$B$3:$B$5) -> 1.0584183e+09 | P17: =$N17*AVERAGE('Assumptions&Calculations'!$M$3:$M$5) -> 4.1254332e+08
A18: Region XIII | B18: =SUM('Total Fuel per Operation (Rice)'!S$75:S$79) -> 1670895 | C18: =SUM('Total Fuel per Operation (Rice)'!T$75:T$79) -> 1597200 | D18: =SUM('Total Fuel per Operation (Rice)'!U$75:U$79) -> 146336 | E18: =SUM('Total Fuel per Operation (Rice)'!V$75:V$79) -> 0 | F18: =SUM('Total Fuel per Operation (Rice)'!W$75:W$79) -> 1020800 | G18: =SUM('Total Fuel per Operation (Rice)'!X$75:X$79) -> 1619582 | H18: =SUM('Total Fuel per Operation (Rice)'!Y$75:Y$79) -> 520883.4 | I18: =SUM('Total Fuel per Operation (Rice)'!Z$75:Z$79) -> 1501385 | ... M18: =SUM('Total Fuel per Operation (Rice)'!AD$75:AD$79) -> 511922.6 | N18: =SUM(B18:M18) -> 15741677 | O18: =$N18*AVERAGE('Assumptions&Calculations'!$B$3:$B$5) -> 1.0555844e+09 | P18: =$N18*AVERAGE('Assumptions&Calculations'!$M$3:$M$5) -> 4.1143871e+08
A19: BARMM | B19: =SUM('Total Fuel per Operation (Rice)'!S$80:S$82) -> 0 | C19: =SUM('Total Fuel per Operation (Rice)'!T$80:T$82) -> 0 | D19: =SUM('Total Fuel per Operation (Rice)'!U$80:U$82) -> 0 | E19: =SUM('Total Fuel per Operation (Rice)'!V$80:V$82) -> 0 | F19: =SUM('Total Fuel per Operation (Rice)'!W$80:W$82) -> 77440 | G19: =SUM('Total Fuel per Operation (Rice)'!X$80:X$82) -> 0 | H19: =SUM('Total Fuel per Operation (Rice)'!Y$80:Y$82) -> 0 | I19: =SUM('Total Fuel per Operation (Rice)'!Z$80:Z$82) -> 77440 | ... M19: =SUM('Total Fuel per Operation (Rice)'!AD$80:AD$82) -> 2640 | N19: =SUM(B19:M19) -> 157520 | O19: =$N19*AVERAGE('Assumptions&Calculations'!$B$3:$B$5) -> 10562766 | P19: =$N19*AVERAGE('Assumptions&Calculations'!$M$3:$M$5) -> 4117085.2
A20: Total per Month | B20: =SUM(B3:B19) -> 17368820 | C20: =SUM(C3:C19) -> 15188460 | D20: =SUM(D3:D19) -> 14399143 | E20: =SUM(E3:E19) -> 9275294 | F20: =SUM(F3:F19) -> 23778265 | G20: =SUM(G3:G19) -> 28360518 | H20: =SUM(H3:H19) -> 16037039 | I20: =SUM(I3:I19) -> 15621045 | ... N20: =SUM(N3:N19) -> 237948411 | O20: =$N20*AVERAGE('Assumptions&Calculations'!$B$3:$B$5) -> 1.5956027e+10 | P20: =$N20*AVERAGE('Assumptions&Calculations'!$M$3:$M$5) -> 6.219235e+09
A22: CORN | B22: January | C22: February | D22: March | E22: April | F22: May | G22: June | H22: July | I22: August | J22: September | K22: October | L22: November | M22: December | N22: Total Fuel (L) Per Region | O22: Cost (Php) Per Region @ average fuel cost | P22: Cost (Php) Per Region @ incremental cost
A23: CAR | B23: =SUM('Total Fuel per Operation (Corn)'!H$4:H$9) -> 626912 | C23: =SUM('Total Fuel per Operation (Corn)'!I$4:I$9) -> 1312432 | D23: =SUM('Total Fuel per Operation (Corn)'!J$4:J$9) -> 0 | E23: =SUM('Total Fuel per Operation (Corn)'!K$4:K$9) -> 1315200 | F23: =SUM('Total Fuel per Operation (Corn)'!L$4:L$9) -> 404272 | G23: =SUM('Total Fuel per Operation (Corn)'!M$4:M$9) -> 0 | H23: =SUM('Total Fuel per Operation (Corn)'!N$4:N$9) -> 1160672 | I23: =SUM('Total Fuel per Operation (Corn)'!O$4:O$9) -> 0 | ... M23: =SUM('Total Fuel per Operation (Corn)'!S$4:S$9) -> 0 | N23: =SUM(B23:M23) -> 6509088 | O23: =$N23*AVERAGE('Assumptions&Calculations'!$B$3:$B$5) -> 4.3647774e+08 | P23: =$N23*AVERAGE('Assumptions&Calculations'!$M$3:$M$5) -> 1.7012741e+08
A24: Region I | B24: =SUM('Total Fuel per Operation (Corn)'!H$10:H$13) -> 0 | C24: =SUM('Total Fuel per Operation (Corn)'!I$10:I$13) -> 12398400 | D24: =SUM('Total Fuel per Operation (Corn)'!J$10:J$13) -> 0 | E24: =SUM('Total Fuel per Operation (Corn)'!K$10:K$13) -> 0 | F24: =SUM('Total Fuel per Operation (Corn)'!L$10:L$13) -> 1089760 | G24: =SUM('Total Fuel per Operation (Corn)'!M$10:M$13) -> 1478400 | H24: =SUM('Total Fuel per Operation (Corn)'!N$10:N$13) -> 1920000 | I24: =SUM('Total Fuel per Operation (Corn)'!O$10:O$13) -> 9000000 | ... M24: =SUM('Total Fuel per Operation (Corn)'!S$10:S$13) -> 0 | N24: =SUM(B24:M24) -> 26976320 | O24: =$N24*AVERAGE('Assumptions&Calculations'!$B$3:$B$5) -> 1.8089421e+09 | P24: =$N24*AVERAGE('Assumptions&Calculations'!$M$3:$M$5) -> 7.0507751e+08
A25: Region II | B25: =SUM('Total Fuel per Operation (Corn)'!H$14:H$18) -> 3379584 | C25: =SUM('Total Fuel per Operation (Corn)'!I$14:I$18) -> 0 | D25: =SUM('Total Fuel per Operation (Corn)'!J$14:J$18) -> 0 | E25: =SUM('Total Fuel per Operation (Corn)'!K$14:K$18) -> 16008000 | F25: =SUM('Total Fuel per Operation (Corn)'!L$14:L$18) -> 0 | G25: =SUM('Total Fuel per Operation (Corn)'!M$14:M$18) -> 0 | H25: =SUM('Total Fuel per Operation (Corn)'!N$14:N$18) -> 3379584 | I25: =SUM('Total Fuel per Operation (Corn)'!O$14:O$18) -> 0 | ... M25: =SUM('Total Fuel per Operation (Corn)'!S$14:S$18) -> 0 | N25: =SUM(B25:M25) -> 38775168 | O25: =$N25*AVERAGE('Assumptions&Calculations'!$B$3:$B$5) -> 2.6001335e+09 | P25: =$N25*AVERAGE('Assumptions&Calculations'!$M$3:$M$5) -> 1.0134629e+09
A26: Region III | B26: =SUM('Total Fuel per Operation (Corn)'!H$19:H$25) -> 1202800 | C26: =SUM('Total Fuel per Operation (Corn)'!I$19:I$25) -> 0 | D26: =SUM('Total Fuel per Operation (Corn)'!J$19:J$25) -> 5366400 | E26: =SUM('Total Fuel per Operation (Corn)'!K$19:K$25) -> 470400 | F26: =SUM('Total Fuel per Operation (Corn)'!L$19:L$25) -> 0 | G26: =SUM('Total Fuel per Operation (Corn)'!M$19:M$25) -> 1006304 | H26: =SUM('Total Fuel per Operation (Corn)'!N$19:N$25) -> 196496 | I26: =SUM('Total Fuel per Operation (Corn)'!O$19:O$25) -> 0 | ... M26: =SUM('Total Fuel per Operation (Corn)'!S$19:S$25) -> 0 | N26: =SUM(B26:M26) -> 14079200 | O26: =$N26*AVERAGE('Assumptions&Calculations'!$B$3:$B$5) -> 9.4410422e+08 | P26: =$N26*AVERAGE('Assumptions&Calculations'!$M$3:$M$5) -> 3.6798671e+08
A27: CALABARZON | B27: =SUM('Total Fuel per Operation (Corn)'!H$26:H$30) -> 845760 | C27: =SUM('Total Fuel per Operation (Corn)'!I$26:I$30) -> 0 | D27: =SUM('Total Fuel per Operation (Corn)'!J$26:J$30) -> 0 | E27: =SUM('Total Fuel per Operation (Corn)'!K$26:K$30) -> 0 | F27: =SUM('Total Fuel per Operation (Corn)'!L$26:L$30) -> 2529600 | G27: =SUM('Total Fuel per Operation (Corn)'!M$26:M$30) -> 0 | H27: =SUM('Total Fuel per Operation (Corn)'!N$26:N$30) -> 0 | I27: =SUM('Total Fuel per Operation (Corn)'!O$26:O$30) -> 845760 | ... M27: =SUM('Total Fuel per Operation (Corn)'!S$26:S$30) -> 0 | N27: =SUM(B27:M27) -> 6750720 | O27: =$N27*AVERAGE('Assumptions&Calculations'!$B$3:$B$5) -> 4.5268078e+08 | P27: =$N27*AVERAGE('Assumptions&Calculations'!$M$3:$M$5) -> 1.7644293e+08
A28: MIMAROPA | B28: =SUM('Total Fuel per Operation (Corn)'!H$31:H$35) -> 0 | C28: =SUM('Total Fuel per Operation (Corn)'!I$31:I$35) -> 0 | D28: =SUM('Total Fuel per Operation (Corn)'!J$31:J$35) -> 0 | E28: =SUM('Total Fuel per Operation (Corn)'!K$31:K$35) -> 0 | F28: =SUM('Total Fuel per Operation (Corn)'!L$31:L$35) -> 2928000 | G28: =SUM('Total Fuel per Operation (Corn)'!M$31:M$35) -> 0 | H28: =SUM('Total Fuel per Operation (Corn)'!N$31:N$35) -> 0 | I28: =SUM('Total Fuel per Operation (Corn)'!O$31:O$35) -> 1363440 | ... M28: =SUM('Total Fuel per Operation (Corn)'!S$31:S$35) -> 1363440 | N28: =SUM(B28:M28) -> 8582880 | O28: =$N28*AVERAGE('Assumptions&Calculations'!$B$3:$B$5) -> 5.7553932e+08 | P28: =$N28*AVERAGE('Assumptions&Calculations'!$M$3:$M$5) -> 2.2432992e+08
A29: Region V | B29: =SUM('Total Fuel per Operation (Corn)'!H$36:H$41) -> 2510400 | C29: =SUM('Total Fuel per Operation (Corn)'!I$36:I$41) -> 0 | D29: =SUM('Total Fuel per Operation (Corn)'!J$36:J$41) -> 0 | E29: =SUM('Total Fuel per Operation (Corn)'!K$36:K$41) -> 1645872 | F29: =SUM('Total Fuel per Operation (Corn)'!L$36:L$41) -> 681600 | G29: =SUM('Total Fuel per Operation (Corn)'!M$36:M$41) -> 0 | H29: =SUM('Total Fuel per Operation (Corn)'!N$36:N$41) -> 1259472 | I29: =SUM('Total Fuel per Operation (Corn)'!O$36:O$41) -> 290400 | ... M29: =SUM('Total Fuel per Operation (Corn)'!S$36:S$41) -> 0 | N29: =SUM(B29:M29) -> 6387744 | O29: =$N29*AVERAGE('Assumptions&Calculations'!$B$3:$B$5) -> 4.2834082e+08 | P29: =$N29*AVERAGE('Assumptions&Calculations'!$M$3:$M$5) -> 1.6695586e+08
A30: Region VI | B30: =SUM('Total Fuel per Operation (Corn)'!H$42:H$46) -> 1404336 | C30: =SUM('Total Fuel per Operation (Corn)'!I$42:I$46) -> 0 | D30: =SUM('Total Fuel per Operation (Corn)'!J$42:J$46) -> 0 | E30: =SUM('Total Fuel per Operation (Corn)'!K$42:K$46) -> 1291200 | F30: =SUM('Total Fuel per Operation (Corn)'!L$42:L$46) -> 0 | G30: =SUM('Total Fuel per Operation (Corn)'!M$42:M$46) -> 0 | H30: =SUM('Total Fuel per Operation (Corn)'!N$42:N$46) -> 1404336 | I30: =SUM('Total Fuel per Operation (Corn)'!O$42:O$46) -> 0 | ... M30: =SUM('Total Fuel per Operation (Corn)'!S$42:S$46) -> 0 | N30: =SUM(B30:M30) -> 5391072 | O30: =$N30*AVERAGE('Assumptions&Calculations'!$B$3:$B$5) -> 3.6150732e+08 | P30: =$N30*AVERAGE('Assumptions&Calculations'!$M$3:$M$5) -> 1.4090594e+08
A31: NIR | B31: =SUM('Total Fuel per Operation (Corn)'!H$47:H$49) -> 400352 | C31: =SUM('Total Fuel per Operation (Corn)'!I$47:I$49) -> 0 | D31: =SUM('Total Fuel per Operation (Corn)'!J$47:J$49) -> 0 | E31: =SUM('Total Fuel per Operation (Corn)'!K$47:K$49) -> 705600 | F31: =SUM('Total Fuel per Operation (Corn)'!L$47:L$49) -> 0 | G31: =SUM('Total Fuel per Operation (Corn)'!M$47:M$49) -> 0 | H31: =SUM('Total Fuel per Operation (Corn)'!N$47:N$49) -> 400352 | I31: =SUM('Total Fuel per Operation (Corn)'!O$47:O$49) -> 0 | ... M31: =SUM('Total Fuel per Operation (Corn)'!S$47:S$49) -> 0 | N31: =SUM(B31:M31) -> 2211904 | O31: =$N31*AVERAGE('Assumptions&Calculations'!$B$3:$B$5) -> 1.4832291e+08 | P31: =$N31*AVERAGE('Assumptions&Calculations'!$M$3:$M$5) -> 57812324
A32: Region VII | B32: =SUM('Total Fuel per Operation (Corn)'!H$50:H$51) -> 0 | C32: =SUM('Total Fuel per Operation (Corn)'!I$50:I$51) -> 0 | D32: =SUM('Total Fuel per Operation (Corn)'!J$50:J$51) -> 0 | E32: =SUM('Total Fuel per Operation (Corn)'!K$50:K$51) -> 912000 | F32: =SUM('Total Fuel per Operation (Corn)'!L$50:L$51) -> 0 | G32: =SUM('Total Fuel per Operation (Corn)'!M$50:M$51) -> 0 | H32: =SUM('Total Fuel per Operation (Corn)'!N$50:N$51) -> 391520 | I32: =SUM('Total Fuel per Operation (Corn)'!O$50:O$51) -> 0 | ... M32: =SUM('Total Fuel per Operation (Corn)'!S$50:S$51) -> 391520 | N32: =SUM(B32:M32) -> 2607040 | O32: =$N32*AVERAGE('Assumptions&Calculations'!$B$3:$B$5) -> 1.7481941e+08 | P32: =$N32*AVERAGE('Assumptions&Calculations'!$M$3:$M$5) -> 68139956
A33: Region VIII | B33: =SUM('Total Fuel per Operation (Corn)'!H$52:H$57) -> 488304 | C33: =SUM('Total Fuel per Operation (Corn)'!I$52:I$57) -> 0 | D33: =SUM('Total Fuel per Operation (Corn)'!J$52:J$57) -> 0 | E33: =SUM('Total Fuel per Operation (Corn)'!K$52:K$57) -> 1051200 | F33: =SUM('Total Fuel per Operation (Corn)'!L$52:L$57) -> 0 | G33: =SUM('Total Fuel per Operation (Corn)'!M$52:M$57) -> 0 | H33: =SUM('Total Fuel per Operation (Corn)'!N$52:N$57) -> 488304 | I33: =SUM('Total Fuel per Operation (Corn)'!O$52:O$57) -> 0 | ... M33: =SUM('Total Fuel per Operation (Corn)'!S$52:S$57) -> 0 | N33: =SUM(B33:M33) -> 3079008 | O33: =$N33*AVERAGE('Assumptions&Calculations'!$B$3:$B$5) -> 2.0646801e+08 | P33: =$N33*AVERAGE('Assumptions&Calculations'!$M$3:$M$5) -> 80475739
A34: Region IX | B34: =SUM('Total Fuel per Operation (Corn)'!H$58:H$60) -> 0 | C34: =SUM('Total Fuel per Operation (Corn)'!I$58:I$60) -> 1051200 | D34: =SUM('Total Fuel per Operation (Corn)'!J$58:J$60) -> 211200 | E34: =SUM('Total Fuel per Operation (Corn)'!K$58:K$60) -> 0 | F34: =SUM('Total Fuel per Operation (Corn)'!L$58:L$60) -> 792432 | G34: =SUM('Total Fuel per Operation (Corn)'!M$58:M$60) -> 96576 | H34: =SUM('Total Fuel per Operation (Corn)'!N$58:N$60) -> 0 | I34: =SUM('Total Fuel per Operation (Corn)'!O$58:O$60) -> 1051200 | ... M34: =SUM('Total Fuel per Operation (Corn)'!S$58:S$60) -> 96576 | N34: =SUM(B34:M34) -> 4302816 | O34: =$N34*AVERAGE('Assumptions&Calculations'!$B$3:$B$5) -> 2.885325e+08 | P34: =$N34*AVERAGE('Assumptions&Calculations'!$M$3:$M$5) -> 1.1246229e+08
A35: Region X | B35: =SUM('Total Fuel per Operation (Corn)'!H$61:H$65) -> 1266560 | C35: =SUM('Total Fuel per Operation (Corn)'!I$61:I$65) -> 6413648 | D35: =SUM('Total Fuel per Operation (Corn)'!J$61:J$65) -> 0 | E35: =SUM('Total Fuel per Operation (Corn)'!K$61:K$65) -> 0 | F35: =SUM('Total Fuel per Operation (Corn)'!L$61:L$65) -> 2501008 | G35: =SUM('Total Fuel per Operation (Corn)'!M$61:M$65) -> 0 | H35: =SUM('Total Fuel per Operation (Corn)'!N$61:N$65) -> 0 | I35: =SUM('Total Fuel per Operation (Corn)'!O$61:O$65) -> 0 | ... M35: =SUM('Total Fuel per Operation (Corn)'!S$61:S$65) -> 0 | N35: =SUM(B35:M35) -> 15360416 | O35: =$N35*AVERAGE('Assumptions&Calculations'!$B$3:$B$5) -> 1.0300183e+09 | P35: =$N35*AVERAGE('Assumptions&Calculations'!$M$3:$M$5) -> 4.0147373e+08
A36: Region XI | B36: =SUM('Total Fuel per Operation (Corn)'!H$66:H$70) -> 1756800 | C36: =SUM('Total Fuel per Operation (Corn)'!I$66:I$70) -> 0 | D36: =SUM('Total Fuel per Operation (Corn)'!J$66:J$70) -> 0 | E36: =SUM('Total Fuel per Operation (Corn)'!K$66:K$70) -> 895616 | F36: =SUM('Total Fuel per Operation (Corn)'!L$66:L$70) -> 0 | G36: =SUM('Total Fuel per Operation (Corn)'!M$66:M$70) -> 0 | H36: =SUM('Total Fuel per Operation (Corn)'!N$66:N$70) -> 1756800 | I36: =SUM('Total Fuel per Operation (Corn)'!O$66:O$70) -> 0 | ... M36: =SUM('Total Fuel per Operation (Corn)'!S$66:S$70) -> 0 | N36: =SUM(B36:M36) -> 5304832 | O36: =$N36*AVERAGE('Assumptions&Calculations'!$B$3:$B$5) -> 3.5572435e+08 | P36: =$N36*AVERAGE('Assumptions&Calculations'!$M$3:$M$5) -> 1.3865189e+08
A37: Region XII | B37: =SUM('Total Fuel per Operation (Corn)'!H$71:H$74) -> 0 | C37: =SUM('Total Fuel per Operation (Corn)'!I$71:I$74) -> 0 | D37: =SUM('Total Fuel per Operation (Corn)'!J$71:J$74) -> 0 | E37: =SUM('Total Fuel per Operation (Corn)'!K$71:K$74) -> 4219200 | F37: =SUM('Total Fuel per Operation (Corn)'!L$71:L$74) -> 0 | G37: =SUM('Total Fuel per Operation (Corn)'!M$71:M$74) -> 0 | H37: =SUM('Total Fuel per Operation (Corn)'!N$71:N$74) -> 2405584 | I37: =SUM('Total Fuel per Operation (Corn)'!O$71:O$74) -> 0 | ... M37: =SUM('Total Fuel per Operation (Corn)'!S$71:S$74) -> 2405584 | N37: =SUM(B37:M37) -> 13249568 | O37: =$N37*AVERAGE('Assumptions&Calculations'!$B$3:$B$5) -> 8.8847186e+08 | P37: =$N37*AVERAGE('Assumptions&Calculations'!$M$3:$M$5) -> 3.463027e+08
A38: Region XIII | B38: =SUM('Total Fuel per Operation (Corn)'!H$75:H$79) -> 0 | C38: =SUM('Total Fuel per Operation (Corn)'!I$75:I$79) -> 763456 | D38: =SUM('Total Fuel per Operation (Corn)'!J$75:J$79) -> 0 | E38: =SUM('Total Fuel per Operation (Corn)'!K$75:K$79) -> 0 | F38: =SUM('Total Fuel per Operation (Corn)'!L$75:L$79) -> 2112000 | G38: =SUM('Total Fuel per Operation (Corn)'!M$75:M$79) -> 0 | H38: =SUM('Total Fuel per Operation (Corn)'!N$75:N$79) -> 0 | I38: =SUM('Total Fuel per Operation (Corn)'!O$75:O$79) -> 763456 | ... M38: =SUM('Total Fuel per Operation (Corn)'!S$75:S$79) -> 0 | N38: =SUM(B38:M38) -> 5750912 | O38: =$N38*AVERAGE('Assumptions&Calculations'!$B$3:$B$5) -> 3.8563699e+08 | P38: =$N38*AVERAGE('Assumptions&Calculations'!$M$3:$M$5) -> 1.5031104e+08
A39: BARMM | B39: =SUM('Total Fuel per Operation (Corn)'!H$80:H$82) -> 0 | C39: =SUM('Total Fuel per Operation (Corn)'!I$80:I$82) -> 0 | D39: =SUM('Total Fuel per Operation (Corn)'!J$80:J$82) -> 120000 | E39: =SUM('Total Fuel per Operation (Corn)'!K$80:K$82) -> 31152 | F39: =SUM('Total Fuel per Operation (Corn)'!L$80:L$82) -> 0 | G39: =SUM('Total Fuel per Operation (Corn)'!M$80:M$82) -> 0 | H39: =SUM('Total Fuel per Operation (Corn)'!N$80:N$82) -> 120000 | I39: =SUM('Total Fuel per Operation (Corn)'!O$80:O$82) -> 0 | ... M39: =SUM('Total Fuel per Operation (Corn)'!S$80:S$82) -> 151152 | N39: =SUM(B39:M39) -> 453456 | O39: =$N39*AVERAGE('Assumptions&Calculations'!$B$3:$B$5) -> 30407248 | P39: =$N39*AVERAGE('Assumptions&Calculations'!$M$3:$M$5) -> 11851936
A40: Total per Month | B40: =SUM(B23:B39) -> 13881808 | C40: =SUM(C23:C39) -> 21939136 | D40: =SUM(D23:D39) -> 5697600 | E40: =SUM(E23:E39) -> 28545440 | F40: =SUM(F23:F39) -> 13038672 | G40: =SUM(G23:G39) -> 2581280 | H40: =SUM(H23:H39) -> 14883120 | I40: =SUM(I23:I39) -> 13314256 | ... N40: =SUM(N23:N39) -> 165772144 | O40: =N40*AVERAGE('Assumptions&Calculations'!$B$3:$B$5) -> 1.1116127e+10 | P40: =$N40*AVERAGE('Assumptions&Calculations'!$M$3:$M$5) -> 4.3327707e+09
A42: HVC | B42: January | C42: February | D42: March | E42: April | F42: May | G42: June | H42: July | I42: August | J42: September | K42: October | L42: November | M42: December | N42: Total Fuel (L) Per Region | O42: Cost (Php) Per Region @ average fuel cost | P42: Cost (Php) Per Region @ incremental cost
A43: CAR | B43: =SUM('Total Fuel per Operation (HVC)'!L$4:L$9) -> 139410 | C43: =SUM('Total Fuel per Operation (HVC)'!M$4:M$9) -> 0 | D43: =SUM('Total Fuel per Operation (HVC)'!N$4:N$9) -> 0 | E43: =SUM('Total Fuel per Operation (HVC)'!O$4:O$9) -> 0 | F43: =SUM('Total Fuel per Operation (HVC)'!P$4:P$9) -> 258862 | G43: =SUM('Total Fuel per Operation (HVC)'!Q$4:Q$9) -> 153472 | H43: =SUM('Total Fuel per Operation (HVC)'!R$4:R$9) -> 139410 | I43: =SUM('Total Fuel per Operation (HVC)'!S$4:S$9) -> 0 | ... M43: =SUM('Total Fuel per Operation (HVC)'!W$4:W$9) -> 153472 | N43: =SUM(B43:M43) -> 1158637 | O43: =$N43*AVERAGE('Assumptions&Calculations'!$B$3:$B$5) -> 77694335 | P43: =$N43*AVERAGE('Assumptions&Calculations'!$M$3:$M$5) -> 30283185
A44: Region I | B44: =SUM('Total Fuel per Operation (HVC)'!L$10:L$13) -> 0 | C44: =SUM('Total Fuel per Operation (HVC)'!M$10:M$13) -> 0 | D44: =SUM('Total Fuel per Operation (HVC)'!N$10:N$13) -> 0 | E44: =SUM('Total Fuel per Operation (HVC)'!O$10:O$13) -> 0 | F44: =SUM('Total Fuel per Operation (HVC)'!P$10:P$13) -> 498706 | G44: =SUM('Total Fuel per Operation (HVC)'!Q$10:Q$13) -> 373696 | H44: =SUM('Total Fuel per Operation (HVC)'!R$10:R$13) -> 176670 | I44: =SUM('Total Fuel per Operation (HVC)'!S$10:S$13) -> 0 | ... M44: =SUM('Total Fuel per Operation (HVC)'!W$10:W$13) -> 176670 | N44: =SUM(B44:M44) -> 2098144 | O44: =$N44*AVERAGE('Assumptions&Calculations'!$B$3:$B$5) -> 1.4069454e+08 | P44: =$N44*AVERAGE('Assumptions&Calculations'!$M$3:$M$5) -> 54838990
A45: Region II | B45: =SUM('Total Fuel per Operation (HVC)'!L$14:L$18) -> 608746 | C45: =SUM('Total Fuel per Operation (HVC)'!M$14:M$18) -> 15616 | D45: =SUM('Total Fuel per Operation (HVC)'!N$14:N$18) -> 4374526 | E45: =SUM('Total Fuel per Operation (HVC)'!O$14:O$18) -> 15616 | F45: =SUM('Total Fuel per Operation (HVC)'!P$14:P$18) -> 3765780 | G45: =SUM('Total Fuel per Operation (HVC)'!Q$14:Q$18) -> 608746 | H45: =SUM('Total Fuel per Operation (HVC)'!R$14:R$18) -> 15616 | I45: =SUM('Total Fuel per Operation (HVC)'!S$14:S$18) -> 3765780 | ... M45: =SUM('Total Fuel per Operation (HVC)'!W$14:W$18) -> 3765780 | N45: =SUM(B45:M45) -> 17560568 | O45: =$N45*AVERAGE('Assumptions&Calculations'!$B$3:$B$5) -> 1.1775532e+09 | P45: =$N45*AVERAGE('Assumptions&Calculations'!$M$3:$M$5) -> 4.5897889e+08
A46: Region III | B46: =SUM('Total Fuel per Operation (HVC)'!L$19:L$25) -> 92241 | C46: =SUM('Total Fuel per Operation (HVC)'!M$19:M$25) -> 69696 | D46: =SUM('Total Fuel per Operation (HVC)'!N$19:N$25) -> 75501 | E46: =SUM('Total Fuel per Operation (HVC)'!O$19:O$25) -> 69696 | F46: =SUM('Total Fuel per Operation (HVC)'!P$19:P$25) -> 519893 | G46: =SUM('Total Fuel per Operation (HVC)'!Q$19:Q$25) -> 559364 | H46: =SUM('Total Fuel per Operation (HVC)'!R$19:R$25) -> 155196 | I46: =SUM('Total Fuel per Operation (HVC)'!S$19:S$25) -> 2025 | ... M46: =SUM('Total Fuel per Operation (HVC)'!W$19:W$25) -> 165336 | N46: =SUM(B46:M46) -> 2759300 | O46: =$N46*AVERAGE('Assumptions&Calculations'!$B$3:$B$5) -> 1.8502946e+08 | P46: =$N46*AVERAGE('Assumptions&Calculations'!$M$3:$M$5) -> 72119561
A47: CALABARZON | B47: =SUM('Total Fuel per Operation (HVC)'!L$26:L$30) -> 417030 | C47: =SUM('Total Fuel per Operation (HVC)'!M$26:M$30) -> 305280 | D47: =SUM('Total Fuel per Operation (HVC)'!N$26:N$30) -> 441150 | E47: =SUM('Total Fuel per Operation (HVC)'!O$26:O$30) -> 305280 | F47: =SUM('Total Fuel per Operation (HVC)'!P$26:P$30) -> 641242 | G47: =SUM('Total Fuel per Operation (HVC)'!Q$26:Q$30) -> 811552 | H47: =SUM('Total Fuel per Operation (HVC)'!R$26:R$30) -> 470700 | I47: =SUM('Total Fuel per Operation (HVC)'!S$26:S$30) -> 113310 | ... M47: =SUM('Total Fuel per Operation (HVC)'!W$26:W$30) -> 508580 | N47: =SUM(B47:M47) -> 5339848 | O47: =$N47*AVERAGE('Assumptions&Calculations'!$B$3:$B$5) -> 3.5807241e+08 | P47: =$N47*AVERAGE('Assumptions&Calculations'!$M$3:$M$5) -> 1.395671e+08
A48: MIMAROPA | B48: =SUM('Total Fuel per Operation (HVC)'!L$31:L$35) -> 110475 | C48: =SUM('Total Fuel per Operation (HVC)'!M$31:M$35) -> 0 | D48: =SUM('Total Fuel per Operation (HVC)'!N$31:N$35) -> 0 | E48: =SUM('Total Fuel per Operation (HVC)'!O$31:O$35) -> 0 | F48: =SUM('Total Fuel per Operation (HVC)'!P$31:P$35) -> 64130 | G48: =SUM('Total Fuel per Operation (HVC)'!Q$31:Q$35) -> 1280 | H48: =SUM('Total Fuel per Operation (HVC)'!R$31:R$35) -> 203625 | I48: =SUM('Total Fuel per Operation (HVC)'!S$31:S$35) -> 0 | ... M48: =SUM('Total Fuel per Operation (HVC)'!W$31:W$35) -> 94430 | N48: =SUM(B48:M48) -> 538070 | O48: =$N48*AVERAGE('Assumptions&Calculations'!$B$3:$B$5) -> 36081181 | P48: =$N48*AVERAGE('Assumptions&Calculations'!$M$3:$M$5) -> 14063484
A49: Region V | B49: =SUM('Total Fuel per Operation (HVC)'!L$36:L$41) -> 202959 | C49: =SUM('Total Fuel per Operation (HVC)'!M$36:M$41) -> 50304 | D49: =SUM('Total Fuel per Operation (HVC)'!N$36:N$41) -> 106254 | E49: =SUM('Total Fuel per Operation (HVC)'!O$36:O$41) -> 50304 | F49: =SUM('Total Fuel per Operation (HVC)'!P$36:P$41) -> 201738 | G49: =SUM('Total Fuel per Operation (HVC)'!Q$36:Q$41) -> 198432 | H49: =SUM('Total Fuel per Operation (HVC)'!R$36:R$41) -> 197679 | I49: =SUM('Total Fuel per Operation (HVC)'!S$36:S$41) -> 50670 | ... M49: =SUM('Total Fuel per Operation (HVC)'!W$36:W$41) -> 193518 | N49: =SUM(B49:M49) -> 1902227 | O49: =$N49*AVERAGE('Assumptions&Calculations'!$B$3:$B$5) -> 1.27557e+08 | P49: =$N49*AVERAGE('Assumptions&Calculations'!$M$3:$M$5) -> 49718326
A50: Region VI | B50: =SUM('Total Fuel per Operation (HVC)'!L$42:L$46) -> 86940 | C50: =SUM('Total Fuel per Operation (HVC)'!M$42:M$46) -> 0 | D50: =SUM('Total Fuel per Operation (HVC)'!N$42:N$46) -> 0 | E50: =SUM('Total Fuel per Operation (HVC)'!O$42:O$46) -> 0 | F50: =SUM('Total Fuel per Operation (HVC)'!P$42:P$46) -> 43882 | G50: =SUM('Total Fuel per Operation (HVC)'!Q$42:Q$46) -> 22144 | H50: =SUM('Total Fuel per Operation (HVC)'!R$42:R$46) -> 196200 | I50: =SUM('Total Fuel per Operation (HVC)'!S$42:S$46) -> 0 | ... M50: =SUM('Total Fuel per Operation (HVC)'!W$42:W$46) -> 118924 | N50: =SUM(B50:M50) -> 578794 | O50: =$N50*AVERAGE('Assumptions&Calculations'!$B$3:$B$5) -> 38811996 | P50: =$N50*AVERAGE('Assumptions&Calculations'!$M$3:$M$5) -> 15127884
A51: NIR | B51: =SUM('Total Fuel per Operation (HVC)'!L$47:L$49) -> 351990 | C51: =SUM('Total Fuel per Operation (HVC)'!M$47:M$49) -> 0 | D51: =SUM('Total Fuel per Operation (HVC)'!N$47:N$49) -> 0 | E51: =SUM('Total Fuel per Operation (HVC)'!O$47:O$49) -> 0 | F51: =SUM('Total Fuel per Operation (HVC)'!P$47:P$49) -> 66952 | G51: =SUM('Total Fuel per Operation (HVC)'!Q$47:Q$49) -> 44992 | H51: =SUM('Total Fuel per Operation (HVC)'!R$47:R$49) -> 351990 | I51: =SUM('Total Fuel per Operation (HVC)'!S$47:S$49) -> 0 | ... M51: =SUM('Total Fuel per Operation (HVC)'!W$47:W$49) -> 44992 | N51: =SUM(B51:M51) -> 1316248 | O51: =$N51*AVERAGE('Assumptions&Calculations'!$B$3:$B$5) -> 88263203 | P51: =$N51*AVERAGE('Assumptions&Calculations'!$M$3:$M$5) -> 34402649
A52: Region VII | B52: =SUM('Total Fuel per Operation (HVC)'!L$50:L$51) -> 275130 | C52: =SUM('Total Fuel per Operation (HVC)'!M$50:M$51) -> 0 | D52: =SUM('Total Fuel per Operation (HVC)'!N$50:N$51) -> 0 | E52: =SUM('Total Fuel per Operation (HVC)'!O$50:O$51) -> 0 | F52: =SUM('Total Fuel per Operation (HVC)'!P$50:P$51) -> 38488 | G52: =SUM('Total Fuel per Operation (HVC)'!Q$50:Q$51) -> 20608 | H52: =SUM('Total Fuel per Operation (HVC)'!R$50:R$51) -> 275130 | I52: =SUM('Total Fuel per Operation (HVC)'!S$50:S$51) -> 0 | ... M52: =SUM('Total Fuel per Operation (HVC)'!W$50:W$51) -> 20608 | N52: =SUM(B52:M52) -> 698126 | O52: =$N52*AVERAGE('Assumptions&Calculations'!$B$3:$B$5) -> 46814002 | P52: =$N52*AVERAGE('Assumptions&Calculations'!$M$3:$M$5) -> 18246853
A53: Region VIII | B53: =SUM('Total Fuel per Operation (HVC)'!L$52:L$57) -> 284332 | C53: =SUM('Total Fuel per Operation (HVC)'!M$52:M$57) -> 19072 | D53: =SUM('Total Fuel per Operation (HVC)'!N$52:N$57) -> 207607 | E53: =SUM('Total Fuel per Operation (HVC)'!O$52:O$57) -> 19072 | F53: =SUM('Total Fuel per Operation (HVC)'!P$52:P$57) -> 229495 | G53: =SUM('Total Fuel per Operation (HVC)'!Q$52:Q$57) -> 61772 | H53: =SUM('Total Fuel per Operation (HVC)'!R$52:R$57) -> 268192 | I53: =SUM('Total Fuel per Operation (HVC)'!S$52:S$57) -> 172395 | ... M53: =SUM('Total Fuel per Operation (HVC)'!W$52:W$57) -> 198955 | N53: =SUM(B53:M53) -> 1905056 | O53: =$N53*AVERAGE('Assumptions&Calculations'!$B$3:$B$5) -> 1.2774671e+08 | P53: =$N53*AVERAGE('Assumptions&Calculations'!$M$3:$M$5) -> 49792267
A54: Region IX | B54: =SUM('Total Fuel per Operation (HVC)'!L$58:L$60) -> 140175 | C54: =SUM('Total Fuel per Operation (HVC)'!M$58:M$60) -> 0 | D54: =SUM('Total Fuel per Operation (HVC)'!N$58:N$60) -> 0 | E54: =SUM('Total Fuel per Operation (HVC)'!O$58:O$60) -> 0 | F54: =SUM('Total Fuel per Operation (HVC)'!P$58:P$60) -> 101172 | G54: =SUM('Total Fuel per Operation (HVC)'!Q$58:Q$60) -> 44352 | H54: =SUM('Total Fuel per Operation (HVC)'!R$58:R$60) -> 140175 | I54: =SUM('Total Fuel per Operation (HVC)'!S$58:S$60) -> 0 | ... M54: =SUM('Total Fuel per Operation (HVC)'!W$58:W$60) -> 44352 | N54: =SUM(B54:M54) -> 676647 | O54: =$N54*AVERAGE('Assumptions&Calculations'!$B$3:$B$5) -> 45373692 | P54: =$N54*AVERAGE('Assumptions&Calculations'!$M$3:$M$5) -> 17685458
A55: Region X | B55: =SUM('Total Fuel per Operation (HVC)'!L$61:L$65) -> 442935 | C55: =SUM('Total Fuel per Operation (HVC)'!M$61:M$65) -> 0 | D55: =SUM('Total Fuel per Operation (HVC)'!N$61:N$65) -> 0 | E55: =SUM('Total Fuel per Operation (HVC)'!O$61:O$65) -> 0 | F55: =SUM('Total Fuel per Operation (HVC)'!P$61:P$65) -> 140992 | G55: =SUM('Total Fuel per Operation (HVC)'!Q$61:Q$65) -> 99712 | H55: =SUM('Total Fuel per Operation (HVC)'!R$61:R$65) -> 442935 | I55: =SUM('Total Fuel per Operation (HVC)'!S$61:S$65) -> 0 | ... M55: =SUM('Total Fuel per Operation (HVC)'!W$61:W$65) -> 99712 | N55: =SUM(B55:M55) -> 1367278 | O55: =$N55*AVERAGE('Assumptions&Calculations'!$B$3:$B$5) -> 91685105 | P55: =$N55*AVERAGE('Assumptions&Calculations'!$M$3:$M$5) -> 35736415
A56: Region XI | B56: =SUM('Total Fuel per Operation (HVC)'!L$66:L$70) -> 234045 | C56: =SUM('Total Fuel per Operation (HVC)'!M$66:M$70) -> 0 | D56: =SUM('Total Fuel per Operation (HVC)'!N$66:N$70) -> 0 | E56: =SUM('Total Fuel per Operation (HVC)'!O$66:O$70) -> 0 | F56: =SUM('Total Fuel per Operation (HVC)'!P$66:P$70) -> 123152 | G56: =SUM('Total Fuel per Operation (HVC)'!Q$66:Q$70) -> 113792 | H56: =SUM('Total Fuel per Operation (HVC)'!R$66:R$70) -> 234045 | I56: =SUM('Total Fuel per Operation (HVC)'!S$66:S$70) -> 0 | ... M56: =SUM('Total Fuel per Operation (HVC)'!W$66:W$70) -> 113792 | N56: =SUM(B56:M56) -> 1412967 | O56: =$N56*AVERAGE('Assumptions&Calculations'!$B$3:$B$5) -> 94748857 | P56: =$N56*AVERAGE('Assumptions&Calculations'!$M$3:$M$5) -> 36930584
A57: Region XII | B57: =SUM('Total Fuel per Operation (HVC)'!L$71:L$74) -> 1515915 | C57: =SUM('Total Fuel per Operation (HVC)'!M$71:M$74) -> 0 | D57: =SUM('Total Fuel per Operation (HVC)'!N$71:N$74) -> 0 | E57: =SUM('Total Fuel per Operation (HVC)'!O$71:O$74) -> 0 | F57: =SUM('Total Fuel per Operation (HVC)'!P$71:P$74) -> 410864 | G57: =SUM('Total Fuel per Operation (HVC)'!Q$71:Q$74) -> 305024 | H57: =SUM('Total Fuel per Operation (HVC)'!R$71:R$74) -> 1515915 | I57: =SUM('Total Fuel per Operation (HVC)'!S$71:S$74) -> 0 | ... M57: =SUM('Total Fuel per Operation (HVC)'!W$71:W$74) -> 305024 | N57: =SUM(B57:M57) -> 6695409 | O57: =$N57*AVERAGE('Assumptions&Calculations'!$B$3:$B$5) -> 4.4897181e+08 | P57: =$N57*AVERAGE('Assumptions&Calculations'!$M$3:$M$5) -> 1.7499727e+08
A58: Region XIII | B58: =SUM('Total Fuel per Operation (HVC)'!L$75:L$79) -> 791614 | C58: =SUM('Total Fuel per Operation (HVC)'!M$75:M$79) -> 118144 | D58: =SUM('Total Fuel per Operation (HVC)'!N$75:N$79) -> 545734 | E58: =SUM('Total Fuel per Operation (HVC)'!O$75:O$79) -> 118144 | F58: =SUM('Total Fuel per Operation (HVC)'!P$75:P$79) -> 671146 | G58: =SUM('Total Fuel per Operation (HVC)'!Q$75:Q$79) -> 388670 | H58: =SUM('Total Fuel per Operation (HVC)'!R$75:R$79) -> 748864 | I58: =SUM('Total Fuel per Operation (HVC)'!S$75:S$79) -> 384840 | ... M58: =SUM('Total Fuel per Operation (HVC)'!W$75:W$79) -> 612616 | N58: =SUM(B58:M58) -> 6089918 | O58: =$N58*AVERAGE('Assumptions&Calculations'!$B$3:$B$5) -> 4.083696e+08 | P58: =$N58*AVERAGE('Assumptions&Calculations'!$M$3:$M$5) -> 1.5917161e+08
A59: BARMM | B59: =SUM('Total Fuel per Operation (HVC)'!L$80:L$82) -> 1240 | C59: =SUM('Total Fuel per Operation (HVC)'!M$80:M$82) -> 640 | D59: =SUM('Total Fuel per Operation (HVC)'!N$80:N$82) -> 5965 | E59: =SUM('Total Fuel per Operation (HVC)'!O$80:O$82) -> 640 | F59: =SUM('Total Fuel per Operation (HVC)'!P$80:P$82) -> 4725 | G59: =SUM('Total Fuel per Operation (HVC)'!Q$80:Q$82) -> 1240 | H59: =SUM('Total Fuel per Operation (HVC)'!R$80:R$82) -> 640 | I59: =SUM('Total Fuel per Operation (HVC)'!S$80:S$82) -> 4725 | ... M59: =SUM('Total Fuel per Operation (HVC)'!W$80:W$82) -> 4725 | N59: =SUM(B59:M59) -> 26420 | O59: =$N59*AVERAGE('Assumptions&Calculations'!$B$3:$B$5) -> 1771637.1 | P59: =$N59*AVERAGE('Assumptions&Calculations'!$M$3:$M$5) -> 690537.02
A60: Total per Month | B60: =SUM(B43:B59) -> 5695177 | C60: =SUM(C43:C59) -> 578752 | D60: =SUM(D43:D59) -> 5756737 | E60: =SUM(E43:E59) -> 578752 | F60: =SUM(F43:F59) -> 7781219 | G60: =SUM(G43:G59) -> 3808848 | H60: =SUM(H43:H59) -> 5532982 | I60: =SUM(I43:I59) -> 4493745 | ... N60: =SUM(N43:N59) -> 52123657 | O60: =$N60*AVERAGE('Assumptions&Calculations'!$B$3:$B$5) -> 3.4952387e+09 | P60: =$N60*AVERAGE('Assumptions&Calculations'!$M$3:$M$5) -> 1.3623511e+09
A62: SUGAR | B62: January | C62: February | D62: March | E62: April | F62: May | G62: June | H62: July | I62: August | J62: September | K62: October | L62: November | M62: December | N62: Total Fuel (L) Per Region | O62: Cost (Php) Per Region @ average fuel cost | P62: Cost (Php) Per Region @ incremental cost
A63: CAR | B63: =SUM('Fuel per Region (Sugar)'!D$4:D$9) -> 0 | C63: =SUM('Fuel per Region (Sugar)'!E$4:E$9) -> 0 | D63: =SUM('Fuel per Region (Sugar)'!F$4:F$9) -> 0 | E63: =SUM('Fuel per Region (Sugar)'!G$4:G$9) -> 0 | F63: =SUM('Fuel per Region (Sugar)'!H$4:H$9) -> 0 | G63: =SUM('Fuel per Region (Sugar)'!I$4:I$9) -> 0 | H63: =SUM('Fuel per Region (Sugar)'!J$4:J$9) -> 0 | I63: =SUM('Fuel per Region (Sugar)'!K$4:K$9) -> 0 | ... M63: =SUM('Fuel per Region (Sugar)'!O$4:O$9) -> 0 | N63: =SUM(B63:M63) -> 0 | O63: =$N63*AVERAGE('Assumptions&Calculations'!$B$3:$B$5) -> 0 | P63: =$N63*AVERAGE('Assumptions&Calculations'!$M$3:$M$5) -> 0
A64: Region I | B64: =SUM('Fuel per Region (Sugar)'!D$10:D$13) -> 0 | C64: =SUM('Fuel per Region (Sugar)'!E$10:E$13) -> 0 | D64: =SUM('Fuel per Region (Sugar)'!F$10:F$13) -> 0 | E64: =SUM('Fuel per Region (Sugar)'!G$10:G$13) -> 0 | F64: =SUM('Fuel per Region (Sugar)'!H$10:H$13) -> 0 | G64: =SUM('Fuel per Region (Sugar)'!I$10:I$13) -> 0 | H64: =SUM('Fuel per Region (Sugar)'!J$10:J$13) -> 0 | I64: =SUM('Fuel per Region (Sugar)'!K$10:K$13) -> 0 | ... M64: =SUM('Fuel per Region (Sugar)'!O$10:O$13) -> 0 | N64: =SUM(B64:M64) -> 0 | O64: =N64*AVERAGE('Assumptions&Calculations'!$B$3:$B$5) -> 0 | P64: =$N64*AVERAGE('Assumptions&Calculations'!$M$3:$M$5) -> 0
A65: Region II | B65: =SUM('Fuel per Region (Sugar)'!D$14:D$18) -> 36789.299 | C65: =SUM('Fuel per Region (Sugar)'!E$14:E$18) -> 82830.075 | D65: =SUM('Fuel per Region (Sugar)'!F$14:F$18) -> 82830.075 | E65: =SUM('Fuel per Region (Sugar)'!G$14:G$18) -> 59363.408 | F65: =SUM('Fuel per Region (Sugar)'!H$14:H$18) -> 59363.408 | G65: =SUM('Fuel per Region (Sugar)'!I$14:I$18) -> 59363.408 | H65: =SUM('Fuel per Region (Sugar)'!J$14:J$18) -> 0 | I65: =SUM('Fuel per Region (Sugar)'!K$14:K$18) -> 0 | ... M65: =SUM('Fuel per Region (Sugar)'!O$14:O$18) -> 0 | N65: =SUM(B65:M65) -> 380539.67 | O65: =N65*AVERAGE('Assumptions&Calculations'!$B$3:$B$5) -> 25517722 | P65: =$N65*AVERAGE('Assumptions&Calculations'!$M$3:$M$5) -> 9946129.2
A66: Region III | B66: =SUM('Fuel per Region (Sugar)'!D$19:D$25) -> 265407.57 | C66: =SUM('Fuel per Region (Sugar)'!E$19:E$25) -> 265407.57 | D66: =SUM('Fuel per Region (Sugar)'!F$19:F$25) -> 30489.6 | E66: =SUM('Fuel per Region (Sugar)'!G$19:G$25) -> 0 | F66: =SUM('Fuel per Region (Sugar)'!H$19:H$25) -> 0 | G66: =SUM('Fuel per Region (Sugar)'!I$19:I$25) -> 0 | H66: =SUM('Fuel per Region (Sugar)'!J$19:J$25) -> 0 | I66: =SUM('Fuel per Region (Sugar)'!K$19:K$25) -> 0 | ... M66: =SUM('Fuel per Region (Sugar)'!O$19:O$25) -> 265407.57 | N66: =SUM(B66:M66) -> 857201.92 | O66: =N66*AVERAGE('Assumptions&Calculations'!$B$3:$B$5) -> 57481103 | P66: =$N66*AVERAGE('Assumptions&Calculations'!$M$3:$M$5) -> 22404605
A67: CALABARZON | B67: =SUM('Fuel per Region (Sugar)'!D$26:D$30) -> 483172.07 | C67: =SUM('Fuel per Region (Sugar)'!E$26:E$30) -> 483172.07 | D67: =SUM('Fuel per Region (Sugar)'!F$26:F$30) -> 483172.07 | E67: =SUM('Fuel per Region (Sugar)'!G$26:G$30) -> 483172.07 | F67: =SUM('Fuel per Region (Sugar)'!H$26:H$30) -> 56246.034 | G67: =SUM('Fuel per Region (Sugar)'!I$26:I$30) -> 0 | H67: =SUM('Fuel per Region (Sugar)'!J$26:J$30) -> 0 | I67: =SUM('Fuel per Region (Sugar)'!K$26:K$30) -> 0 | ... M67: =SUM('Fuel per Region (Sugar)'!O$26:O$30) -> 254696.76 | N67: =SUM(B67:M67) -> 2498327.8 | O67: =N67*AVERAGE('Assumptions&Calculations'!$B$3:$B$5) -> 1.6752954e+08 | P67: =$N67*AVERAGE('Assumptions&Calculations'!$M$3:$M$5) -> 65298556
A68: MIMAROPA | B68: =SUM('Fuel per Region (Sugar)'!D$31:D$35) -> 0 | C68: =SUM('Fuel per Region (Sugar)'!E$31:E$35) -> 0 | D68: =SUM('Fuel per Region (Sugar)'!F$31:F$35) -> 0 | E68: =SUM('Fuel per Region (Sugar)'!G$31:G$35) -> 0 | F68: =SUM('Fuel per Region (Sugar)'!H$31:H$35) -> 0 | G68: =SUM('Fuel per Region (Sugar)'!I$31:I$35) -> 0 | H68: =SUM('Fuel per Region (Sugar)'!J$31:J$35) -> 0 | I68: =SUM('Fuel per Region (Sugar)'!K$31:K$35) -> 0 | ... M68: =SUM('Fuel per Region (Sugar)'!O$31:O$35) -> 0 | N68: =SUM(B68:M68) -> 0 | O68: =N68*AVERAGE('Assumptions&Calculations'!$B$3:$B$5) -> 0 | P68: =$N68*AVERAGE('Assumptions&Calculations'!$M$3:$M$5) -> 0
A69: Region V | B69: =SUM('Fuel per Region (Sugar)'!D$36:D$41) -> 58001.429 | C69: =SUM('Fuel per Region (Sugar)'!E$36:E$41) -> 58001.429 | D69: =SUM('Fuel per Region (Sugar)'!F$36:F$41) -> 58001.429 | E69: =SUM('Fuel per Region (Sugar)'!G$36:G$41) -> 41868.096 | F69: =SUM('Fuel per Region (Sugar)'!H$36:H$41) -> 41868.096 | G69: =SUM('Fuel per Region (Sugar)'!I$36:I$41) -> 0 | H69: =SUM('Fuel per Region (Sugar)'!J$36:J$41) -> 0 | I69: =SUM('Fuel per Region (Sugar)'!K$36:K$41) -> 0 | ... M69: =SUM('Fuel per Region (Sugar)'!O$36:O$41) -> 0 | N69: =SUM(B69:M69) -> 257740.48 | O69: =N69*AVERAGE('Assumptions&Calculations'!$B$3:$B$5) -> 17283217 | P69: =$N69*AVERAGE('Assumptions&Calculations'!$M$3:$M$5) -> 6736538.4
A70: Region VI | B70: =SUM('Fuel per Region (Sugar)'!D$42:D$46) -> 486930.5 | C70: =SUM('Fuel per Region (Sugar)'!E$42:E$46) -> 486930.5 | D70: =SUM('Fuel per Region (Sugar)'!F$42:F$46) -> 486930.5 | E70: =SUM('Fuel per Region (Sugar)'!G$42:G$46) -> 383490.5 | F70: =SUM('Fuel per Region (Sugar)'!H$42:H$46) -> 383490.5 | G70: =SUM('Fuel per Region (Sugar)'!I$42:I$46) -> 0 | H70: =SUM('Fuel per Region (Sugar)'!J$42:J$46) -> 0 | I70: =SUM('Fuel per Region (Sugar)'!K$42:K$46) -> 0 | ... M70: =SUM('Fuel per Region (Sugar)'!O$42:O$46) -> 486930.5 | N70: =SUM(B70:M70) -> 3585124 | O70: =N70*AVERAGE('Assumptions&Calculations'!$B$3:$B$5) -> 2.4040647e+08 | P70: =$N70*AVERAGE('Assumptions&Calculations'!$M$3:$M$5) -> 93704045
A71: NIR | B71: =SUM('Fuel per Region (Sugar)'!D$47:D$49) -> 4351051.8 | C71: =SUM('Fuel per Region (Sugar)'!E$47:E$49) -> 4351051.8 | D71: =SUM('Fuel per Region (Sugar)'!F$47:F$49) -> 4351051.8 | E71: =SUM('Fuel per Region (Sugar)'!G$47:G$49) -> 4351051.8 | F71: =SUM('Fuel per Region (Sugar)'!H$47:H$49) -> 457382.52 | G71: =SUM('Fuel per Region (Sugar)'!I$47:I$49) -> 0 | H71: =SUM('Fuel per Region (Sugar)'!J$47:J$49) -> 0 | I71: =SUM('Fuel per Region (Sugar)'!K$47:K$49) -> 0 | ... M71: =SUM('Fuel per Region (Sugar)'!O$47:O$49) -> 4351051.8 | N71: =SUM(B71:M71) -> 30914745 | O71: =N71*AVERAGE('Assumptions&Calculations'!$B$3:$B$5) -> 2.0730398e+09 | P71: =$N71*AVERAGE('Assumptions&Calculations'!$M$3:$M$5) -> 8.0801575e+08
A72: Region VII | B72: =SUM('Fuel per Region (Sugar)'!D$50:D$52) -> 81829.02 | C72: =SUM('Fuel per Region (Sugar)'!E$50:E$52) -> 81829.02 | D72: =SUM('Fuel per Region (Sugar)'!F$50:F$52) -> 81829.02 | E72: =SUM('Fuel per Region (Sugar)'!G$50:G$52) -> 81829.02 | F72: =SUM('Fuel per Region (Sugar)'!H$50:H$52) -> 0 | G72: =SUM('Fuel per Region (Sugar)'!I$50:I$52) -> 0 | H72: =SUM('Fuel per Region (Sugar)'!J$50:J$52) -> 0 | I72: =SUM('Fuel per Region (Sugar)'!K$50:K$52) -> 0 | ... M72: =SUM('Fuel per Region (Sugar)'!O$50:O$52) -> 61469.02 | N72: =SUM(B72:M72) -> 388785.1 | O72: =N72*AVERAGE('Assumptions&Calculations'!$B$3:$B$5) -> 26070633 | P72: =$N72*AVERAGE('Assumptions&Calculations'!$M$3:$M$5) -> 10161639
A73: Region VIII | B73: =SUM('Fuel per Region (Sugar)'!D$52:D$57) -> 122230.78 | C73: =SUM('Fuel per Region (Sugar)'!E$52:E$57) -> 122230.78 | D73: =SUM('Fuel per Region (Sugar)'!F$52:F$57) -> 122230.78 | E73: =SUM('Fuel per Region (Sugar)'!G$52:G$57) -> 122230.78 | F73: =SUM('Fuel per Region (Sugar)'!H$52:H$57) -> 106230.78 | G73: =SUM('Fuel per Region (Sugar)'!I$52:I$57) -> 0 | H73: =SUM('Fuel per Region (Sugar)'!J$52:J$57) -> 0 | I73: =SUM('Fuel per Region (Sugar)'!K$52:K$57) -> 0 | ... M73: =SUM('Fuel per Region (Sugar)'!O$52:O$57) -> 16000 | N73: =SUM(B73:M73) -> 627153.88 | O73: =N73*AVERAGE('Assumptions&Calculations'!$B$3:$B$5) -> 42054849 | P73: =$N73*AVERAGE('Assumptions&Calculations'!$M$3:$M$5) -> 16391861
A74: Region IX | B74: =SUM('Fuel per Region (Sugar)'!D$58:D$60) -> 0 | C74: =SUM('Fuel per Region (Sugar)'!E$58:E$60) -> 0 | D74: =SUM('Fuel per Region (Sugar)'!F$58:F$60) -> 0 | E74: =SUM('Fuel per Region (Sugar)'!G$58:G$60) -> 0 | F74: =SUM('Fuel per Region (Sugar)'!H$58:H$60) -> 0 | G74: =SUM('Fuel per Region (Sugar)'!I$58:I$60) -> 0 | H74: =SUM('Fuel per Region (Sugar)'!J$58:J$60) -> 0 | I74: =SUM('Fuel per Region (Sugar)'!K$58:K$60) -> 0 | ... M74: =SUM('Fuel per Region (Sugar)'!O$58:O$60) -> 0 | N74: =SUM(B74:M74) -> 0 | O74: =N74*AVERAGE('Assumptions&Calculations'!$B$3:$B$5) -> 0 | P74: =$N74*AVERAGE('Assumptions&Calculations'!$M$3:$M$5) -> 0
A75: Region X | B75: =SUM('Fuel per Region (Sugar)'!D$61:D$65) -> 963617.17 | C75: =SUM('Fuel per Region (Sugar)'!E$61:E$65) -> 963617.17 | D75: =SUM('Fuel per Region (Sugar)'!F$61:F$65) -> 963617.17 | E75: =SUM('Fuel per Region (Sugar)'!G$61:G$65) -> 963617.17 | F75: =SUM('Fuel per Region (Sugar)'!H$61:H$65) -> 963617.17 | G75: =SUM('Fuel per Region (Sugar)'!I$61:I$65) -> 839763.17 | H75: =SUM('Fuel per Region (Sugar)'!J$61:J$65) -> 0 | I75: =SUM('Fuel per Region (Sugar)'!K$61:K$65) -> 0 | ... M75: =SUM('Fuel per Region (Sugar)'!O$61:O$65) -> 963617.17 | N75: =SUM(B75:M75) -> 7708937.4 | O75: =N75*AVERAGE('Assumptions&Calculations'!$B$3:$B$5) -> 5.1693564e+08 | P75: =$N75*AVERAGE('Assumptions&Calculations'!$M$3:$M$5) -> 2.0148776e+08
A76: Region XI | B76: =SUM('Fuel per Region (Sugar)'!D$66:D$70) -> 140472.37 | C76: =SUM('Fuel per Region (Sugar)'!E$66:E$70) -> 140472.37 | D76: =SUM('Fuel per Region (Sugar)'!F$66:F$70) -> 140472.37 | E76: =SUM('Fuel per Region (Sugar)'!G$66:G$70) -> 106352.37 | F76: =SUM('Fuel per Region (Sugar)'!H$66:H$70) -> 106352.37 | G76: =SUM('Fuel per Region (Sugar)'!I$66:I$70) -> 0 | H76: =SUM('Fuel per Region (Sugar)'!J$66:J$70) -> 0 | I76: =SUM('Fuel per Region (Sugar)'!K$66:K$70) -> 0 | ... M76: =SUM('Fuel per Region (Sugar)'!O$66:O$70) -> 34120 | N76: =SUM(B76:M76) -> 668241.84 | O76: =N76*AVERAGE('Assumptions&Calculations'!$B$3:$B$5) -> 44810070 | P76: =$N76*AVERAGE('Assumptions&Calculations'!$M$3:$M$5) -> 17465773
A77: Region XII | B77: =SUM('Fuel per Region (Sugar)'!D$71:D$74) -> 218136.86 | C77: =SUM('Fuel per Region (Sugar)'!E$71:E$74) -> 218136.86 | D77: =SUM('Fuel per Region (Sugar)'!F$71:F$74) -> 218136.86 | E77: =SUM('Fuel per Region (Sugar)'!G$71:G$74) -> 164536.86 | F77: =SUM('Fuel per Region (Sugar)'!H$71:H$74) -> 164536.86 | G77: =SUM('Fuel per Region (Sugar)'!I$71:I$74) -> 0 | H77: =SUM('Fuel per Region (Sugar)'!J$71:J$74) -> 0 | I77: =SUM('Fuel per Region (Sugar)'!K$71:K$74) -> 0 | ... M77: =SUM('Fuel per Region (Sugar)'!O$71:O$74) -> 218136.86 | N77: =SUM(B77:M77) -> 1366158 | O77: =N77*AVERAGE('Assumptions&Calculations'!$B$3:$B$5) -> 91610002 | P77: =$N77*AVERAGE('Assumptions&Calculations'!$M$3:$M$5) -> 35707142
A78: Region XIII | B78: =SUM('Fuel per Region (Sugar)'!D$75:D$79) -> 0 | C78: =SUM('Fuel per Region (Sugar)'!E$75:E$79) -> 0 | D78: =SUM('Fuel per Region (Sugar)'!F$75:F$79) -> 0 | E78: =SUM('Fuel per Region (Sugar)'!G$75:G$79) -> 0 | F78: =SUM('Fuel per Region (Sugar)'!H$75:H$79) -> 0 | G78: =SUM('Fuel per Region (Sugar)'!I$75:I$79) -> 0 | H78: =SUM('Fuel per Region (Sugar)'!J$75:J$79) -> 0 | I78: =SUM('Fuel per Region (Sugar)'!K$75:K$79) -> 0 | ... M78: =SUM('Fuel per Region (Sugar)'!O$75:O$79) -> 0 | N78: =SUM(B78:M78) -> 0 | O78: =N78*AVERAGE('Assumptions&Calculations'!$B$3:$B$5) -> 0 | P78: =$N78*AVERAGE('Assumptions&Calculations'!$M$3:$M$5) -> 0
A79: BARMM | B79: =SUM('Fuel per Region (Sugar)'!D$80:D$82) -> 0 | C79: =SUM('Fuel per Region (Sugar)'!E$80:E$82) -> 0 | D79: =SUM('Fuel per Region (Sugar)'!F$80:F$82) -> 0 | E79: =SUM('Fuel per Region (Sugar)'!G$80:G$82) -> 0 | F79: =SUM('Fuel per Region (Sugar)'!H$80:H$82) -> 0 | G79: =SUM('Fuel per Region (Sugar)'!I$80:I$82) -> 0 | H79: =SUM('Fuel per Region (Sugar)'!J$80:J$82) -> 0 | I79: =SUM('Fuel per Region (Sugar)'!K$80:K$82) -> 0 | ... M79: =SUM('Fuel per Region (Sugar)'!O$80:O$82) -> 0 | N79: =SUM(B79:M79) -> 0 | O79: =N79*AVERAGE('Assumptions&Calculations'!$B$3:$B$5) -> 0 | P79: =$N79*AVERAGE('Assumptions&Calculations'!$M$3:$M$5) -> 0
A80: Total per Month | B80: =SUM(B63:B79) -> 7207638.9 | C80: =SUM(C63:C79) -> 7253679.7 | D80: =SUM(D63:D79) -> 7018761.7 | E80: =SUM(E63:E79) -> 6757512.1 | F80: =SUM(F63:F79) -> 2339087.7 | G80: =SUM(G63:G79) -> 899126.58 | H80: =SUM(H63:H79) -> 0 | I80: =SUM(I63:I79) -> 0 | ... N80: =SUM(N63:N79) -> 49252955 | O80: =N80*AVERAGE('Assumptions&Calculations'!$B$3:$B$5) -> 3.302739e+09 | P80: =$N80*AVERAGE('Assumptions&Calculations'!$M$3:$M$5) -> 1.2873198e+09
A82: MARINE CAPTURE | B82: January | C82: February | D82: March | E82: April | F82: May | G82: June | H82: July | I82: August | J82: September | K82: October | L82: November | M82: December | N82: Total Fuel (L) Per Region | O82: Cost (Php) Per Region @ average fuel cost | P82: Cost (Php) Per Region @ incremental cost
A83: NCR | B83: ='Fishery Beneficiary Estimation'!C3 -> 8447096 | C83: ='Fishery Beneficiary Estimation'!D3 -> 8447096 | D83: ='Fishery Beneficiary Estimation'!E3 -> 10558870 | E83: ='Fishery Beneficiary Estimation'!F3 -> 10558870 | F83: ='Fishery Beneficiary Estimation'!G3 -> 10558870 | G83: ='Fishery Beneficiary Estimation'!H3 -> 10558870 | H83: ='Fishery Beneficiary Estimation'!I3 -> 10558870 | I83: ='Fishery Beneficiary Estimation'!J3 -> 10558870 | ... M83: ='Fishery Beneficiary Estimation'!N3 -> 8447096 | N83: =SUM(B83:M83) -> 114035796 | O83: =$N83*AVERAGE('Assumptions&Calculations'!$B$3:$B$5) -> 7.6468604e+09 | P83: =$N83*AVERAGE('Assumptions&Calculations'!$M$3:$M$5) -> 2.9805427e+09
A84: CAR | B84: ='Fishery Beneficiary Estimation'!C4 -> 55968 | C84: ='Fishery Beneficiary Estimation'!D4 -> 55968 | D84: ='Fishery Beneficiary Estimation'!E4 -> 69960 | E84: ='Fishery Beneficiary Estimation'!F4 -> 69960 | F84: ='Fishery Beneficiary Estimation'!G4 -> 69960 | G84: ='Fishery Beneficiary Estimation'!H4 -> 69960 | H84: ='Fishery Beneficiary Estimation'!I4 -> 69960 | I84: ='Fishery Beneficiary Estimation'!J4 -> 69960 | ... M84: ='Fishery Beneficiary Estimation'!N4 -> 55968 | N84: =SUM(B84:M84) -> 755568 | O84: =N84*AVERAGE('Assumptions&Calculations'!$B$3:$B$5) -> 50665872 | P84: =$N84*AVERAGE('Assumptions&Calculations'!$M$3:$M$5) -> 19748209
A85: Region I | B85: ='Fishery Beneficiary Estimation'!C5 -> 5431512 | C85: ='Fishery Beneficiary Estimation'!D5 -> 5431512 | D85: ='Fishery Beneficiary Estimation'!E5 -> 6789390 | E85: ='Fishery Beneficiary Estimation'!F5 -> 6789390 | F85: ='Fishery Beneficiary Estimation'!G5 -> 6789390 | G85: ='Fishery Beneficiary Estimation'!H5 -> 6789390 | H85: ='Fishery Beneficiary Estimation'!I5 -> 6789390 | I85: ='Fishery Beneficiary Estimation'!J5 -> 6789390 | ... M85: ='Fishery Beneficiary Estimation'!N5 -> 5431512 | N85: =SUM(B85:M85) -> 73325412 | O85: =N85*AVERAGE('Assumptions&Calculations'!$B$3:$B$5) -> 4.9169577e+09 | P85: =$N85*AVERAGE('Assumptions&Calculations'!$M$3:$M$5) -> 1.9164993e+09
A86: Region II | B86: ='Fishery Beneficiary Estimation'!C6 -> 1719328 | C86: ='Fishery Beneficiary Estimation'!D6 -> 1719328 | D86: ='Fishery Beneficiary Estimation'!E6 -> 2149160 | E86: ='Fishery Beneficiary Estimation'!F6 -> 2149160 | F86: ='Fishery Beneficiary Estimation'!G6 -> 2149160 | G86: ='Fishery Beneficiary Estimation'!H6 -> 2146160 | H86: ='Fishery Beneficiary Estimation'!I6 -> 2146160 | I86: ='Fishery Beneficiary Estimation'!J6 -> 2146160 | ... M86: ='Fishery Beneficiary Estimation'!N6 -> 1719328 | N86: =SUM(B86:M86) -> 23201928 | O86: =N86*AVERAGE('Assumptions&Calculations'!$B$3:$B$5) -> 1.555844e+09 | P86: =$N86*AVERAGE('Assumptions&Calculations'!$M$3:$M$5) -> 6.0642658e+08
A87: Region III | B87: ='Fishery Beneficiary Estimation'!C7 -> 3399704 | C87: ='Fishery Beneficiary Estimation'!D7 -> 3399704 | D87: ='Fishery Beneficiary Estimation'!E7 -> 4249630 | E87: ='Fishery Beneficiary Estimation'!F7 -> 4249630 | F87: ='Fishery Beneficiary Estimation'!G7 -> 4249630 | G87: ='Fishery Beneficiary Estimation'!H7 -> 4240630 | H87: ='Fishery Beneficiary Estimation'!I7 -> 4240630 | I87: ='Fishery Beneficiary Estimation'!J7 -> 4240630 | ... M87: ='Fishery Beneficiary Estimation'!N7 -> 3399704 | N87: =SUM(B87:M87) -> 45869004 | O87: =N87*AVERAGE('Assumptions&Calculations'!$B$3:$B$5) -> 3.0758225e+09 | P87: =$N87*AVERAGE('Assumptions&Calculations'!$M$3:$M$5) -> 1.1988738e+09
A88: CALABARZON | B88: ='Fishery Beneficiary Estimation'!C8 -> 3207192 | C88: ='Fishery Beneficiary Estimation'!D8 -> 3207192 | D88: ='Fishery Beneficiary Estimation'!E8 -> 4008990 | E88: ='Fishery Beneficiary Estimation'!F8 -> 4008990 | F88: ='Fishery Beneficiary Estimation'!G8 -> 4008990 | G88: ='Fishery Beneficiary Estimation'!H8 -> 2536930 | H88: ='Fishery Beneficiary Estimation'!I8 -> 2536930 | I88: ='Fishery Beneficiary Estimation'!J8 -> 2536930 | ... M88: ='Fishery Beneficiary Estimation'!N8 -> 3207192 | N88: =SUM(B88:M88) -> 38880912 | O88: =N88*AVERAGE('Assumptions&Calculations'!$B$3:$B$5) -> 2.6072244e+09 | P88: =$N88*AVERAGE('Assumptions&Calculations'!$M$3:$M$5) -> 1.0162267e+09
A89: MIMAROPA | B89: ='Fishery Beneficiary Estimation'!C9 -> 4568432 | C89: ='Fishery Beneficiary Estimation'!D9 -> 4568432 | D89: ='Fishery Beneficiary Estimation'!E9 -> 5710540 | E89: ='Fishery Beneficiary Estimation'!F9 -> 5710540 | F89: ='Fishery Beneficiary Estimation'!G9 -> 5710540 | G89: ='Fishery Beneficiary Estimation'!H9 -> 4422540 | H89: ='Fishery Beneficiary Estimation'!I9 -> 4422540 | I89: ='Fishery Beneficiary Estimation'!J9 -> 4422540 | ... M89: ='Fishery Beneficiary Estimation'!N9 -> 4568432 | N89: =SUM(B89:M89) -> 57809832 | O89: =N89*AVERAGE('Assumptions&Calculations'!$B$3:$B$5) -> 3.8765346e+09 | P89: =$N89*AVERAGE('Assumptions&Calculations'!$M$3:$M$5) -> 1.5109701e+09
A90: Region V | B90: ='Fishery Beneficiary Estimation'!C10 -> 4748272 | C90: ='Fishery Beneficiary Estimation'!D10 -> 4748272 | D90: ='Fishery Beneficiary Estimation'!E10 -> 5941840 | E90: ='Fishery Beneficiary Estimation'!F10 -> 5941840 | F90: ='Fishery Beneficiary Estimation'!G10 -> 5941840 | G90: ='Fishery Beneficiary Estimation'!H10 -> 5941840 | H90: ='Fishery Beneficiary Estimation'!I10 -> 5941840 | I90: ='Fishery Beneficiary Estimation'!J10 -> 5941840 | ... M90: ='Fishery Beneficiary Estimation'!N10 -> 4748272 | N90: =SUM(B90:M90) -> 64156272 | O90: =N90*AVERAGE('Assumptions&Calculations'!$B$3:$B$5) -> 4.3021057e+09 | P90: =$N90*AVERAGE('Assumptions&Calculations'!$M$3:$M$5) -> 1.6768464e+09
A91: Region VI | B91: ='Fishery Beneficiary Estimation'!C11 -> 6023472 | C91: ='Fishery Beneficiary Estimation'!D11 -> 6023472 | D91: ='Fishery Beneficiary Estimation'!E11 -> 7942640 | E91: ='Fishery Beneficiary Estimation'!F11 -> 7942640 | F91: ='Fishery Beneficiary Estimation'!G11 -> 7942640 | G91: ='Fishery Beneficiary Estimation'!H11 -> 7942640 | H91: ='Fishery Beneficiary Estimation'!I11 -> 7942640 | I91: ='Fishery Beneficiary Estimation'!J11 -> 7942640 | ... M91: ='Fishery Beneficiary Estimation'!N11 -> 6023472 | N91: =SUM(B91:M91) -> 84788592 | O91: =N91*AVERAGE('Assumptions&Calculations'!$B$3:$B$5) -> 5.6856404e+09 | P91: =$N91*AVERAGE('Assumptions&Calculations'!$M$3:$M$5) -> 2216111354
A92: NIR
A93: Region VII | B93: ='Fishery Beneficiary Estimation'!C13 -> 4593712 | C93: ='Fishery Beneficiary Estimation'!D13 -> 4593712 | D93: ='Fishery Beneficiary Estimation'!E13 -> 5742140 | E93: ='Fishery Beneficiary Estimation'!F13 -> 5742140 | F93: ='Fishery Beneficiary Estimation'!G13 -> 5742140 | G93: ='Fishery Beneficiary Estimation'!H13 -> 5742140 | H93: ='Fishery Beneficiary Estimation'!I13 -> 5742140 | I93: ='Fishery Beneficiary Estimation'!J13 -> 5742140 | ... M93: ='Fishery Beneficiary Estimation'!N13 -> 4593712 | N93: =SUM(B93:M93) -> 62015112 | O93: =N93*AVERAGE('Assumptions&Calculations'!$B$3:$B$5) -> 4.1585267e+09 | P93: =$N93*AVERAGE('Assumptions&Calculations'!$M$3:$M$5) -> 1.6208831e+09
A94: Region VIII | B94: ='Fishery Beneficiary Estimation'!C14 -> 2833008 | C94: ='Fishery Beneficiary Estimation'!D14 -> 2833008 | D94: ='Fishery Beneficiary Estimation'!E14 -> 4717260 | E94: ='Fishery Beneficiary Estimation'!F14 -> 4717260 | F94: ='Fishery Beneficiary Estimation'!G14 -> 4717260 | G94: ='Fishery Beneficiary Estimation'!H14 -> 4717260 | H94: ='Fishery Beneficiary Estimation'!I14 -> 4717260 | I94: ='Fishery Beneficiary Estimation'!J14 -> 4717260 | ... M94: ='Fishery Beneficiary Estimation'!N14 -> 2833008 | N94: =SUM(B94:M94) -> 48124008 | O94: =N94*AVERAGE('Assumptions&Calculations'!$B$3:$B$5) -> 3.2270356e+09 | P94: =$N94*AVERAGE('Assumptions&Calculations'!$M$3:$M$5) -> 1.2578126e+09
A95: Region IX | B95: ='Fishery Beneficiary Estimation'!C15 -> 5905200 | C95: ='Fishery Beneficiary Estimation'!D15 -> 5905200 | D95: ='Fishery Beneficiary Estimation'!E15 -> 8557500 | E95: ='Fishery Beneficiary Estimation'!F15 -> 8557500 | F95: ='Fishery Beneficiary Estimation'!G15 -> 8557500 | G95: ='Fishery Beneficiary Estimation'!H15 -> 8518500 | H95: ='Fishery Beneficiary Estimation'!I15 -> 8518500 | I95: ='Fishery Beneficiary Estimation'!J15 -> 8518500 | ... M95: ='Fishery Beneficiary Estimation'!N15 -> 5905200 | N95: =SUM(B95:M95) -> 89481600 | O95: =N95*AVERAGE('Assumptions&Calculations'!$B$3:$B$5) -> 6000337824 | P95: =$N95*AVERAGE('Assumptions&Calculations'!$M$3:$M$5) -> 2.3387721e+09
A96: Region X | B96: ='Fishery Beneficiary Estimation'!C16 -> 3437008 | C96: ='Fishery Beneficiary Estimation'!D16 -> 3437008 | D96: ='Fishery Beneficiary Estimation'!E16 -> 5472260 | E96: ='Fishery Beneficiary Estimation'!F16 -> 5472260 | F96: ='Fishery Beneficiary Estimation'!G16 -> 5472260 | G96: ='Fishery Beneficiary Estimation'!H16 -> 5433260 | H96: ='Fishery Beneficiary Estimation'!I16 -> 5433260 | I96: ='Fishery Beneficiary Estimation'!J16 -> 5433260 | ... M96: ='Fishery Beneficiary Estimation'!N16 -> 3437008 | N96: =SUM(B96:M96) -> 56161008 | O96: =N96*AVERAGE('Assumptions&Calculations'!$B$3:$B$5) -> 3.76597e+09 | P96: =$N96*AVERAGE('Assumptions&Calculations'!$M$3:$M$5) -> 1.4678749e+09
A97: Region XI | B97: ='Fishery Beneficiary Estimation'!C17 -> 3430528 | C97: ='Fishery Beneficiary Estimation'!D17 -> 3430528 | D97: ='Fishery Beneficiary Estimation'!E17 -> 5476160 | E97: ='Fishery Beneficiary Estimation'!F17 -> 5476160 | F97: ='Fishery Beneficiary Estimation'!G17 -> 5476160 | G97: ='Fishery Beneficiary Estimation'!H17 -> 5444160 | H97: ='Fishery Beneficiary Estimation'!I17 -> 5444160 | I97: ='Fishery Beneficiary Estimation'!J17 -> 5444160 | ... M97: ='Fishery Beneficiary Estimation'!N17 -> 3430528 | N97: =SUM(B97:M97) -> 56195328 | O97: =N97*AVERAGE('Assumptions&Calculations'!$B$3:$B$5) -> 3.7682714e+09 | P97: =$N97*AVERAGE('Assumptions&Calculations'!$M$3:$M$5) -> 1.4687719e+09
A98: Region XII | B98: ='Fishery Beneficiary Estimation'!C18 -> 4383952 | C98: ='Fishery Beneficiary Estimation'!D18 -> 4383952 | D98: ='Fishery Beneficiary Estimation'!E18 -> 5491940 | E98: ='Fishery Beneficiary Estimation'!F18 -> 5491940 | F98: ='Fishery Beneficiary Estimation'!G18 -> 5491940 | G98: ='Fishery Beneficiary Estimation'!H18 -> 5459940 | H98: ='Fishery Beneficiary Estimation'!I18 -> 5459940 | I98: ='Fishery Beneficiary Estimation'!J18 -> 5459940 | ... M98: ='Fishery Beneficiary Estimation'!N18 -> 4383952 | N98: =SUM(B98:M98) -> 59188152 | O98: =N98*AVERAGE('Assumptions&Calculations'!$B$3:$B$5) -> 3.9689602e+09 | P98: =$N98*AVERAGE('Assumptions&Calculations'!$M$3:$M$5) -> 1.5469951e+09
A99: Region XIII | B99: ='Fishery Beneficiary Estimation'!C19 -> 8815696 | C99: ='Fishery Beneficiary Estimation'!D19 -> 8815696 | D99: ='Fishery Beneficiary Estimation'!E19 -> 11031620 | E99: ='Fishery Beneficiary Estimation'!F19 -> 11031620 | F99: ='Fishery Beneficiary Estimation'!G19 -> 11031620 | G99: ='Fishery Beneficiary Estimation'!H19 -> 10999620 | H99: ='Fishery Beneficiary Estimation'!I19 -> 10999620 | I99: ='Fishery Beneficiary Estimation'!J19 -> 10999620 | ... M99: ='Fishery Beneficiary Estimation'!N19 -> 8815696 | N99: =SUM(B99:M99) -> 119016696 | O99: =N99*AVERAGE('Assumptions&Calculations'!$B$3:$B$5) -> 7.9808629e+09 | P99: =$N99*AVERAGE('Assumptions&Calculations'!$M$3:$M$5) -> 3.110728e+09
A100: BARMM | B100: ='Fishery Beneficiary Estimation'!C20 -> 1672768 | C100: ='Fishery Beneficiary Estimation'!D20 -> 1672768 | D100: ='Fishery Beneficiary Estimation'!E20 -> 2102960 | E100: ='Fishery Beneficiary Estimation'!F20 -> 2102960 | F100: ='Fishery Beneficiary Estimation'!G20 -> 2102960 | G100: ='Fishery Beneficiary Estimation'!H20 -> 2070960 | H100: ='Fishery Beneficiary Estimation'!I20 -> 2070960 | I100: ='Fishery Beneficiary Estimation'!J20 -> 2070960 | ... M100: ='Fishery Beneficiary Estimation'!N20 -> 1672768 | N100: =SUM(B100:M100) -> 22587168 | O100: =N100*AVERAGE('Assumptions&Calculations'!$B$3:$B$5) -> 1.5146202e+09 | P100: =$N100*AVERAGE('Assumptions&Calculations'!$M$3:$M$5) -> 5.9035866e+08
A101: Total per Month | B101: =SUM(B83:B100) -> 72672848 | C101: =SUM(C83:C100) -> 72672848 | D101: =SUM(D83:D100) -> 96012860 | E101: =SUM(E83:E100) -> 96012860 | F101: =SUM(F83:F100) -> 96012860 | G101: =SUM(G83:G100) -> 93034800 | H101: =SUM(H83:H100) -> 93034800 | I101: =SUM(I83:I100) -> 93034800 | ... N101: =SUM(N83:N100) -> 1015592388 | O101: =N101*AVERAGE('Assumptions&Calculations'!$B$3:$B$5) -> 6.810224e+10 | P101: =$N101*AVERAGE('Assumptions&Calculations'!$M$3:$M$5) -> 2.6544442e+10
A103: AQUACULTURE CAPTURE | B103: January | C103: February | D103: March | E103: April | F103: May | G103: June | H103: July | I103: August | J103: September | K103: October | L103: November | M103: December | N103: Total Fuel (L) Per Region | O103: Cost (Php) Per Region @ average fuel cost | P103: Cost (Php) Per Region @ incremental cost
A104: NCR | B104: ='Aquaculture Fuel Consumption'!$M20 -> 171282.76 | C104: ='Aquaculture Fuel Consumption'!$M20 -> 171282.76 | D104: ='Aquaculture Fuel Consumption'!$M20 -> 171282.76 | E104: ='Aquaculture Fuel Consumption'!$M20 -> 171282.76 | F104: ='Aquaculture Fuel Consumption'!$M20 -> 171282.76 | G104: ='Aquaculture Fuel Consumption'!$M20 -> 171282.76 | H104: ='Aquaculture Fuel Consumption'!$M20 -> 171282.76 | I104: ='Aquaculture Fuel Consumption'!$M20 -> 171282.76 | ... M104: ='Aquaculture Fuel Consumption'!$M20 -> 171282.76 | N104: =SUM(B104:M104) -> 2055393.1 | O104: =N104*AVERAGE('Assumptions&Calculations'!$B$3:$B$5) -> 1.3782781e+08 | P104: =$N104*AVERAGE('Assumptions&Calculations'!$M$3:$M$5) -> 53721614
A105: CAR | B105: ='Aquaculture Fuel Consumption'!$M19 -> 76020 | C105: ='Aquaculture Fuel Consumption'!$M19 -> 76020 | D105: ='Aquaculture Fuel Consumption'!$M19 -> 76020 | E105: ='Aquaculture Fuel Consumption'!$M19 -> 76020 | F105: ='Aquaculture Fuel Consumption'!$M19 -> 76020 | G105: ='Aquaculture Fuel Consumption'!$M19 -> 76020 | H105: ='Aquaculture Fuel Consumption'!$M19 -> 76020 | I105: ='Aquaculture Fuel Consumption'!$M19 -> 76020 | ... M105: ='Aquaculture Fuel Consumption'!$M19 -> 76020 | N105: =SUM(B105:M105) -> 912240 | O105: =N105*AVERAGE('Assumptions&Calculations'!$B$3:$B$5) -> 61171774 | P105: =$N105*AVERAGE('Assumptions&Calculations'!$M$3:$M$5) -> 23843130
...

Sheet L Requirements
A1: Region | B1: Rice | C1: Corn | D1: HVC | E1: Sugar | F1: Total
A2: CAR | B2: =Summary!N3 -> 2007985.6 | C2: =Summary!N23 -> 6509088 | D2: =Summary!N43 -> 1158637 | E2: =Summary!N63 -> 0 | F2: =SUM(B2:E2) -> 9675710.6 | G2: =F2*60 -> 580542636 | I2: =D2+E2 -> 1158637
A3: Region I | B3: =Summary!N4 -> 33623794 | C3: =Summary!N24 -> 26976320 | D3: =Summary!N44 -> 2098144 | E3: =Summary!N64 -> 0 | F3: =SUM(B3:E3) -> 62698258 | G3: =F3*60 -> 3761895456 | I3: =D3+E3 -> 2098144
A4: Region II | B4: =Summary!N5 -> 54953507 | C4: =Summary!N25 -> 38775168 | D4: =Summary!N45 -> 17560568 | E4: =Summary!N65 -> 380539.67 | F4: =SUM(B4:E4) -> 1.1166978e+08 | G4: =F4*60 -> 6.700187e+09 | I4: =D4+E4 -> 17941108
A5: Region III | B5: =Summary!N6 -> 33191945 | C5: =Summary!N26 -> 14079200 | D5: =Summary!N46 -> 2759300 | E5: =Summary!N66 -> 857201.92 | F5: =SUM(B5:E5) -> 50887647 | G5: =F5*60 -> 3.0532588e+09 | I5: =D5+E5 -> 3616501.9
A6: CALABARZON | B6: =Summary!N7 -> 11080654 | C6: =Summary!N27 -> 6750720 | D6: =Summary!N47 -> 5339848 | E6: =Summary!N67 -> 2498327.8 | F6: =SUM(B6:E6) -> 25669550 | G6: =F6*60 -> 1.540173e+09 | I6: =D6+E6 -> 7838175.8
A7: MIMAROPA | B7: =Summary!N8 -> 10699891 | C7: =Summary!N28 -> 8582880 | D7: =Summary!N48 -> 538070 | E7: =Summary!N68 -> 0 | F7: =SUM(B7:E7) -> 19820841 | G7: =F7*60 -> 1.1892505e+09 | I7: =D7+E7 -> 538070
A8: Region V | B8: =Summary!N9 -> 13271970 | C8: =Summary!N29 -> 6387744 | D8: =Summary!N49 -> 1902227 | E8: =Summary!N69 -> 257740.48 | F8: =SUM(B8:E8) -> 21819681 | G8: =F8*60 -> 1.3091809e+09 | I8: =D8+E8 -> 2159967.5
A9: Region VI | B9: =Summary!N10 -> 8189092.8 | C9: =Summary!N30 -> 5391072 | D9: =Summary!N50 -> 578794 | E9: =Summary!N70 -> 3585124 | F9: =SUM(B9:E9) -> 17744083 | G9: =F9*60 -> 1064644968 | I9: =D9+E9 -> 4163918
A10: NIR | B10: =Summary!N11 -> 2220524.8 | C10: =Summary!N31 -> 2211904 | D10: =Summary!N51 -> 1316248 | E10: =Summary!N71 -> 30914745 | F10: =SUM(B10:E10) -> 36663422 | G10: =F10*60 -> 2199805326 | I10: =D10+E10 -> 32230993
A11: Region VII | B11: =Summary!N12 -> 2920065.6 | C11: =Summary!N32 -> 2607040 | D11: =Summary!N52 -> 698126 | E11: =Summary!N72 -> 388785.1 | F11: =SUM(B11:E11) -> 6614016.7 | G11: =F11*60 -> 3.96841e+08 | I11: =D11+E11 -> 1086911.1
A12: Region VIII | B12: =Summary!N13 -> 7199756.8 | C12: =Summary!N33 -> 3079008 | D12: =Summary!N53 -> 1905056 | E12: =Summary!N73 -> 627153.88 | F12: =SUM(B12:E12) -> 12810975 | G12: =F12*60 -> 7.6865848e+08 | I12: =D12+E12 -> 2532209.9
A13: Region IX | B13: =Summary!N14 -> 4640419.2 | C13: =Summary!N34 -> 4302816 | D13: =Summary!N54 -> 676647 | E13: =Summary!N74 -> 0 | F13: =SUM(B13:E13) -> 9619882.2 | G13: =F13*60 -> 577192932 | I13: =D13+E13 -> 676647
... A17: Region XIII | B17: =Summary!N18 -> 15741677 | C17: =Summary!N38 -> 5750912 | D17: =Summary!N58 -> 6089918 | E17: =Summary!N78 -> 0 | F17: =SUM(B17:E17) -> 27582507 | G17: =F17*60 -> 1654950408 | I17: =D17+E17 -> 6089918
A18: BARMM | B18: =Summary!N19 -> 157520 | C18: =Summary!N39 -> 453456 | D18: =Summary!N59 -> 26420 | E18: =Summary!N79 -> 0 | F18: =SUM(B18:E18) -> 637396 | G18: =F18*60 -> 38243760 | H18: =F18/F19 -> 0.0012619275 | I18: =D18+E18 -> 26420
A19: Total | B19: =SUM(B2:B18) -> 237948411 | C19: =SUM(C2:C18) -> 165772144 | D19: =SUM(D2:D18) -> 52123657 | E19: =SUM(E2:E18) -> 49252955 | F19: =SUM(F2:F18) -> 5.0509717e+08 | G19: =F19*60 -> 3.030583e+10 | I19: =D19+E19 -> 1.0137661e+08
B20: =B19*60 -> 14276904660 | C20: =C19*60 -> 9946328640 | D20: =D19*60 -> 3127419420 | E20: =E19*60 -> 2.9551773e+09 | F20: =F19*60 -> 3.030583e+10

Sheet Beneficiary Estimation
A1: FUEL COST PER REGION (Php) | O1: Target No of Beneficiaries | U1: Financial Allocation | W1: Administrative Fund | Y1: Total Fund Allocation | AA1: Target No of Beneficiaries | AG1: Financial Allocation | AN1: Administrative Fund | AU1: Total Regional Fund (Program and Administrative) | AV1: Percentage Share | AW1: Total Fund Allocation | AY1: Total Number of Beneficiaries | AZ1: Total Percentage Share | BA1: 2022 | BG1: Increment | BH1: Percentage Increment
A2: REGION | B2: RICE | D2: CORN | F2: HVC | H2: SUGAR | J2: CROPS | L2: FISHERIES | O2: CROPS | R2: FISHERIES | AA2: CROPS | AD2: FISHERIES | BA2: Number of Beneficiaries | BC2: Total Fuel Fund
B3: 100% Subsidy | C3: incremental Cost | D3: 100% Subsidy | E3: incremental Cost | F3: 100% Subsidy | G3: incremental Cost | H3: 100% Subsidy | I3: incremental Cost | J3: 100% Subsidy | K3: incremental Cost | L3: Marine Capture | M3: Aquaculture | N3: Total Cost | O3: Percentage Share | P3: Number of Beneficiaries | Q3: Round | R3: Percentage Share | S3: Number of Beneficiaries | T3: Round | U3: Crop | V3: Fisheries | W3: Crop | X3: Fisheries | Y3: Crop | Z3: Fisheries | AA3: Percentage Share | AB3: Number of Beneficiaries | AC3: Round | AD3: Percentage Share | AE3: Number of Beneficiaries | AF3: Round | AG3: Crop | AJ3: Fisheries | AL3: Total | AM3: Total ('000) | AN3: Percentage Share | AO3: Crop | AQ3: Fisheries | AS3: Total | AT3: Total ('000) | AW3: Crop | AX3: Fisheries | BA3: Crops (Corn) | BB3: Fisheries | BC3: Crops (Corn) | BD3: Fisheries | BE3: Total | BF3: Percentage Share
A4: NCR | L4: =Summary!O83 -> 7.6468604e+09 | M4: =Summary!O104 -> 1.3782781e+08 | N4: =SUM(L4:M4) -> 7.7846882e+09 | O4: =K4/$K$21 -> 0 | P4: =$J$31*O4 -> 0 | Q4: =ROUND(P4, 0) -> 0 | R4: =N4/$N$21 -> 0.091436985 | S4: =R4*$J$32 -> 8818.3603 | T4: =ROUND(S4,0) -> 8818 | U4: =Q4*$I$30 -> 0 | V4: =S4*$I$30 -> 44091802 | W4: =Y4-U4 -> 0 | X4: =Z4-V4 -> 671448.76 | Y4: =Q4*$I$30/0.985 -> 0 | Z4: =S4*$I$30/0.985 -> 44763250 | AA4: =J4/$J$21 -> 0 | AB4: =$M$31*AA4 -> 0 | AC4: =ROUND(AB4, 0) -> 0 | AD4: =N4/$N$21 -> 0.091436985 | AE4: =AD4*$M$32 -> 8561.5149 | AF4: =ROUND(AE4,0)+1 -> 8563 | AG4: =AB4*$L$30 -> 0 | AH4: =ROUND(AG4,0) -> 0 | AI4: =AC4*$L$30 -> 0 | AJ4: =AE4*$L$30 -> 44091802 | AK4: =AF4*$L$30 -> 44099450 | AL4: =AG4+AJ4 -> 44091802 | AM4: =ROUND(AL4/1000,2) -> 44091.8 | AN4: =AL4/$AW$23 -> 0.044091802 | AO4: =(AW4-AG4)*$AQ$24 -> 0 | AP4: =ROUND(AO4,0) -> 0 | AQ4: =(AX4-AJ4)*$AQ$24 -> 637876.32 | AR4: =ROUND(AQ4,0) -> 637876 | AS4: =SUM(AO4:AQ4) -> 637876.32 | AT4: =ROUND(AS4/1000,2) -> 637.88 | AU4: =AQ4+AL4+AO4 -> 44729678 | AV4: =AU4/$AW$23 -> 0.044729678 | AW4: =AB4*$L$30/0.985 -> 0 | AX4: =AE4*$L$30/0.985 -> 44763250 | AY4: =AC4+AF4 -> 8563 | AZ4: =AY4/$AY$21 -> 0.044770345 | BA4: 2124 | BC4: =BA4*3150 -> 6690600 | BD4: =BB4*3150 -> 0 | BE4: =SUM(BC4:BD4) -> 6690600 | BF4: =BE4/$BE$21 -> 0.013381213 | BG4: =AU4-BE4 -> 38039078 | BH4: =BG4/BE4 -> 5.6854509
A5: CAR | B5: =Summary!O3 -> 1.3464882e+08 | C5: 42187777 | D5: =Summary!O23 -> 4.3647774e+08 | E5: 44734828 | F5: =Summary!O43 -> 77694335 | G5: 7967538.3 | H5: =Summary!O63 -> 0 | I5: 0 | J5: =B5+D5+F5+H5 -> 6.488209e+08 | K5: =C5+E5+G5+I5 -> 94890144 | L5: =Summary!O84 -> 50665872 | M5: =Summary!O105 -> 61171774 | N5: =SUM(L5:M5) -> 1.1183765e+08 | O5: =K5/$K$21 -> 0.017546755 | P5: =$J$31*O5 -> 1764.4677 | Q5: =ROUND(P5, 0) -> 1764 | R5: =N5/$N$21 -> 0.0013136168 | S5: =R5*$J$32 -> 126.68775 | T5: =ROUND(S5,0) -> 127 | U5: =Q5*$I$30 -> 8820000 | V5: =S5*$I$30 -> 633438.77 | W5: =Y5-U5 -> 134314.72 | X5: =Z5-V5 -> 9646.2756 | Y5: =Q5*$I$30/0.985 -> 8954314.7 | Z5: =S5*$I$30/0.985 -> 643085.04 | AA5: =J5/$J$21 -> 0.020655452 | AB5: =$M$31*AA5 -> 2016.5749 | AC5: =ROUND(AB5, 0) -> 2017 | AD5: =N5/$N$21 -> 0.0013136168 | AE5: =AD5*$M$32 -> 122.99782 | AF5: =ROUND(AE5,0) -> 123 | AG5: =AB5*$L$30 -> 10385361 | AH5: =ROUND(AG5,0) -> 10385361 | AI5: =AC5*$L$30 -> 10387550 | AJ5: =AE5*$L$30 -> 633438.77 | AK5: =AF5*$L$30 -> 633450 | AL5: =AG5+AJ5 -> 11018799 | AM5: =ROUND(AL5/1000,2) -> 11018.8 | AN5: =AL5/$AW$23 -> 0.011018799 | AO5: =(AW5-AG5)*$AQ$24 -> 150245.07 | AP5: =ROUND(AO5,0) -> 150245 | AQ5: =(AX5-AJ5)*$AQ$24 -> 9163.9618 | AR5: =ROUND(AQ5,0) -> 9164 | AS5: =SUM(AO5:AQ5) -> 309654.03 | AT5: =ROUND(AS5/1000,2) -> 309.65 | AU5: =AQ5+AL5+AO5 -> 11178208 | AV5: =AU5/$AW$23 -> 0.011178208 | AW5: =AB5*$L$30/0.985 -> 10543513 | AX5: =AE5*$L$30/0.985 -> 643085.04 | AY5: =AC5+AF5 -> 2140 | AZ5: =AY5/$AY$21 -> 0.011188665 | BA5: 308 | BB5: 1502 | BC5: =BA5*3150 -> 970200 | BD5: =BB5*3150 -> 4731300 | BE5: =SUM(BC5:BD5) -> 5701500 | BF5: =BE5/$BE$21 -> 0.011403011 | BG5: =AU5-BE5 -> 5476708.4 | BH5: =BG5/BE5 -> 0.96057326
A6: Region I | B6: =Summary!O4 -> 2.2546995e+09 | C6: 2.3149211e+08 | D6: =Summary!O24 -> 1.8089421e+09 | E6: 1.8591463e+08 | F6: =Summary!O44 -> 1.4069454e+08 | G6: 14470301 | H6: =Summary!O64 -> 0 | I6: 0 | J6: =B6+D6+F6+H6 -> 4.2043362e+09 | K6: =C6+E6+G6+I6 -> 4.3187705e+08 | L6: =Summary!O85 -> 4.9169577e+09 | M6: =Summary!O106 -> 1.4567165e+08 | N6: =SUM(L6:M6) -> 5.0626294e+09 | O6: =K6/$K$21 -> 0.079861202 | P6: =$J$31*O6 -> 8030.6874 | Q6: =ROUND(P6, 0) -> 8031 | R6: =N6/$N$21 -> 0.059464369 | S6: =R6*$J$32 -> 5734.8591 | T6: =ROUND(S6,0) -> 5735 | U6: =Q6*$I$30 -> 40155000 | V6: =S6*$I$30 -> 28674296 | W6: =Y6-U6 -> 611497.46 | X6: =Z6-V6 -> 436664.4 | Y6: =Q6*$I$30/0.985 -> 40766497 | Z6: =S6*$I$30/0.985 -> 29110960 | AA6: =J6/$J$21 -> 0.13384659 | AB6: =$M$31*AA6 -> 13067.333 | AC6: =ROUND(AB6, 0) -> 13067 | AD6: =N6/$N$21 -> 0.059464369 | AE6: =AD6*$M$32 -> 5567.8244 | AF6: =ROUND(AE6,0) -> 5568 | AG6: =AB6*$L$30 -> 67296764 | AH6: =ROUND(AG6,0) -> 67296764 | AI6: =AC6*$L$30 -> 67295050 | AJ6: =AE6*$L$30 -> 28674296 | AK6: =AF6*$L$30 -> 28675200 | AL6: =AG6+AJ6 -> 95971060 | AM6: =ROUND(AL6/1000,2) -> 95971.06 | AN6: =AL6/$AW$23 -> 0.09597106 | AO6: =(AW6-AG6)*$AQ$24 -> 973582.63 | AP6: =ROUND(AO6,0) -> 973583 | AQ6: =(AX6-AJ6)*$AQ$24 -> 414831.18 | AR6: =ROUND(AQ6,0) -> 414831 | AS6: =SUM(AO6:AQ6) -> 2361996.8 | AT6: =ROUND(AS6/1000,2) -> 2362 | AU6: =AQ6+AL6+AO6 -> 97359474 | AV6: =AU6/$AW$23 -> 0.097359474 | AW6: =AB6*$L$30/0.985 -> 68321588 | AX6: =AE6*$L$30/0.985 -> 29110960 | AY6: =AC6+AF6 -> 18635 | AZ6: =AY6/$AY$21 -> 0.097430267 | BA6: 5097 | BB6: 12244 | BC6: =BA6*3150 -> 16055550 | BD6: =BB6*3150 -> 38568600 | BE6: =SUM(BC6:BD6) -> 54624150 | BF6: =BE6/$BE$21 -> 0.10924841 | BG6: =AU6-BE6 -> 42735324 | BH6: =BG6/BE6 -> 0.7823522
A7: Region II | B7: =Summary!O5 -> 3.684999e+09 | C7: 3.7852133e+08 | D7: =Summary!O25 -> 2.6001335e+09 | E7: 2.6693659e+08 | F7: =Summary!O45 -> 1.1775532e+09 | G7: 1.2094028e+08 | H7: =Summary!O65 -> 25517722 | I7: 7995138.5 | J7: =B7+D7+F7+H7 -> 7.4882034e+09 | K7: =C7+E7+G7+I7 -> 7.7439334e+08 | L7: =Summary!O86 -> 1.555844e+09 | M7: =Summary!O107 -> 4.7154409e+08 | N7: =SUM(L7:M7) -> 2.027388e+09 | O7: =K7/$K$21 -> 0.14319812 | P7: =$J$31*O7 -> 14399.725 | Q7: =ROUND(P7, 0) -> 14400 | R7: =N7/$N$21 -> 0.023813189 | S7: =R7*$J$32 -> 2296.5902 | T7: =ROUND(S7,0) -> 2297 | U7: =Q7*$I$30 -> 72000000 | V7: =S7*$I$30 -> 11482951 | W7: =Y7-U7 -> 1096446.7 | X7: =Z7-V7 -> 174867.27 | Y7: =Q7*$I$30/0.985 -> 73096447 | Z7: =S7*$I$30/0.985 -> 11657818 | AA7: =J7/$J$21 -> 0.23838971 | AB7: =$M$31*AA7 -> 23273.792 | AC7: =ROUND(AB7, 0) -> 23274 | AD7: =N7/$N$21 -> 0.023813189 | AE7: =AD7*$M$32 -> 2229.6992 | AF7: =ROUND(AE7,0) -> 2230 | AG7: =AB7*$L$30 -> 1.1986003e+08 | AH7: =ROUND(AG7,0) -> 119860031 | AI7: =AC7*$L$30 -> 119861100 | AJ7: =AE7*$L$30 -> 11482951 | AK7: =AF7*$L$30 -> 11484500 | AL7: =AG7+AJ7 -> 1.3134298e+08 | AM7: =ROUND(AL7/1000,2) -> 131342.98 | AN7: =AL7/$AW$23 -> 0.13134298 | AO7: =(AW7-AG7)*$AQ$24 -> 1734015.7 | AP7: =ROUND(AO7,0)+1 -> 1734017 | AQ7: =(AX7-AJ7)*$AQ$24 -> 166123.91 | AR7: =ROUND(AQ7,0)+1 -> 166125 | AS7: =SUM(AO7:AQ7) -> 3634156.6 | AT7: =ROUND(AS7/1000,2) -> 3634.16 | AU7: =AQ7+AL7+AO7 -> 1.3324312e+08 | AV7: =AU7/$AW$23 -> 0.13324312 | AW7: =AB7*$L$30/0.985 -> 1.2168531e+08 | AX7: =AE7*$L$30/0.985 -> 11657818 | AY7: =AC7+AF7 -> 25504 | AZ7: =AY7/$AY$21 -> 0.13334379 | BA7: 2303 | BB7: 16811 | BC7: =BA7*3150 -> 7254450 | BD7: =BB7*3150 -> 52954650 | BE7: =SUM(BC7:BD7) -> 60209100 | BF7: =BE7/$BE$21 -> 0.12041832 | BG7: =AU7-BE7 -> 73034021 | BH7: =BG7/BE7 -> 1.2130064
A8: Region III | B8: =Summary!O6 -> 2.2257412e+09 | C8: 6.309502e+08 | D8: =Summary!O26 -> 9.4410422e+08 | E8: 2.6721089e+08 | F8: =Summary!O46 -> 1.8502946e+08 | G8: 52326329 | H8: =Summary!O66 -> 57481103 | I8: 18009812 | J8: =B8+D8+F8+H8 -> 3.412356e+09 | K8: =C8+E8+G8+I8 -> 9.6849724e+08 | L8: =Summary!O87 -> 3.0758225e+09 | M8: =Summary!O108 -> 496004.75 | N8: =SUM(L8:M8) -> 3.0763185e+09 | O8: =K8/$K$21 -> 0.17909114 | P8: =$J$31*O8 -> 18009.058 | Q8: =ROUND(P8, 0) -> 18009 | R8: =N8/$N$21 -> 0.036133662 | S8: =R8*$J$32 -> 3484.8005 | T8: =ROUND(S8,0) -> 3485 | U8: =Q8*$I$30 -> 90045000 | V8: =S8*$I$30 -> 17424002 | W8: =Y8-U8 -> 1371243.7 | X8: =Z8-V8 -> 265340.14 | Y8: =Q8*$I$30/0.985 -> 91416244 | Z8: =S8*$I$30/0.985 -> 17689343 | AA8: =J8/$J$21 -> 0.10863361 | AB8: =$M$31*AA8 -> 10605.81 | AC8: =ROUND(AB8, 0) -> 10606 | AD8: =N8/$N$21 -> 0.036133662 | AE8: =AD8*$M$32 -> 3383.3015 | AF8: =ROUND(AE8,0) -> 3383 | AG8: =AB8*$L$30 -> 54619923 | AH8: =ROUND(AG8,0) -> 54619923 | AI8: =AC8*$L$30 -> 54620900 | AJ8: =AE8*$L$30 -> 17424002 | AK8: =AF8*$L$30 -> 17422450 | AL8: =AG8+AJ8 -> 72043925 | AM8: =ROUND(AL8/1000,2) -> 72043.93 | AN8: =AL8/$AW$23 -> 0.072043925 | AO8: =(AW8-AG8)*$AQ$24 -> 790186.7 | AP8: =ROUND(AO8,0) -> 790187 | AQ8: =(AX8-AJ8)*$AQ$24 -> 252073.13 | AR8: =ROUND(AQ8,0) -> 252073 | AS8: =SUM(AO8:AQ8) -> 1832446.8 | AT8: =ROUND(AS8/1000,2) -> 1832.45 | AU8: =AQ8+AL8+AO8 -> 73086185 | AV8: =AU8/$AW$23 -> 0.073086185 | AW8: =AB8*$L$30/0.985 -> 55451698 | AX8: =AE8*$L$30/0.985 -> 17689343 | AY8: =AC8+AF8 -> 13989 | AZ8: =AY8/$AY$21 -> 0.073139362 | BA8: 7049 | BB8: 2255 | BC8: =BA8*3150 -> 22204350 | BD8: =BB8*3150 -> 7103250 | BE8: =SUM(BC8:BD8) -> 29307600 | BF8: =BE8/$BE$21 -> 0.058615259 | BG8: =AU8-BE8 -> 43778585 | BH8: =BG8/BE8 -> 1.4937622
A9: CALABARZON | B9: =Summary!O7 -> 7.4303175e+08 | C9: 75093505 | D9: =Summary!O27 -> 4.5268078e+08 | E9: 45835416 | F9: =Summary!O47 -> 3.5807241e+08 | G9: 36278975 | H9: =Summary!O67 -> 1.6752954e+08 | I9: 52489867 | J9: =B9+D9+F9+H9 -> 1.7213145e+09 | K9: =C9+E9+G9+I9 -> 2.0969776e+08 | L9: =Summary!O88 -> 2.6072244e+09 | M9: =Summary!O109 -> 4.6938723e+09 | N9: =SUM(L9:M9) -> 7.3010966e+09 | O9: =K9/$K$21 -> 0.038776581 | P9: =$J$31*O9 -> 3899.2977 | Q9: =ROUND(P9, 0) -> 3899 | R9: =N9/$N$21 -> 0.085756841 | S9: =R9*$J$32 -> 8270.5562 | T9: =ROUND(S9,0) -> 8271 | U9: =Q9*$I$30 -> 19495000 | V9: =S9*$I$30 -> 41352781 | W9: =Y9-U9 -> 296878.17 | X9: =Z9-V9 -> 629737.78 | Y9: =Q9*$I$30/0.985 -> 19791878 | Z9: =S9*$I$30/0.985 -> 41982519 | AA9: =J9/$J$21 -> 0.054798679 | AB9: =$M$31*AA9 -> 5349.9502 | AC9: =ROUND(AB9, 0) -> 5350 | AD9: =N9/$N$21 -> 0.085756841 | AE9: =AD9*$M$32 -> 8029.6662 | AF9: =ROUND(AE9,0) -> 8030 | AG9: =AB9*$L$30 -> 27552244 | AH9: =ROUND(AG9,0) -> 27552244 | AI9: =AC9*$L$30 -> 27552500 | AJ9: =AE9*$L$30 -> 41352781 | AK9: =AF9*$L$30 -> 41354500 | AL9: =AG9+AJ9 -> 68905025 | AM9: =ROUND(AL9/1000,2) -> 68905.02 | AN9: =AL9/$AW$23 -> 0.068905025 | AO9: =(AW9-AG9)*$AQ$24 -> 398598.45 | AP9: =ROUND(AO9,0) -> 398598 | AQ9: =(AX9-AJ9)*$AQ$24 -> 598250.89 | AR9: =ROUND(AQ9,0) -> 598251 | AS9: =SUM(AO9:AQ9) -> 1395447.3 | AT9: =ROUND(AS9/1000,2) -> 1395.45 | AU9: =AQ9+AL9+AO9 -> 69901874 | AV9: =AU9/$AW$23 -> 0.069901874 | AW9: =AB9*$L$30/0.985 -> 27971821 | AX9: =AE9*$L$30/0.985 -> 41982519 | AY9: =AC9+AF9 -> 13380 | AZ9: =AY9/$AY$21 -> 0.069955298 | BA9: 6838 | BB9: 1950 | BC9: =BA9*3150 -> 21539700 | BD9: =BB9*3150 -> 6142500 | BE9: =SUM(BC9:BD9) -> 27682200 | BF9: =BE9/$BE$21 -> 0.055364455 | BG9: =AU9-BE9 -> 42219674 | BH9: =BG9/BE9 -> 1.525156
A10: MIMAROPA | B10: =Summary!O8 -> 7.1749904e+08 | C10: 58064177 | D10: =Summary!O28 -> 5.7553932e+08 | E10: 46671110 | F10: =Summary!O48 -> 36081181 | G10: 2991193.7 | H10: =Summary!O68 -> 0 | I10: 0 | J10: =B10+D10+F10+H10 -> 1.3291195e+09 | K10: =C10+E10+G10+I10 -> 1.0772648e+08 | L10: =Summary!O89 -> 3.8765346e+09 | M10: =Summary!O110 -> 2.3700845e+08 | N10: =SUM(L10:M10) -> 4.1135431e+09 | O10: =K10/$K$21 -> 0.019920406 | P10: =$J$31*O10 -> 2003.1574 | Q10: =ROUND(P10, 0) -> 2003 | R10: =N10/$N$21 -> 0.04831664 | S10: =R10*$J$32 -> 4659.7506 | T10: =ROUND(S10,0) -> 4660 | U10: =Q10*$I$30 -> 10015000 | V10: =S10*$I$30 -> 23298753 | W10: =Y10-U10 -> 152512.69 | X10: =Z10-V10 -> 354803.34 | Y10: =Q10*$I$30/0.985 -> 10167513 | Z10: =S10*$I$30/0.985 -> 23653556 | AA10: =J10/$J$21 -> 0.042313009 | AB10: =$M$31*AA10 -> 4130.9845 | AC10: =ROUND(AB10, 0) -> 4131 | AD10: =N10/$N$21 -> 0.04831664 | AE10: =AD10*$M$32 -> 4524.0297 | AF10: =ROUND(AE10,0) -> 4524 | AG10: =AB10*$L$30 -> 21274570 | AH10: =ROUND(AG10,0) -> 21274570 | AI10: =AC10*$L$30 -> 21274650 | AJ10: =AE10*$L$30 -> 23298753 | AK10: =AF10*$L$30 -> 23298600 | AL10: =AG10+AJ10 -> 44573323 | AM10: =ROUND(AL10/1000,2) -> 44573.32 | AN10: =AL10/$AW$23 -> 0.044573323 | AO10: =(AW10-AG10)*$AQ$24 -> 307779.31 | AP10: =ROUND(AO10,0) -> 307779 | AQ10: =(AX10-AJ10)*$AQ$24 -> 337063.18 | AR10: =ROUND(AQ10,0) -> 337063 | AS10: =SUM(AO10:AQ10) -> 952621.49 | AT10: =ROUND(AS10/1000,2) -> 952.62 | AU10: =AQ10+AL10+AO10 -> 45218166 | AV10: =AU10/$AW$23 -> 0.045218166 | AW10: =AB10*$L$30/0.985 -> 21598548 | AX10: =AE10*$L$30/0.985 -> 23653556 | AY10: =AC10+AF10 -> 8655 | AZ10: =AY10/$AY$21 -> 0.045251353 | BA10: 10148 | BB10: 1102 | BC10: =BA10*3150 -> 31966200 | BD10: =BB10*3150 -> 3471300 | BE10: =SUM(BC10:BD10) -> 35437500 | BF10: =BE10/$BE$21 -> 0.070875071 | BG10: =AU10-BE10 -> 9780665.6 | BH10: =BG10/BE10 -> 0.27599762
A11: Region V | B11: =Summary!O9 -> 8.8997404e+08 | C11: 91261356 | D11: =Summary!O29 -> 4.2834082e+08 | E11: 43862157 | F11: =Summary!O49 -> 1.27557e+08 | G11: 12989559 | H11: =Summary!O69 -> 17283217 | I11: 5415127.5 | J11: =B11+D11+F11+H11 -> 1.4631551e+09 | K11: =C11+E11+G11+I11 -> 1.535282e+08 | L11: =Summary!O90 -> 4.3021057e+09 | M11: =Summary!O111 -> 3.7074756e+08 | N11: =SUM(L11:M11) -> 4.6728533e+09 | O11: =K11/$K$21 -> 0.0283899 | P11: =$J$31*O11 -> 2854.8333 | Q11: =ROUND(P11, 0) -> 2855 | R11: =N11/$N$21 -> 0.054886157 | S11: =R11*$J$32 -> 5293.3275 | T11: =ROUND(S11,0) -> 5293 | U11: =Q11*$I$30 -> 14275000 | V11: =S11*$I$30 -> 26466638 | W11: =Y11-U11 -> 217385.79 | X11: =Z11-V11 -> 403045.24 | Y11: =Q11*$I$30/0.985 -> 14492386 | Z11: =S11*$I$30/0.985 -> 26869683 | AA11: =J11/$J$21 -> 0.046580079 | AB11: =$M$31*AA11 -> 4547.5751 | AC11: =ROUND(AB11, 0) -> 4548 | AD11: =N11/$N$21 -> 0.054886157 | AE11: =AD11*$M$32 -> 5139.1529 | AF11: =ROUND(AE11,0) -> 5139 | AG11: =AB11*$L$30 -> 23420012 | AH11: =ROUND(AG11,0) -> 23420012 | AI11: =AC11*$L$30 -> 23422200 | AJ11: =AE11*$L$30 -> 26466638 | AK11: =AF11*$L$30 -> 26465850 | AL11: =AG11+AJ11 -> 49886650 | AM11: =ROUND(AL11/1000,2) -> 49886.65 | AN11: =AL11/$AW$23 -> 0.04988665 | AO11: =(AW11-AG11)*$AQ$24 -> 338817.43 | AP11: =ROUND(AO11,0) -> 338817 | AQ11: =(AX11-AJ11)*$AQ$24 -> 382892.98 | AR11: =ROUND(AQ11,0) -> 382893 | AS11: =SUM(AO11:AQ11) -> 1060527.4 | AT11: =ROUND(AS11/1000,2) -> 1060.53 | AU11: =AQ11+AL11+AO11 -> 50608360 | AV11: =AU11/$AW$23 -> 0.05060836 | AW11: =AB11*$L$30/0.985 -> 23776662 | AX11: =AE11*$L$30/0.985 -> 26869683 | AY11: =AC11+AF11 -> 9687 | AZ11: =AY11/$AY$21 -> 0.050647008 | BA11: 6970 | BB11: 3880 | BC11: =BA11*3150 -> 21955500 | BD11: =BB11*3150 -> 12222000 | BE11: =SUM(BC11:BD11) -> 34177500 | BF11: =BE11/$BE$21 -> 0.068355068 | BG11: =AU11-BE11 -> 16430860 | BH11: =BG11/BE11 -> 0.48075079
A12: Region VI | B12: =Summary!O10 -> 5.4913327e+08 | C12: 1.1549237e+08 | D12: =Summary!O30 -> 3.6150732e+08 | E12: 78972052 | F12: =Summary!O50 -> 38811996 | G12: 9042275.4 | H12: =Summary!O70 -> 2.4040647e+08 | I12: 6.2324356e+08 | J12: =B12+D12+F12+H12 -> 1.189859e+09 | K12: =C12+E12+G12+I12 -> 8.2675026e+08 | L12: =Summary!O91 -> 5.6856404e+09 | M12: =Summary!O112 -> 1.2449312e+09 | N12: =SUM(L12:M12) -> 6.9305716e+09 | O12: =K12/$K$21 -> 0.15287978 | P12: =$J$31*O12 -> 15373.294 | Q12: =ROUND(P12, 0) -> 15373 | R12: =N12/$N$21 -> 0.081404747 | S12: =R12*$J$32 -> 7850.8318 | T12: =ROUND(S12,0) -> 7851 | U12: =Q12*$I$30 -> 76865000 | V12: =S12*$I$30 -> 39254159 | W12: =Y12-U12 -> 1170533 | X12: =Z12-V12 -> 597779.07 | Y12: =Q12*$I$30/0.985 -> 78035533 | Z12: =S12*$I$30/0.985 -> 39851938 | AA12: =J12/$J$21 -> 0.0378796 | AB12: =$M$31*AA12 -> 3698.1544 | AC12: =ROUND(AB12, 0) -> 3698 | AD12: =N12/$N$21 -> 0.081404747 | AE12: =AD12*$M$32 -> 7622.1668 | AF12: =ROUND(AE12,0) -> 7622 | AG12: =AB12*$L$30 -> 19045495 | AH12: =ROUND(AG12,0) -> 19045495 | AI12: =AC12*$L$30 -> 19044700 | AJ12: =AE12*$L$30 -> 39254159 | AK12: =AF12*$L$30 -> 39253300 | AL12: =AG12+AJ12 -> 58299654 | AM12: =ROUND(AL12/1000,2) -> 58299.65 | AN12: =AL12/$AW$23 -> 0.058299654 | AO12: =(AW12-AG12)*$AQ$24 -> 275531.28 | AP12: =ROUND(AO12,0) -> 275531 | AQ12: =(AX12-AJ12)*$AQ$24 -> 567890.12 | AR12: =ROUND(AQ12,0) -> 567890 | AS12: =SUM(AO12:AQ12) -> 1118952.4 | AT12: =ROUND(AS12/1000,2) -> 1118.95 | AU12: =AQ12+AL12+AO12 -> 59143076 | AV12: =AU12/$AW$23 -> 0.059143076 | AW12: =AB12*$L$30/0.985 -> 19335528 | AX12: =AE12*$L$30/0.985 -> 39851938 | AY12: =AC12+AF12 -> 11320 | AZ12: =AY12/$AY$21 -> 0.059184901 | BA12: 7116 | BB12: 3222 | BC12: =BA12*3150 -> 22415400 | BD12: =BB12*3150 -> 10149300 | BE12: =SUM(BC12:BD12) -> 32564700 | BF12: =BE12/$BE$21 -> 0.065129465 | BG12: =AU12-BE12 -> 26578376 | BH12: =BG12/BE12 -> 0.81617136
A13: Region VII | B13: =Summary!O12 -> 1.9580987e+08 | C13: 21680404 | D13: =Summary!O32 -> 1.7481941e+08 | E13: 20788807 | F13: =Summary!O52 -> 46814002 | G13: 10248720 | H13: =Summary!O72 -> 26070633 | I13: 1.0976707e+08 | J13: =B13+D13+F13+H13 -> 4.4351391e+08 | K13: =C13+E13+G13+I13 -> 1.62485e+08 | L13: =Summary!O93 -> 4.1585267e+09 | M13: =Summary!O114 -> 2.2551134e+08 | N13: =SUM(L13:M13) -> 4.384038e+09 | O13: =K13/$K$21 -> 0.030046161 | P13: =$J$31*O13 -> 3021.3836 | Q13: =ROUND(P13, 0) -> 3021 | R13: =N13/$N$21 -> 0.051493806 | S13: =R13*$J$32 -> 4966.1626 | T13: =ROUND(S13,0) -> 4966 | U13: =Q13*$I$30 -> 15105000 | V13: =S13*$I$30 -> 24830813 | W13: =Y13-U13 -> 230025.38 | X13: =Z13-V13 -> 378134.21 | Y13: =Q13*$I$30/0.985 -> 15335025 | Z13: =S13*$I$30/0.985 -> 25208947 | AA13: =J13/$J$21 -> 0.014119428 | AB13: =$M$31*AA13 -> 1378.4683 | AC13: =ROUND(AB13, 0) -> 1378 | AD13: =N13/$N$21 -> 0.051493806 | AE13: =AD13*$M$32 -> 4821.5171 | AF13: =ROUND(AE13,0) -> 4822 | AG13: =AB13*$L$30 -> 7099111.5 | AH13: =ROUND(AG13,0) -> 7099112 | AI13: =AC13*$L$30 -> 7096700 | AJ13: =AE13*$L$30 -> 24830813 | AK13: =AF13*$L$30 -> 24833300 | AL13: =AG13+AJ13 -> 31929924 | AM13: =ROUND(AL13/1000,2) -> 31929.92 | AN13: =AL13/$AW$23 -> 0.031929924 | AO13: =(AW13-AG13)*$AQ$24 -> 102702.88 | AP13: =ROUND(AO13,0) -> 102703 | AQ13: =(AX13-AJ13)*$AQ$24 -> 359227.5 | AR13: =ROUND(AQ13,0) -> 359227 | AS13: =SUM(AO13:AQ13) -> 564633.38 | AT13: =ROUND(AS13/1000,2) -> 564.63 | AU13: =AQ13+AL13+AO13 -> 32391855 | AV13: =AU13/$AW$23 -> 0.032391855 | AW13: =AB13*$L$30/0.985 -> 7207219.8 | AX13: =AE13*$L$30/0.985 -> 25208947 | AY13: =AC13+AF13 -> 6200 | AZ13: =AY13/$AY$21 -> 0.032415758 | BA13: 5175 | BB13: 2642 | BC13: =BA13*3150 -> 16301250 | BD13: =BB13*3150 -> 8322300 | BE13: =SUM(BC13:BD13) -> 24623550 | BF13: =BE13/$BE$21 -> 0.049247149 | BG13: =AU13-BE13 -> 7768304.8 | BH13: =BG13/BE13 -> 0.31548273
A14: Region VIII | B14: =Summary!O13 -> 4.8279169e+08 | C14: 49522856 | D14: =Summary!O33 -> 2.0646801e+08 | E14: 21280945 | F14: =Summary!O53 -> 1.2774671e+08 | G14: 13326601 | H14: =Summary!O73 -> 42054849 | I14: 13176503 | J14: =B14+D14+F14+H14 -> 8.5906126e+08 | K14: =C14+E14+G14+I14 -> 97306905 | L14: =Summary!O94 -> 3.2270356e+09 | M14: =Summary!O115 -> 45339595 | N14: =SUM(L14:M14) -> 3.2723752e+09 | O14: =K14/$K$21 -> 0.017993654 | P14: =$J$31*O14 -> 1809.407 | Q14: =ROUND(P14, 0) -> 1809 | R14: =N14/$N$21 -> 0.038436494 | S14: =R14*$J$32 -> 3706.8901 | T14: =ROUND(S14,0) -> 3707 | U14: =Q14*$I$30 -> 9045000 | V14: =S14*$I$30 -> 18534450 | W14: =Y14-U14 -> 137741.12 | X14: =Z14-V14 -> 282250.51 | Y14: =Q14*$I$30/0.985 -> 9182741.1 | Z14: =S14*$I$30/0.985 -> 18816701 | AA14: =J14/$J$21 -> 0.027348531 | AB14: =$M$31*AA14 -> 2670.0147 | AC14: =ROUND(AB14, 0) -> 2670 | AD14: =N14/$N$21 -> 0.038436494 | AE14: =AD14*$M$32 -> 3598.9224 | AF14: =ROUND(AE14,0) -> 3599 | AG14: =AB14*$L$30 -> 13750576 | AH14: =ROUND(AG14,0) -> 13750576 | AI14: =AC14*$L$30 -> 13750500 | AJ14: =AE14*$L$30 -> 18534450 | AK14: =AF14*$L$30 -> 18534850 | AL14: =AG14+AJ14 -> 32285026 | AM14: =ROUND(AL14/1000,2) -> 32285.03 | AN14: =AL14/$AW$23 -> 0.032285026 | AO14: =(AW14-AG14)*$AQ$24 -> 198929.65 | AP14: =ROUND(AO14,0) -> 198930 | AQ14: =(AX14-AJ14)*$AQ$24 -> 268137.99 | AR14: =ROUND(AQ14,0) -> 268138 | AS14: =SUM(AO14:AQ14) -> 665997.64 | AT14: =ROUND(AS14/1000,2) -> 666 | AU14: =AQ14+AL14+AO14 -> 32752094 | AV14: =AU14/$AW$23 -> 0.032752094 | AW14: =AB14*$L$30/0.985 -> 13959975 | AX14: =AE14*$L$30/0.985 -> 18816701 | AY14: =AC14+AF14 -> 6269 | AZ14: =AY14/$AY$21 -> 0.032776514 | BA14: 5898 | BB14: 967 | BC14: =BA14*3150 -> 18578700 | BD14: =BB14*3150 -> 3046050 | BE14: =SUM(BC14:BD14) -> 21624750 | BF14: =BE14/$BE$21 -> 0.043249543 | BG14: =AU14-BE14 -> 11127344 | BH14: =BG14/BE14 -> 0.5145652
A15: Region IX | B15: =Summary!O14 -> 3.1117104e+08 | C15: 15046555 | D15: =Summary!O34 -> 2.885325e+08 | E15: 14120737 | F15: =Summary!O54 -> 45373692 | G15: 2267882.4 | H15: =Summary!O74 -> 0 | I15: 0 | J15: =B15+D15+F15+H15 -> 6.4507723e+08 | K15: =C15+E15+G15+I15 -> 31435175 | L15: =Summary!O95 -> 6000337824 | M15: =Summary!O116 -> 4.1712197e+08 | N15: =SUM(L15:M15) -> 6.4174598e+09 | O15: =K15/$K$21 -> 0.0058128832 | P15: =$J$31*O15 -> 584.53225 | Q15: =ROUND(P15, 0) -> 585 | R15: =N15/$N$21 -> 0.075377865 | S15: =R15*$J$32 -> 7269.5876 | T15: =ROUND(S15,0) -> 7270 | U15: =Q15*$I$30 -> 2925000 | V15: =S15*$I$30 -> 36347938 | W15: =Y15-U15 -> 44543.147 | X15: =Z15-V15 -> 553521.9 | Y15: =Q15*$I$30/0.985 -> 2969543.1 | Z15: =S15*$I$30/0.985 -> 36901460 | AA15: =J15/$J$21 -> 0.020536271 | AB15: =$M$31*AA15 -> 2004.9393 | AC15: =ROUND(AB15, 0) -> 2005 | AD15: =N15/$N$21 -> 0.075377865 | AE15: =AD15*$M$32 -> 7057.8521 | AF15: =ROUND(AE15,0) -> 7058 | AG15: =AB15*$L$30 -> 10325438 | AH15: =ROUND(AG15,0) -> 10325438 | AI15: =AC15*$L$30 -> 10325750 | AJ15: =AE15*$L$30 -> 36347938 | AK15: =AF15*$L$30 -> 36348700 | AL15: =AG15+AJ15 -> 46673376 | AM15: =ROUND(AL15/1000,2) -> 46673.38 | AN15: =AL15/$AW$23 -> 0.046673376 | AO15: =(AW15-AG15)*$AQ$24 -> 149378.16 | AP15: =ROUND(AO15,0) -> 149378 | AQ15: =(AX15-AJ15)*$AQ$24 -> 525845.81 | AR15: =ROUND(AQ15,0) -> 525846 | AS15: =SUM(AO15:AQ15) -> 824601.96 | AT15: =ROUND(AS15/1000,2) -> 824.6 | AU15: =AQ15+AL15+AO15 -> 47348600 | AV15: =AU15/$AW$23 -> 0.0473486 | AW15: =AB15*$L$30/0.985 -> 10482678 | AX15: =AE15*$L$30/0.985 -> 36901460 | AY15: =AC15+AF15 -> 9063 | AZ15: =AY15/$AY$21 -> 0.047384519 | BA15: 9380 | BB15: 5156 | BC15: =BA15*3150 -> 29547000 | BD15: =BB15*3150 -> 16241400 | BE15: =SUM(BC15:BD15) -> 45788400 | BF15: =BE15/$BE$21 -> 0.091576892 | BG15: =AU15-BE15 -> 1560199.8 | BH15: =BG15/BE15 -> 0.034074128
A16: Region X | B16: =Summary!O15 -> 1.024204e+09 | C16: 83310936 | D16: =Summary!O35 -> 1.0300183e+09 | E16: 83769727 | F16: =Summary!O55 -> 91685105 | G16: 7410100.9 | H16: =Summary!O75 -> 5.1693564e+08 | I16: 1.6196477e+08 | J16: =B16+D16+F16+H16 -> 2.662843e+09 | K16: =C16+E16+G16+I16 -> 3.3645554e+08 | L16: =Summary!O96 -> 3.76597e+09 | M16: =Summary!O117 -> 1.2580374e+08 | N16: =SUM(L16:M16) -> 3.8917737e+09 | O16: =K16/$K$21 -> 0.062216188 | P16: =$J$31*O16 -> 6256.3391 | Q16: =ROUND(P16, 0) -> 6256 | R16: =N16/$N$21 -> 0.045711793 | S16: =R16*$J$32 -> 4408.5341 | T16: =ROUND(S16,0) -> 4409 | U16: =Q16*$I$30 -> 31280000 | V16: =S16*$I$30 -> 22042670 | W16: =Y16-U16 -> 476345.18 | X16: =Z16-V16 -> 335675.18 | Y16: =Q16*$I$30/0.985 -> 31756345 | Z16: =S16*$I$30/0.985 -> 22378346 | AA16: =J16/$J$21 -> 0.084772586 | AB16: =$M$31*AA16 -> 8276.2784 | AC16: =ROUND(AB16, 0) -> 8276 | AD16: =N16/$N$21 -> 0.045711793 | AE16: =AD16*$M$32 -> 4280.1302 | AF16: =ROUND(AE16,0) -> 4280 | AG16: =AB16*$L$30 -> 42622834 | AH16: =ROUND(AG16,0) -> 42622834 | AI16: =AC16*$L$30 -> 42621400 | AJ16: =AE16*$L$30 -> 22042670 | AK16: =AF16*$L$30 -> 22042000 | AL16: =AG16+AJ16 -> 64665504 | AM16: =ROUND(AL16/1000,2) -> 64665.5 | AN16: =AL16/$AW$23 -> 0.064665504 | AO16: =(AW16-AG16)*$AQ$24 -> 616624.75 | AP16: =ROUND(AO16,0) -> 616625 | AQ16: =(AX16-AJ16)*$AQ$24 -> 318891.42 | AR16: =ROUND(AQ16,0) -> 318891 | AS16: =SUM(AO16:AQ16) -> 1552141.2 | AT16: =ROUND(AS16/1000,2) -> 1552.14 | AU16: =AQ16+AL16+AO16 -> 65601020 | AV16: =AU16/$AW$23 -> 0.06560102 | AW16: =AB16*$L$30/0.985 -> 43271912 | AX16: =AE16*$L$30/0.985 -> 22378346 | AY16: =AC16+AF16 -> 12556 | AZ16: =AY16/$AY$21 -> 0.065647139 | BA16: 2326 | BB16: 9585 | BC16: =BA16*3150 -> 7326900 | BD16: =BB16*3150 -> 30192750 | BE16: =SUM(BC16:BD16) -> 37519650 | BF16: =BE16/$BE$21 -> 0.075039375 | BG16: =AU16-BE16 -> 28081370 | BH16: =BG16/BE16 -> 0.74844436
A17: Region XI | B17: =Summary!O16 -> 4.6885753e+08 | C17: 57211541 | D17: =Summary!O36 -> 3.5572435e+08 | E17: 44505567 | F17: =Summary!O56 -> 94748857 | G17: 11908132 | H17: =Summary!O76 -> 44810070 | I17: 14039761 | J17: =B17+D17+F17+H17 -> 9.6414081e+08 | K17: =C17+E17+G17+I17 -> 1.27665e+08 | L17: =Summary!O97 -> 3.7682714e+09 | M17: =Summary!O118 -> 1.4800479e+08 | N17: =SUM(L17:M17) -> 3.9162762e+09 | O17: =K17/$K$21 -> 0.023607368 | P17: =$J$31*O17 -> 2373.9111 | Q17: =ROUND(P17, 0) -> 2374 | R17: =N17/$N$21 -> 0.045999593 | S17: =R17*$J$32 -> 4436.29 | T17: =ROUND(S17,0) -> 4436 | U17: =Q17*$I$30 -> 11870000 | V17: =S17*$I$30 -> 22181450 | W17: =Y17-U17 -> 180761.42 | X17: =Z17-V17 -> 337788.58 | Y17: =Q17*$I$30/0.985 -> 12050761 | Z17: =S17*$I$30/0.985 -> 22519239 | AA17: =J17/$J$21 -> 0.030693777 | AB17: =$M$31*AA17 -> 2996.6084 | AC17: =ROUND(AB17, 0) -> 2997 | AD17: =N17/$N$21 -> 0.045999593 | AE17: =AD17*$M$32 -> 4307.0777 | AF17: =ROUND(AE17,0) -> 4307 | AG17: =AB17*$L$30 -> 15432533 | AH17: =ROUND(AG17,0) -> 15432533 | AI17: =AC17*$L$30 -> 15434550 | AJ17: =AE17*$L$30 -> 22181450 | AK17: =AF17*$L$30 -> 22181050 | AL17: =AG17+AJ17 -> 37613983 | AM17: =ROUND(AL17/1000,2) -> 37613.98 | AN17: =AL17/$AW$23 -> 0.037613983 | AO17: =(AW17-AG17)*$AQ$24 -> 223262.53 | AP17: =ROUND(AO17,0) -> 223263 | AQ17: =(AX17-AJ17)*$AQ$24 -> 320899.15 | AR17: =ROUND(AQ17,0) -> 320899 | AS17: =SUM(AO17:AQ17) -> 767424.69 | AT17: =ROUND(AS17/1000,2) -> 767.42 | AU17: =AQ17+AL17+AO17 -> 38158145 | AV17: =AU17/$AW$23 -> 0.038158145 | AW17: =AB17*$L$30/0.985 -> 15667546 | AX17: =AE17*$L$30/0.985 -> 22519239 | AY17: =AC17+AF17 -> 7304 | AZ17: =AY17/$AY$21 -> 0.038187855 | BA17: 2743 | BB17: 3545 | BC17: =BA17*3150 -> 8640450 | BD17: =BB17*3150 -> 11166750 | BE17: =SUM(BC17:BD17) -> 19807200 | BF17: =BE17/$BE$21 -> 0.03961444 | BG17: =AU17-BE17 -> 18350945 | BH17: =BG17/BE17 -> 0.9264785
A18: Region XII | B18: =Summary!O17 -> 1.0584183e+09 | C18: 3.6278962e+08 | D18: =Summary!O37 -> 8.8847186e+08 | E18: 3.0457911e+08 | F18: =Summary!O57 -> 4.4897181e+08 | G18: 1.5394567e+08 | H18: =Summary!O77 -> 91610002 | I18: 28702980 | J18: =B18+D18+F18+H18 -> 2.487472e+09 | K18: =C18+E18+G18+I18 -> 8.5001738e+08 | L18: =Summary!O98 -> 3.9689602e+09 | M18: =Summary!O119 -> 97324137 | N18: =SUM(L18:M18) -> 4.0662843e+09 | O18: =K18/$K$21 -> 0.15718226 | P18: =$J$31*O18 -> 15805.943 | Q18: =ROUND(P18, 0) -> 15806 | R18: =N18/$N$21 -> 0.047761551 | S18: =R18*$J$32 -> 4606.2167 | T18: =ROUND(S18,0) -> 4606 | U18: =Q18*$I$30 -> 79030000 | V18: =S18*$I$30 -> 23031083 | W18: =Y18-U18 -> 1203502.5 | X18: =Z18-V18 -> 350727.16 | Y18: =Q18*$I$30/0.985 -> 80233503 | Z18: =S18*$I$30/0.985 -> 23381810 | AA18: =J18/$J$21 -> 0.079189586 | AB18: =$M$31*AA18 -> 7731.2146 | AC18: =ROUND(AB18, 0) -> 7731 | AD18: =N18/$N$21 -> 0.047761551 | AE18: =AD18*$M$32 -> 4472.055 | AF18: =ROUND(AE18,0) -> 4472 | AG18: =AB18*$L$30 -> 39815755 | AH18: =ROUND(AG18,0) -> 39815755 | AI18: =AC18*$L$30 -> 39814650 | AJ18: =AE18*$L$30 -> 23031083 | AK18: =AF18*$L$30 -> 23030800 | AL18: =AG18+AJ18 -> 62846838 | AM18: =ROUND(AL18/1000,2) -> 62846.84 | AN18: =AL18/$AW$23 -> 0.062846838 | AO18: =(AW18-AG18)*$AQ$24 -> 576014.73 | AP18: =ROUND(AO18,0) -> 576015 | AQ18: =(AX18-AJ18)*$AQ$24 -> 333190.8 | AR18: =ROUND(AQ18,0) -> 333191 | AS18: =SUM(AO18:AQ18) -> 1485220.5 | AT18: =ROUND(AS18/1000,2) -> 1485.22 | AU18: =AQ18+AL18+AO18 -> 63756044 | AV18: =AU18/$AW$23 -> 0.063756044 | AW18: =AB18*$L$30/0.985 -> 40422086 | AX18: =AE18*$L$30/0.985 -> 23381810 | AY18: =AC18+AF18 -> 12203 | AZ18: =AY18/$AY$21 -> 0.063801532 | BA18: 3675 | BB18: 12888 | BC18: =BA18*3150 -> 11576250 | BD18: =BB18*3150 -> 40597200 | BE18: =SUM(BC18:BD18) -> 52173450 | BF18: =BE18/$BE$21 -> 0.104347 | BG18: =AU18-BE18 -> 11582594 | BH18: =BG18/BE18 -> 0.22200169
A19: Region XIII | B19: =Summary!O18 -> 1.0555844e+09 | C19: 1.4920485e+08 | D19: =Summary!O38 -> 3.8563699e+08 | E19: 39267522 | F19: =Summary!O58 -> 4.083696e+08 | G19: 41974786 | H19: =Summary!O78 -> 0 | I19: 0 | J19: =B19+D19+F19+H19 -> 1.849591e+09 | K19: =C19+E19+G19+I19 -> 2.3044716e+08 | L19: =Summary!O99 -> 7.9808629e+09 | M19: =Summary!O120 -> 95099496 | N19: =SUM(L19:M19) -> 8.0759624e+09 | O19: =K19/$K$21 -> 0.042613487 | P19: =$J$31*O19 -> 4285.1296 | Q19: =ROUND(P19, 0) -> 4285 | R19: =N19/$N$21 -> 0.094858219 | S19: =R19*$J$32 -> 9148.3108 | T19: =ROUND(S19,0) -> 9148 | U19: =Q19*$I$30 -> 21425000 | V19: =S19*$I$30 -> 45741554 | W19: =Y19-U19 -> 326269.04 | X19: =Z19-V19 -> 696571.89 | Y19: =Q19*$I$30/0.985 -> 21751269 | Z19: =S19*$I$30/0.985 -> 46438126 | AA19: =J19/$J$21 -> 0.058882408 | AB19: =$M$31*AA19 -> 5748.6414 | AC19: =ROUND(AB19, 0) -> 5749 | AD19: =N19/$N$21 -> 0.094858219 | AE19: =AD19*$M$32 -> 8881.8551 | AF19: =ROUND(AE19,0) -> 8882 | AG19: =AB19*$L$30-0.01 -> 29605503 | AH19: =ROUND(AG19,0) -> 29605503 | AI19: =AC19*$L$30 -> 29607350 | AJ19: =AE19*$L$30 -> 45741554 | AK19: =AF19*$L$30 -> 45742300 | AL19: =AG19+AJ19 -> 75347057 | AM19: =ROUND(AL19/1000,2) -> 75347.06 | AN19: =AL19/$AW$23 -> 0.075347057 | AO19: =(AW19-AG19)*$AQ$24 -> 428302.97 | AP19: =ROUND(AO19,0) -> 428303 | AQ19: =(AX19-AJ19)*$AQ$24 -> 661743.29 | AR19: =ROUND(AQ19,0) -> 661743 | AS19: =SUM(AO19:AQ19) -> 1518349.3 | AT19: =ROUND(AS19/1000,2) -> 1518.35 | AU19: =AQ19+AL19+AO19 -> 76437103 | AV19: =AU19/$AW$23 -> 0.076437103 | AW19: =AB19*$L$30/0.985 -> 30056348 | AX19: =AE19*$L$30/0.985 -> 46438126 | AY19: =AC19+AF19 -> 14631 | AZ19: =AY19/$AY$21 -> 0.076495961 | BA19: 2215 | BB19: 1616 | BC19: =BA19*3150 -> 6977250 | BD19: =BB19*3150 -> 5090400 | BE19: =SUM(BC19:BD19) -> 12067650 | BF19: =BE19/$BE$21 -> 0.024135324 | BG19: =AU19-BE19 -> 64369453 | BH19: =BG19/BE19 -> 5.3340504
A20: BARMM | B20: =Summary!O19 -> 10562766 | C20: 1409771 | D20: =Summary!O39 -> 30407248 | E20: 3085948.8 | F20: =Summary!O59 -> 1771637.1 | G20: 177240.36 | H20: =Summary!O79 -> 0 | I20: 0 | J20: =B20+D20+F20+H20 -> 42741651 | K20: =C20+E20+G20+I20 -> 4672960.2 | L20: =Summary!O100 -> 1.5146202e+09 | M20: =Summary!O121 -> 8.5174759e+09 | N20: =SUM(L20:M20) -> 1.0032096e+10 | O20: =K20/$K$21 -> 0.00086410754 | P20: =$J$31*O20 -> 86.892977 | Q20: =ROUND(P20, 0) -> 87 | R20: =N20/$N$21 -> 0.11783447 | S20: =R20*$J$32 -> 11364.185 | T20: =ROUND(S20,0) -> 11364 | U20: =Q20*$I$30 -> 435000 | V20: =S20*$I$30 -> 56820926 | W20: =Y20-U20 -> 6624.3655 | X20: =Z20-V20 -> 865293.29 | Y20: =Q20*$I$30/0.985 -> 441624.37 | Z20: =S20*$I$30/0.985 -> 57686219 | AA20: =J20/$J$21 -> 0.0013606962 | AB20: =$M$31*AA20 -> 132.84366 | AC20: =ROUND(AB20, 0) -> 133 | AD20: =N20/$N$21 -> 0.11783447 | AE20: =AD20*$M$32 -> 11033.19 | AF20: =ROUND(AE20,0) -> 11033 | AG20: =AB20*$L$30 -> 684144.83 | AH20: =ROUND(AG20,0) -> 684145 | AI20: =AC20*$L$30 -> 684950 | AJ20: =AE20*$L$30 -> 56820926 | AK20: =AF20*$L$30 -> 56819950 | AL20: =AG20+AJ20 -> 57505071 | AM20: =ROUND(AL20/1000,2)+0.01 -> 57505.08 | AN20: =AL20/$AW$23 -> 0.057505071 | AO20: =(AW20-AG20)*$AQ$24-0.01 -> 9897.5167 | AP20: =ROUND(AO20,0) -> 9898 | AQ20: =(AX20-AJ20)*$AQ$24 -> 822028.63 | AR20: =ROUND(AQ20,0) -> 822029 | AS20: =SUM(AO20:AQ20) -> 841824.14 | AT20: =ROUND(AS20/1000,2) -> 841.82 | AU20: =AQ20+AL20+AO20 -> 58336997 | AV20: =AU20/$AW$23 -> 0.058336997 | AW20: =AB20*$L$30/0.985 -> 694563.27 | AX20: =AE20*$L$30/0.985 -> 57686219 | AY20: =AC20+AF20 -> 11166 | AZ20: =AY20/$AY$21 -> 0.058379735 | BD20: =BB20*3150 -> 0 | BE20: =SUM(BC20:BD20) -> 0 | BF20: =BE20/$BE$21 -> 0 | BG20: =AU20-BE20 -> 58336997 | BH20: =BG20/BE20 -> #DIV/0!
A21: TOTAL | B21: =SUM(B4:B20) -> 1.5807126e+10 | C21: =SUM(C4:C20) -> 2.3632394e+09 | D21: =SUM(D4:D20) -> 1.0967804e+10 | E21: =SUM(E4:E20) -> 1.511536e+09 | F21: =SUM(F4:F20) -> 3.4069755e+09 | G21: =SUM(G4:G20) -> 4.9826559e+08 | H21: =SUM(H4:H20) -> 1.2296992e+09 | I21: =SUM(I4:I20) -> 1.0348046e+09 | ... N21: =SUM(N4:N20) -> 8.5137192e+10 | O21: =K21/$K$21 -> 1 | P21: =SUM(P4:P20) -> 100558.06 | Q21: =SUM(Q4:Q20) -> 100557 | R21: =N21/$N$21 -> 1 | S21: =SUM(S4:S20) -> 96441.941 | T21: =SUM(T4:T20) -> 96443 | U21: =SUM(U4:U20) -> 502785000 | V21: =SUM(V4:V20) -> 482209705 | W21: =SUM(W4:W20) -> 7656624.4 | X21: =SUM(X4:X20) -> 7343295 | Y21: =SUM(Y4:Y20) -> 5.1044162e+08 | Z21: =SUM(Z4:Z20) -> 4.89553e+08 | AA21: =J21/$J$21 -> 1 | AB21: =SUM(AB4:AB20) -> 97629.183 | AC21: =SUM(AC4:AC20) -> 97630 | AD21: =N21/$N$21 -> 1 | AE21: =SUM(AE4:AE20) -> 93632.952 | AF21: =SUM(AF4:AF20) -> 93635 | AG21: =SUM(AG4:AG20) -> 5.0279029e+08 | AH21: =SUM(AH4:AH20) -> 502790296 | AI21: =SUM(AI4:AI20) -> 502794500 | AJ21: =SUM(AJ4:AJ20) -> 4.822097e+08 | AK21: =SUM(AK4:AK20) -> 482220250 | AL21: =SUM(AL4:AL20) -> 9.85e+08 | AM21: =SUM(AM4:AM20) -> 985000 | AN21: =AL21/$AW$23 -> 0.985 | AO21: =SUM(AO4:AO20) -> 7273869.7 | AP21: =SUM(AP4:AP20) -> 7273872 | AQ21: =SUM(AQ4:AQ20) -> 6976130.3 | AR21: =SUM(AR4:AR20) -> 6976130 | AS21: =SUM(AO21:AQ21) -> 21523872 | AU21: =SUM(AU4:AU20) -> 9.9925e+08 | AV21: =SUM(AV4:AV20) -> 0.99925 | AW21: =SUM(AW4:AW20) -> 5.10447e+08 | AX21: =SUM(AX4:AX20) -> 4.89553e+08 | AY21: =SUM(AY4:AY20) -> 191265 | AZ21: =SUM(AZ4:AZ20) -> 1 | BA21: =SUM(BA4:BA20) -> 79365 | BB21: =SUM(BB4:BB20) -> 79365 | ... BG21: =SUM(BG4:BG20) -> 4.992505e+08 | BH21: =SUM(BH4:BH19) -> 21.328318
Q23: =T21+Q21 -> 197000 | U23: =SUM(U21:V21) -> 984994705 | W23: =SUM(W21:X21) -> 14999919 | Y23: =SUM(Y21:Z21) -> 9.9999462e+08 | AC23: =AF21+AC21 -> 191265 | AG23: =SUM(AG21:AJ21) -> 1.9905848e+09 | AO23: =SUM(AO21,AQ21) -> 14250000 | AP23: =SUM(AP21,AR21) -> 14250002 | AW23: =SUM(AW21:AX21) -> 1e+09 | BD23: =SUM(BC21:BD21) -> 499999500 | BG23: =BG21+AV27 -> 5.000005e+08
AQ24: =19/20 -> 0.95
AG25: =SUM(AG4:AG20) -> 5.0279029e+08 | AO25: =ROUND(AQ25*I28,0) -> 382835 | AP25: =ROUND(AQ25*I29,0) -> 367165 | AQ25: =N27-AO23 -> 750000 | AS25: For NPCG | BA25: 0.3 | BB25: =BA25*AW21 -> 1.531341e+08 | BD25: 0.6 | BE25: =BD25*AW21 -> 3.062682e+08 | BG25: 0.1 | BH25: =BG25*AW21 -> 51044700
I26: Total Fund Allocation | J26: Financial Allocation | K26: Administrative Fund | L26: Total Fund Allocation | M26: Financial Allocation | N26: Administrative Fund | AS26: BAFE | AT26: ICTS | AU26: PROGRAMS | AV26: Total | AX26: January | AY26: February | AZ26: March | BA26: April | BB26: May | BC26: June | BD26: July | BE26: August | BF26: September | BG26: October | BH26: November | BI26: December
H27: Total Fuel Assistance | I27: 1000000000 | J27: =I27*0.985 -> 985000000 | K27: =I27*0.015 -> 15000000 | L27: 1000000000 | M27: =L27*0.985 -> 985000000 | N27: =L27*0.015 -> 15000000 | AQ27: TOTAL | AS27: =1/6*AQ25 -> 125000 | AT27: =1/6*AQ25 -> 125000 | AU27: =2/3*AQ25 -> 500000 | AV27: =SUM(AS27:AU27) -> 750000 | AW27: Budget | BA27: =$BB$25/3 -> 51044700 | BB27: =$BB$25/3 -> 51044700 | BC27: =$BB$25/3 -> 51044700 | BD27: =$BE$25/3 -> 1.020894e+08 | BE27: =$BE$25/3 -> 1.020894e+08 | BF27: =$BE$25/3 -> 1.020894e+08 | BG27: =$BH$25/2 -> 25522350 | BH27: =$BH$25/2 -> 25522350 | BJ27: =SUM(AX27:BI27) -> 5.10447e+08
H28: DA Share | I28: 0.510447 | L28: 0.00510449 | AQ28: NCR | AS28: =AS$27*$AZ4 -> 5596.2931 | AT28: =AT$27*$AZ4 -> 5596.2931 | AU28: =AU$27*$AZ4 -> 22385.172 | AV28: =SUM(AS28:AU28) -> 33577.759 | AW28: Number of Beneficiaries | BA28: =ROUND(BA27/3150,0) -> 16205 | BB28: =ROUND(BB27/3150,0) -> 16205 | BC28: =ROUND(BC27/3150,0) -> 16205 | BD28: =ROUND(BD27/3150,0) -> 32409 | BE28: =ROUND(BE27/3150,0) -> 32409 | BF28: =ROUND(BF27/3150,0) -> 32409 | BG28: =ROUND(BG27/3150,0) -> 8102 | BH28: =ROUND(BH27/3150,0) -> 8102 | BJ28: =SUM(AX28:BI28) -> 162046
H29: BFAR Share | I29: =100%-I28 -> 0.489553 | L29: 0.4 | AQ29: CAR | AS29: =AS$27*AZ5 -> 1398.5831 | AT29: =AT$27*$AZ5 -> 1398.5831 | AU29: =AU$27*$AZ5 -> 5594.3325 | AV29: =SUM(AS29:AU29) -> 8391.4987
H30: Fuel Assistance per Farmer | I30: 5000 | L30: 5150 | AQ30: Region I | AS30: =AS$27*AZ6 -> 12178.783 | AT30: =AT$27*$AZ6 -> 12178.783 | AU30: =AU$27*$AZ6 -> 48715.133 | AV30: =SUM(AS30:AU30) -> 73072.7
H31: Number of DA Bex | I31: =I27*I28/I30 -> 102089.4 | J31: =J27*I28/I30 -> 100558.06 | K31: =K27*I28/I30 -> 1531.341 | L31: =I27*I28/L30 -> 99115.922 | M31: =M27*I28/L30 -> 97629.183 | N31: =N27*I28/L30 -> 1486.7388 | AQ31: Region II | AS31: =AS$27*AZ7 -> 16667.974 | AT31: =AT$27*$AZ7 -> 16667.974 | AU31: =AU$27*$AZ7 -> 66671.895 | AV31: =SUM(AS31:AU31) -> 100007.84
H32: Number of BFAR Bex | I32: =I27*I29/I30 -> 97910.6 | J32: =J27*I29/I30 -> 96441.941 | K32: =K27*I29/I30 -> 1468.659 | L32: =I27*I29/L30 -> 95058.835 | M32: =M27*I29/L30 -> 93632.952 | N32: =N27*I29/L30 -> 1425.8825 | AQ32: Region III | AS32: =AS$27*AZ8 -> 9142.4202 | AT32: =AT$27*$AZ8 -> 9142.4202 | AU32: =AU$27*$AZ8 -> 36569.681 | AV32: =SUM(AS32:AU32) -> 54854.521
H33: Total Number of Bex | I33: =I31+I32 -> 200000 | J33: =SUM(J31:J32) -> 197000 | K33: =SUM(K31:K32) -> 3000 | L33: =L31+L32 -> 194174.76 | M33: =SUM(M31:M32) -> 191262.14 | N33: =SUM(N31:N32) -> 2912.6214 | AQ33: CALABARZON | AS33: =AS$27*AZ9 -> 8744.4122 | AT33: =AT$27*$AZ9 -> 8744.4122 | AU33: =AU$27*$AZ9 -> 34977.649 | AV33: =SUM(AS33:AU33) -> 52466.473
AQ34: MIMAROPA | AS34: =AS$27*AZ10 -> 5656.4191 | AT34: =AT$27*$AZ10 -> 5656.4191 | AU34: =AU$27*$AZ10 -> 22625.676 | AV34: =SUM(AS34:AU34) -> 33938.515
AQ35: Region V | AS35: =AS$27*AZ11 -> 6330.876 | AT35: =AT$27*$AZ11 -> 6330.876 | AU35: =AU$27*$AZ11 -> 25323.504 | AV35: =SUM(AS35:AU35) -> 37985.256
AQ36: Region VI | AS36: =AS$27*AZ12 -> 7398.1126 | AT36: =AT$27*$AZ12 -> 7398.1126 | AU36: =AU$27*$AZ12 -> 29592.45 | AV36: =SUM(AS36:AU36) -> 44388.675
AQ37: Region VII | AS37: =AS$27*AZ13 -> 4051.9698 | AT37: =AT$27*$AZ13 -> 4051.9698 | AU37: =AU$27*$AZ13 -> 16207.879 | AV37: =SUM(AS37:AU37) -> 24311.819
AQ38: Region VIII | AS38: =AS$27*AZ14 -> 4097.0643 | AT38: =AT$27*$AZ14 -> 4097.0643 | AU38: =AU$27*$AZ14 -> 16388.257 | AV38: =SUM(AS38:AU38) -> 24582.386
AQ39: Region IX | AS39: =AS$27*AZ15 -> 5923.0649 | AT39: =AT$27*$AZ15 -> 5923.0649 | AU39: =AU$27*$AZ15 -> 23692.259 | AV39: =SUM(AS39:AU39) -> 35538.389
AQ40: Region X | AS40: =AS$27*AZ16 -> 8205.8924 | AT40: =AT$27*$AZ16 -> 8205.8924 | AU40: =AU$27*$AZ16 -> 32823.569 | AV40: =SUM(AS40:AU40) -> 49235.354
AQ41: Region XI | AS41: =AS$27*AZ17 -> 4773.4818 | AT41: =AT$27*$AZ17 -> 4773.4818 | AU41: =AU$27*$AZ17 -> 19093.927 | AV41: =SUM(AS41:AU41) -> 28640.891
AQ42: Region XII | AS42: =AS$27*AZ18 -> 7975.1915 | AT42: =AT$27*$AZ18 -> 7975.1915 | AU42: =AU$27*$AZ18 -> 31900.766 | AV42: =SUM(AS42:AU42) -> 47851.149
AQ43: Region XIII | AS43: =AS$27*AZ19 -> 9561.9951 | AT43: =AT$27*$AZ19 -> 9561.9951 | AU43: =AU$27*$AZ19 -> 38247.981 | AV43: =SUM(AS43:AU43) -> 57371.971
AQ44: BARMM | AS44: =AS$27*AZ20 -> 7297.4669 | AT44: =AT$27*$AZ20 -> 7297.4669 | AU44: =AU$27*$AZ20 -> 29189.867 | AV44: =SUM(AS44:AU44) -> 43784.801

Sheet World Bank Commodity Price Data
A1: World Bank Commodity Price Data (The Pink Sheet)
A2: annual prices, 1960 to present, nominal US dollars
A3: (annual series are available in nominal and real dollars)
A4: Updated on August 02, 2022
B7: Crude oil, average | C7: Crude oil, Brent | D7: Crude oil, Dubai | E7: Crude oil, WTI | F7: Coal, Australian | G7: Coal, South Afican | H7: Natural gas, US | I7: Natural gas, Europe | J7: Liquefied natural gas, Japan | K7: Natural gas index | L7: Cocoa | M7: Coffee, Arabica | N7: Coffee, Robusta | O7: Tea, avg 3 auctions | P7: Tea, Colombo | Q7: Tea, Kolkata | R7: Tea, Mombasa | S7: Coconut oil | T7: Groundnuts | U7: Fish meal | V7: Groundnut oil | W7: Palm oil | X7: Palm kernel oil | Y7: Soybeans | Z7: Soybean oil | AA7: Soybean meal | AB7: Barley | AC7: Maize | AD7: Sorghum | AE7: Rice, Thai 5% | AF7: Rice, Thai 25% | AG7: Rice, Thai A.1 | AH7: Rice, Viet Namese 5% | AI7: Wheat, US SRW | AJ7: Wheat, US HRW | AK7: Banana, Europe | AL7: Banana, US | AM7: Orange | AN7: Beef | AO7: Meat, chicken | AP7: Meat, sheep | AQ7: Shrimps, Mexican | AR7: Sugar, EU | AS7: Sugar, US | AT7: Sugar, world | AU7: Tobacco, US import u.v. | AV7: Logs, Cameroon | AW7: Logs, Malaysian | AX7: Sawnwood, Cameroon | AY7: Sawnwood, Malaysian | AZ7: Plywood | BA7: Cotton, A Index | BB7: Rubber, TSR20 | BC7: Rubber, SGP/MYS | BD7: Phosphate rock | BE7: DAP | BF7: TSP | BG7: Urea | BH7: Potassium chloride | BI7: Aluminum | BJ7: Iron ore, cfr spot | BK7: Copper | BL7: Lead | BM7: Tin | BN7: Nickel | BO7: Zinc | BP7: Gold | BQ7: Platinum | BR7: Silver
B8: ($/bbl) | C8: ($/bbl) | D8: ($/bbl) | E8: ($/bbl) | F8: ($/mt) | G8: ($/mt) | H8: ($/mmbtu) | I8: ($/mmbtu) | J8: ($/mmbtu) | K8: (2010=100) | L8: ($/kg) | M8: ($/kg) | N8: ($/kg) | O8: ($/kg) | P8: ($/kg) | Q8: ($/kg) | R8: ($/kg) | S8: ($/mt) | T8: ($/mt) | U8: ($/mt) | V8: ($/mt) | W8: ($/mt) | X8: ($/mt) | Y8: ($/mt) | Z8: ($/mt) | AA8: ($/mt) | AB8: ($/mt) | AC8: ($/mt) | AD8: ($/mt) | AE8: ($/mt) | AF8: ($/mt) | AG8: ($/mt) | AH8: ($/mt) | AI8: ($/mt) | AJ8: ($/mt) | AK8: ($/kg) | AL8: ($/kg) | AM8: ($/kg) | AN8: ($/kg) | AO8: ($/kg) | AP8: ($/kg) | AQ8: ($/kg) | AR8: ($/kg) | AS8: ($/kg) | AT8: ($/kg) | AU8: ($/mt) | AV8: ($/cubic meter) | AW8: ($/cubic meter) | AX8: ($/cubic meter) | AY8: ($/cubic meter) | AZ8: (¢/sheet) | BA8: ($/kg) | BB8: ($/kg) | BC8: ($/kg) | BD8: ($/mt) | BE8: ($/mt) | BF8: ($/mt) | BG8: ($/mt) | BH8: ($/mt) | BI8: ($/mt) | BJ8: ($/dmtu) | BK8: ($/mt) | BL8: ($/mt) | BM8: ($/mt) | BN8: ($/mt) | BO8: ($/mt) | BP8: ($/troy oz) | BQ8: ($/troy oz) | BR8: ($/troy oz)
B9: CRUDE_PETRO | C9: CRUDE_BRENT | D9: CRUDE_DUBAI | E9: CRUDE_WTI | F9: COAL_AUS | G9: COAL_SAFRICA | H9: NGAS_US | I9: NGAS_EUR | J9: NGAS_JP | K9: iNATGAS | L9: COCOA | M9: COFFEE_ARABIC | N9: COFFEE_ROBUS | O9: TEA_AVG | P9: TEA_COLOMBO | Q9: TEA_KOLKATA | R9: TEA_MOMBASA | S9: COCONUT_OIL | T9: GRNUT | U9: FISH_MEAL | V9: GRNUT_OIL | W9: PALM_OIL | X9: PLMKRNL_OIL | Y9: SOYBEANS | Z9: SOYBEAN_OIL | AA9: SOYBEAN_MEAL | AB9: BARLEY | AC9: MAIZE | AD9: SORGHUM | AE9: RICE_05 | AF9: RICE_25 | AG9: RICE_A1 | AH9: RICE_05_VNM | AI9: WHEAT_US_SRW | AJ9: WHEAT_US_HRW | AK9: BANANA_EU | AL9: BANANA_US | AM9: ORANGE | AN9: BEEF | AO9: CHICKEN | AP9: LAMB | AQ9: SHRIMP_MEX | AR9: SUGAR_EU | AS9: SUGAR_US | AT9: SUGAR_WLD | AU9: TOBAC_US | AV9: LOGS_CMR | AW9: LOGS_MYS | AX9: SAWNWD_CMR | AY9: SAWNWD_MYS | AZ9: PLYWOOD | BA9: COTTON_A_INDX | BB9: RUBBER_TSR20 | BC9: RUBBER1_MYSG | BD9: PHOSROCK | BE9: DAP | BF9: TSP | BG9: UREA_EE_BULK | BH9: POTASH | BI9: ALUMINUM | BJ9: IRON_ORE | BK9: COPPER | BL9: LEAD | BM9: Tin | BN9: NICKEL | BO9: Zinc | BP9: GOLD | BQ9: PLATINUM | BR9: SILVER
A10: 1960 | B10: 1.6300001 | C10: 1.6300001 | D10: 1.6300001 | E10: .. | F10: .. | G10: .. | H10: 0.14 | I10: 0.404774 | J10: .. | K10: .. | L10: 0.58901667 | M10: 0.92351667 | N10: 0.69594573 | O10: 1.0297 | P10: 0.9303009 | Q10: 1.121401 | R10: 1.0374 | S10: 312.33333 | T10: .. | U10: .. | V10: 327 | W10: 224.41667 | X10: .. | Y10: 91.833333 | Z10: 223.91667 | AA10: 81.008333 | AB10: 20.153697 | AC10: 44.5 | AD10: 36.575 | AE10: 107.34917 | AF10: .. | AG10: .. | AH10: .. | AI10: .. | AJ10: 57.993333 | AK10: .. | AL10: 0.1428675 | AM10: 0.12998333 | AN10: 0.73653333 | AO10: 0.30013023 | AP10: .. | AQ10: 1.6056982 | AR10: 0.12235641 | AS10: 0.12584706 | AT10: 0.066208333 | AU10: 1736.87 | AV10: .. | AW10: 31.94 | AX10: .. | AY10: 149.17498 | AZ10: .. | BA10: 0.65454167 | BB10: .. | BC10: 0.78023333 | BD10: 13 | BE10: .. | BF10: 53 | BG10: 42.25 | BH10: 28.5 | BI10: 511.47183 | BJ10: 11.42 | BK10: 678.75583 | BL10: 198.85 | BM10: 2196.7333 | BN10: 1631 | BO10: 246.19167 | BP10: 35.27 | BQ10: 83.5 | BR10: 0.9137
A11: 1961 | B11: 1.57 | C11: 1.57 | D11: 1.57 | E11: .. | F11: .. | G11: .. | H11: 0.15 | I11: 0.404774 | J11: .. | K11: .. | L11: 0.47855833 | M11: 0.89554167 | N11: 0.66943581 | O11: 0.9518 | P11: 0.8925009 | Q11: 0.978601 | R11: 0.9841996 | S11: 253.41667 | T11: .. | U11: .. | V11: 330.25 | W11: 228.41667 | X11: .. | Y11: 109.33333 | Z11: 287.33333 | AA11: 96.908333 | AB11: 20.74804 | AC11: 44.956667 | AD11: 41.416667 | AE11: 118.95 | AF11: .. | AG11: .. | AH11: .. | AI11: .. | AJ11: 58.605833 | AK11: .. | AL11: 0.13492167 | AM11: 0.13300833 | AN11: 0.68195 | AO11: 0.31227946 | AP11: .. | AQ11: 1.693883 | AR11: 0.12434057 | AS11: 0.12566334 | AT11: 0.05945 | AU11: 1563.19 | AV11: .. | AW11: 33.06 | AX11: .. | AY11: 151.97728 | AZ11: .. | BA11: 0.67218333 | BB11: .. | BC11: 0.60130833 | BD11: 13 | BE11: .. | BF11: 52 | BG11: 42.25 | BH11: 30 | BI11: 511.47183 | BJ11: 11.02 | BK11: 633.08417 | BL11: 176.975 | BM11: 2449.8917 | BN11: 1711 | BO11: 214.30833 | BP11: 35.25 | BQ11: 83.5 | BR11: 0.92444167
A12: 1962 | B12: 1.52 | C12: 1.52 | D12: 1.52 | E12: .. | F12: .. | G12: .. | H12: 0.16 | I12: 0.404774 | J12: .. | K12: .. | L12: 0.45796667 | M12: 0.83259167 | N12: 0.68220393 | O12: 0.973 | P12: 0.8610009 | Q12: 1.104601 | R12: 0.9533996 | S12: 251.21667 | T12: .. | U12: .. | V12: 274.34 | W12: 216.23583 | X12: .. | Y12: 100.54 | Z12: 227 | AA12: 89.008333 | AB12: 22.702439 | AC12: 48.653333 | AD12: 44.700833 | AE12: 134.92583 | AF12: .. | AG12: .. | AH12: .. | AI12: .. | AJ12: 64.3325 | AK12: .. | AL12: 0.13139 | AM12: 0.10800833 | AN12: 0.714125 | AO12: 0.31956188 | AP12: .. | AQ12: 2.2523868 | AR12: 0.12632473 | AS12: 0.12841912 | AT12: 0.061683333 | AU12: 1404.9 | AV12: .. | AW12: 36.39 | AX12: .. | AY12: 160.06097 | AZ12: .. | BA12: 0.649325 | BB12: .. | BC12: 0.56363333 | BD12: 11.5 | BE12: .. | BF12: 51 | BG12: 42.25 | BH12: 30 | BI12: 498.06039 | BJ12: 11.01 | BK12: 645.14333 | BL12: 155.28333 | BM12: 2471.3833 | BN12: 1761 | BO12: 185.925 | BP12: 35.23 | BQ12: 83.5 | BR12: 1.083725
A13: 1963 | B13: 1.5 | C13: 1.5 | D13: 1.5 | E13: .. | F13: .. | G13: .. | H13: 0.16 | I13: 0.39135114 | J13: .. | K13: .. | L13: 0.55234167 | M13: 0.80574167 | N13: 0.62350728 | O13: 0.9529 | P13: 0.8148008 | Q13: 1.083601 | R13: 0.9603996 | S13: 286.33333 | T13: .. | U13: .. | V13: 268.50333 | W13: 222.39333 | X13: .. | Y13: 110.09333 | Z13: 223.58333 | AA13: 91.016667 | AB13: 23.977474 | AC13: 53.770833 | AD13: 47.84 | AE13: 125.66333 | AF13: .. | AG13: .. | AH13: .. | AI13: .. | AJ13: 64.486667 | AK13: .. | AL13: 0.14408333 | AM13: 0.094008333 | AN13: 0.66634167 | AO13: 0.32802899 | AP13: .. | AQ13: 1.9970183 | AR13: 0.12676565 | AS13: 0.16589766 | AT13: 0.18323333 | AU13: 1343.61 | AV13: .. | AW13: 35.485833 | AX13: .. | AY13: 157.84746 | AZ13: .. | BA13: 0.64559167 | BB13: .. | BC13: 0.52138333 | BD13: 11.5 | BE13: .. | BF13: 52 | BG13: 42.25 | BH13: 30 | BI13: 498.79527 | BJ13: 11.02 | BK13: 645.95083 | BL13: 174.80833 | BM13: 2507.7333 | BN13: 1741.6667 | BO13: 211.50833 | BP13: 35.09 | BQ13: 80.930833 | BR13: 1.2791083
A14: 1964 | B14: 1.45 | C14: 1.45 | D14: 1.45 | E14: .. | F14: .. | G14: .. | H14: 0.15 | I14: 0.3841498 | J14: .. | K14: .. | L14: 0.50574167 | M14: 1.0097583 | N14: 0.78706794 | O14: 0.927 | P14: 0.8190008 | Q14: 1.039501 | R14: 0.9225996 | S14: 296.475 | T14: .. | U14: .. | V14: 315.37583 | W14: 239.4525 | X14: .. | Y14: 110.50583 | Z14: 233 | AA14: 89.008333 | AB14: 25.143383 | AC14: 54.631667 | AD14: 48.235 | AE14: 120.1475 | AF14: .. | AG14: .. | AH14: .. | AI14: .. | AJ14: 67.526667 | AK14: .. | AL14: 0.17040833 | AM14: 0.084 | AN14: 0.84088333 | AO14: 0.33763148 | AP14: .. | AQ14: 1.8132999 | AR14: 0.12658193 | AS14: 0.13870734 | AT14: 0.126325 | AU14: 1488.3 | AV14: .. | AW14: 30.255 | AX14: .. | AY14: 144.83399 | AZ14: .. | BA14: 0.65035833 | BB14: .. | BC14: 0.49050833 | BD14: 12.5 | BE14: .. | BF14: 53 | BG14: 60.5 | BH14: 32.5 | BI14: 525.98563 | BJ14: 10.24 | BK14: 969.75333 | BL14: 277.88333 | BM14: 3412.7417 | BN14: 1741.6667 | BO14: 326.49167 | BP14: 35.1 | BQ14: 88.480833 | BR14: 1.293
A15: 1965 | B15: 1.42 | C15: 1.42 | D15: 1.42 | E15: .. | F15: .. | G15: .. | H15: 0.16 | I15: 0.41076611 | J15: .. | K15: .. | L15: 0.36530833 | M15: 1.00035 | N15: 0.67825408 | O15: 1.0003 | P15: 0.8463009 | Q15: 1.142401 | R15: 1.0122 | S15: 350.13333 | T15: .. | U15: .. | V15: 323.9175 | W15: 272.52167 | X15: .. | Y15: 116.86833 | Z15: 270 | AA15: 97.025 | AB15: 24.344802 | AC15: 55.6725 | AD15: 47.931667 | AE15: 118.78917 | AF15: .. | AG15: .. | AH15: .. | AI15: .. | AJ15: 59.461667 | AK15: .. | AL15: 0.15940833 | AM15: 0.096 | AN15: 0.88161667 | AO15: 0.35023988 | AP15: .. | AQ15: 1.9878324 | AR15: 0.12456103 | AS15: 0.13613528 | AT15: 0.044216667 | AU15: 1265.41 | AV15: .. | AW15: 35.025 | AX15: .. | AY15: 156.74931 | AZ15: .. | BA15: 0.637925 | BB15: .. | BC15: 0.50485833 | BD15: 14 | BE15: .. | BF15: 54 | BG15: 65.75 | BH15: 29.5 | BI15: 540.13184 | BJ15: 10.661667 | BK15: 1292.8442 | BL15: 317.175 | BM15: 3890.7833 | BN15: 1735 | BO15: 311.25 | BP15: 35.12 | BQ15: 98.041667 | BR15: 1.293
A16: 1966 | B16: 1.36 | C16: 1.36 | D16: 1.36 | E16: .. | F16: .. | G16: .. | H16: 0.16 | I16: 0.42492867 | J16: .. | K16: .. | L16: 0.51763333 | M16: 0.928725 | N16: 0.7391369 | O16: 0.874325 | P16: 0.7602008 | Q16: 0.94869484 | R16: 0.9141996 | S16: 323.70833 | T16: .. | U16: .. | V16: 296.305 | W16: 235.64 | X16: .. | Y16: 125.6625 | Z16: 261.5 | AA16: 107.03583 | AB16: 25.911774 | AC16: 58.296667 | AD16: 48.575833 | AE16: 145.2025 | AF16: .. | AG16: .. | AH16: .. | AI16: .. | AJ16: 62.954167 | AK16: .. | AL16: 0.15379167 | AM16: 0.084025 | AN16: 1.02235 | AO16: 0.36362516 | AP16: .. | AQ16: 2.314851 | AR16: 0.13095443 | AS16: 0.14091196 | AT16: 0.039808333 | AU16: 1581.22 | AV16: .. | AW16: 36.825 | AX16: .. | AY16: 161.09032 | AZ16: .. | BA16: 0.6228 | BB16: .. | BC16: 0.47155833 | BD16: 13 | BE16: .. | BF16: 50 | BG16: 59.25 | BH16: 27.5 | BI16: 540.13184 | BJ16: 9.52 | BK16: 1531.5133 | BL16: 260.65 | BM16: 3573.5083 | BN16: 1739 | BO16: 281.10833 | BP16: 35.13 | BQ16: 99.720833 | BR16: 1.293
A17: 1967 | B17: 1.33 | C17: 1.33 | D17: 1.33 | E17: .. | F17: .. | G17: .. | H17: 0.16 | I17: 0.45664738 | J17: .. | K17: .. | L17: 0.59811667 | M17: 0.86420833 | N17: 0.73911853 | O17: 0.83614167 | P17: 0.71862073 | Q17: 0.7986667 | R17: 0.9911996 | S17: 326.35833 | T17: .. | U17: .. | V17: 282.95333 | W17: 223.45083 | X17: .. | Y17: 114.725 | Z17: 216.83333 | AA17: 98.891667 | AB17: 26.250324 | AC17: 54.1025 | AD17: 51.8975 | AE17: 189.37333 | AF17: .. | AG17: .. | AH17: .. | AI17: .. | AJ17: 65.71 | AK17: .. | AL17: 0.158625 | AM17: 0.15900833 | AN17: 1.0411333 | AO17: 0.37215392 | AP17: .. | AQ17: 2.2928048 | AR17: 0.12941119 | AS17: 0.14715839 | AT17: 0.042058333 | AU17: 1299.43 | AV17: .. | AW17: 39.329167 | AX17: .. | AY17: 166.88484 | AZ17: .. | BA17: 0.67653333 | BB17: .. | BC17: 0.390125 | BD17: 12 | BE17: 68.5 | BF17: 45 | BG17: 49.25 | BH17: 25.5 | BI17: 540.13184 | BJ17: 8.86 | BK17: 1134.7725 | BL17: 227.675 | BM17: 3308.025 | BN17: 1935.7 | BO17: 273.33333 | BP17: 34.95 | BQ17: 110.24833 | BR17: 1.5491833
A18: 1968 | B18: 1.32 | C18: 1.32 | D18: 1.32 | E18: .. | F18: .. | G18: .. | H18: 0.16 | I18: 0.45180188 | J18: .. | K18: .. | L18: 0.72088333 | M18: 0.867 | N18: 0.74630177 | O18: 0.7487 | P18: 0.6770413 | Q18: 0.7333334 | R18: 0.8357997 | S18: 399.26667 | T18: .. | U18: .. | V18: 270.73417 | W18: 168.83083 | X18: .. | Y18: 110.80083 | Z18: 178.08333 | AA18: 96.416667 | AB18: 25.163888 | AC18: 47.963333 | AD18: 52.566667 | AE18: 182.91333 | AF18: .. | AG18: .. | AH18: .. | AI18: .. | AJ18: 62.771667 | AK18: .. | AL18: 0.15308333 | AM18: 0.16800833 | AN18: 1.0852083 | AO18: 0.38389969 | AP18: .. | AQ18: 2.5794054 | AR18: 0.11221516 | AS18: 0.15285365 | AT18: 0.041933333 | AU18: 1204.4692 | AV18: .. | AW18: 40.048333 | AX18: .. | AY18: 168.53414 | AZ18: .. | BA18: 0.68451667 | BB18: .. | BC18: 0.38211667 | BD18: 11.5 | BE18: 60.5 | BF18: 37.5 | BG18: 35.5 | BH18: 24 | BI18: 552.99209 | BJ18: 8.77 | BK18: 1241.9525 | BL18: 240.49167 | BM18: 3126.8833 | BN18: 2074.5 | BO18: 262.89167 | BP18: 38.925 | BQ18: 117.20833 | BR18: 2.1446333
A19: 1969 | B19: 1.27 | C19: 1.27 | D19: 1.27 | E19: .. | F19: .. | G19: .. | H19: 0.17 | I19: 0.45181992 | J19: .. | K19: .. | L19: 0.89771667 | M19: 0.876725 | N19: 0.72973078 | O19: 0.7262 | P19: 0.5964011 | Q19: 0.8626667 | R19: 0.7195997 | S19: 361.26667 | T19: .. | U19: .. | V19: 331.525 | W19: 181.11417 | X19: .. | Y19: 106.74667 | Z19: 197.16667 | AA19: 94.666667 | AB19: 25.567489 | AC19: 52.286667 | AD19: 53.758333 | AE19: 168.37083 | AF19: .. | AG19: .. | AH19: .. | AI19: .. | AJ19: 58.394167 | AK19: .. | AL19: 0.15950833 | AM19: 0.17003333 | AN19: 1.2228667 | AO19: 0.4006875 | AP19: .. | AQ19: 2.866006 | AR19: 0.11221516 | AS19: 0.15744661 | AT19: 0.070591667 | AU19: 1112.3825 | AV19: .. | AW19: 38.89 | AX19: .. | AY19: 165.90811 | AZ19: .. | BA19: 0.62699167 | BB19: .. | BC19: 0.5022 | BD19: 11.25 | BE19: 58 | BF19: 39.25 | BG19: 26.6 | BH19: 22 | BI19: 588.44987 | BJ19: 9.84 | BK19: 1467.34 | BL19: 289.89167 | BM19: 3427.45 | BN19: 2363.4 | BO19: 286.40833 | BP19: 41.083333 | BQ19: 124.1875 | BR19: 1.7906667
A20: 1970 | B20: 1.21 | C20: 1.21 | D20: 1.21 | E20: .. | F20: 7.8 | G20: .. | H20: 0.17 | I20: 0.44721801 | J20: .. | K20: .. | L20: 0.675 | M20: 1.1466167 | N20: 0.91355507 | O20: 0.835 | P20: 0.6266412 | Q20: 0.9906667 | R20: 0.8875996 | S20: 397.18333 | T20: .. | U20: .. | V20: 378.54583 | W20: 260.04583 | X20: .. | Y20: 116.91667 | Z20: 286.33333 | AA20: 102.58333 | AB20: 26.358666 | AC20: 58.4 | AD20: 51.8 | AE20: 126.30833 | AF20: .. | AG20: .. | AH20: .. | AI20: .. | AJ20: 54.9025 | AK20: .. | AL20: 0.16608333 | AM20: 0.16804167 | AN20: 1.3042917 | AO20: 0.41997203 | AP20: .. | AQ20: 2.7337288 | AR20: 0.11221516 | AS20: 0.1653465 | AT20: 0.082241667 | AU20: 1075.9775 | AV20: 42.99 | AW20: 43.131667 | AX20: 175 | AY20: 175.4064 | AZ20: .. | BA20: 0.67628333 | BB20: .. | BC20: 0.40716667 | BD20: 11 | BE20: 54 | BF20: 42.5 | BG20: 18.25 | BH20: 31.5 | BI20: 614.17045 | BJ20: 9.84 | BK20: 1415.7 | BL20: 302.90833 | BM20: 3673.45 | BN20: 2846.2 | BO20: 295.81667 | BP20: 35.941667 | BQ20: 132.5 | BR20: 1.7708333
A21: 1971 | B21: 1.69 | C21: 1.69 | D21: 1.69 | E21: .. | F21: 8.68 | G21: .. | H21: 0.18 | I21: 0.50224354 | J21: .. | K21: .. | L21: 0.538 | M21: 0.991875 | N21: 0.93157741 | O21: 0.85069167 | P21: 0.67673282 | Q21: 0.97380937 | R21: 0.9015996 | S21: 365.52667 | T21: .. | U21: .. | V21: 440.615 | W21: 260.94167 | X21: .. | Y21: 125.58333 | Z21: 303.75 | AA21: 102.25 | AB21: 28.382951 | AC21: 58.4 | AD21: 55.77 | AE21: 111.5375 | AF21: .. | AG21: .. | AH21: .. | AI21: .. | AJ21: 61.728333 | AK21: .. | AL21: 0.14016667 | AM21: 0.15300833 | AN21: 1.3458583 | AO21: 0.44006712 | AP21: 0.79675833 | AQ21: 3.30693 | AR21: 0.11383188 | AS21: 0.17489985 | AT21: 0.0991 | AU21: 1042.6467 | AV21: 44.43 | AW21: 43.265 | AX21: .. | AY21: 175.72388 | AZ21: .. | BA21: 0.7832 | BB21: .. | BC21: 0.33255 | BD21: 11.25 | BE21: 61.75 | BF21: 43.25 | BG21: 16 | BH21: 32.5 | BI21: 627.94932 | BJ21: 10.33 | BK21: 1081.4167 | BL21: 253.625 | BM21: 3511.9667 | BN21: 2932.1 | BO21: 309.28333 | BP21: 40.804167 | BQ21: 123.04167 | BR21: 1.5456417
A22: 1972 | B22: 1.82 | C22: 1.82 | D22: 1.82 | E22: .. | F22: 9.6 | G22: .. | H22: 0.19 | I22: 0.54216599 | J22: .. | K22: .. | L22: 0.644 | M22: 1.1095917 | N22: 0.99607937 | O22: 0.78224167 | P22: 0.69963159 | Q22: 0.83648714 | R22: 0.8105997 | S22: 234.06 | T22: .. | U22: .. | V22: 425.93417 | W22: 217.25833 | X22: .. | Y22: 140 | Z22: 240.58333 | AA22: 129.83333 | AB22: 30.06643 | AC22: 55.7525 | AD22: 56.238333 | AE22: 129.44917 | AF22: .. | AG22: .. | AH22: .. | AI22: .. | AJ22: 69.8125 | AK22: .. | AL22: 0.1361 | AM22: 0.15498333 | AN22: 1.4802667 | AO22: 0.4726238 | AP22: 1.0681 | AQ22: 4.1226394 | AR22: 0.15002439 | AS22: 0.18812757 | AT22: 0.160275 | AU22: 1073.6425 | AV22: 52.48 | AW22: 41.115833 | AX22: .. | AY22: 170.92857 | AZ22: .. | BA22: 0.82699167 | BB22: .. | BC22: 0.331775 | BD22: 11.5 | BE22: 91 | BF22: 67.5 | BG22: 29.25 | BH22: 33.5 | BI22: 590.10331 | BJ22: 10.33 | BK22: 1057.675 | BL22: 301.65833 | BM22: 3739.9583 | BN22: 3079.9 | BO22: 377.69167 | BP22: 58.159167 | BQ22: 127.125 | BR22: 1.6845667
A23: 1973 | B23: 2.8075 | C23: 2.8075 | D23: 2.8075 | E23: .. | F23: 11.48 | G23: .. | H23: 0.21 | I23: 0.69350672 | J23: .. | K23: .. | L23: 1.131 | M23: 1.37345 | N23: 1.0998595 | O23: 0.78825833 | P23: 0.66159353 | Q23: 0.86592464 | R23: 0.83724386 | S23: 513 | T23: .. | U23: .. | V23: 546.16833 | W23: 377.53833 | X23: .. | Y23: 290.33333 | Z23: 436 | AA23: 301.66667 | AB23: 51.029191 | AC23: 97.821667 | AD23: 93.391667 | AE23: 289.58 | AF23: .. | AG23: .. | AH23: .. | AI23: .. | AJ23: 139.81 | AK23: .. | AL23: 0.14508333 | AM23: 0.163 | AN23: 2.010875 | AO23: 0.52907754 | AP23: 1.39105 | AQ23: 5.0044874 | AR23: 0.14704815 | AS23: 0.2268554 | AT23: 0.208575 | AU23: 1128.0208 | AV23: 133.47 | AW23: 68.029167 | AX23: .. | AY23: 223.52885 | AZ23: .. | BA23: 1.390575 | BB23: .. | BC23: 0.67800833 | BD23: 13.75 | BE23: 118.75 | BF23: 99.5 | BG23: 64.75 | BH23: 42.5 | BI23: 599.10549 | BJ23: 10.33 | BK23: 1785.3583 | BL23: 429.68333 | BM23: 4802.2 | BN23: 3373.1 | BO23: 845.33333 | BP23: 97.325833 | BQ23: 152.18417 | BR23: 2.5575583
A24: 1974 | B24: 10.974999 | C24: 10.974999 | D24: 10.974999 | E24: .. | F24: 16.89 | G24: .. | H24: 0.29 | I24: 1.73 | J24: .. | K24: .. | L24: 1.561 | M24: 1.4515333 | N24: 1.2935493 | O24: 1.093775 | P24: 0.8898866 | Q24: 1.2546285 | R24: 1.1368 | S24: 997.58333 | T24: .. | U24: .. | V24: 1076.8875 | W24: 669.05333 | X24: .. | Y24: 276.91667 | Z24: 832.16667 | AA24: 184.33333 | AB24: 64.933099 | AC24: 131.22583 | AD24: 120.9425 | AE24: 517.165 | AF24: .. | AG24: .. | AH24: .. | AI24: .. | AJ24: 179.70583 | AK24: .. | AL24: 0.18399583 | AM24: 0.183975 | AN24: 1.582225 | AO24: 0.5589023 | AP24: 1.4235917 | AQ24: 4.6517482 | AR24: 0.23470017 | AS24: 0.64997709 | AT24: 0.65481667 | AU24: 1482.0725 | AV24: 120.43 | AW24: 81.663333 | AX24: .. | AY24: 246.83365 | AZ24: .. | BA24: 1.4587417 | BB24: .. | BC24: 0.7516 | BD24: 54.520833 | BE24: 332.62083 | BF24: 303.58333 | BG24: 285.75 | BH24: 60.5 | BI24: 764.81944 | BJ24: 13.38 | BK24: 2058.5 | BL24: 592.25833 | BM24: 8184.2667 | BN24: 3825.25 | BO24: 1239.5833 | BP24: 159.245 | BQ24: 184.9775 | BR24: 4.70798
A25: 1975 | B25: 10.4325 | C25: 10.4325 | D25: 10.4325 | E25: .. | F25: 26.84 | G25: .. | H25: 0.43 | I25: 1.6820936 | J25: .. | K25: .. | L25: 1.246 | M25: 1.442125 | N25: 1.3458527 | O25: 1.14215 | P25: 0.8814117 | Q25: 1.4485832 | R25: 1.0964731 | S25: 393.5 | T25: .. | U25: .. | V25: 857.5 | W25: 434.16917 | X25: .. | Y25: 219.91667 | Z25: 563.33333 | AA25: 155 | AB25: 58.978615 | AC25: 119.635 | AD25: 111.87333 | AE25: 341.42833 | AF25: .. | AG25: .. | AH25: .. | AI25: .. | AJ25: 149.055 | AK25: .. | AL25: 0.21766667 | AM25: 0.22800833 | AN25: 1.3270917 | AO25: 0.58063009 | AP25: 1.4775917 | AQ25: 5.8863354 | AR25: 0.3404117 | AS25: 0.4954516 | AT25: 0.45109167 | AU25: 1841.9892 | AV25: 126.57 | AW25: 67.51 | AX25: .. | AY25: 223.43818 | AZ25: .. | BA25: 1.222875 | BB25: .. | BC25: 0.56090833 | BD25: 67.166667 | BE25: 242.5 | BF25: 202.5 | BG25: 168 | BH25: 81.333333 | BI25: 868.43656 | BJ25: 17.3 | BK25: 1234.75 | BL25: 411.675 | BM25: 6876.575 | BN25: 4571.3333 | BO25: 745.16667 | BP25: 161.02917 | BQ25: 169.87417 | BR25: 4.418515
A26: 1976 | B26: 11.63 | C26: 11.63 | D26: 11.63 | E26: .. | F26: 27.16 | G26: .. | H26: 0.58083333 | I26: 1.7351133 | J26: .. | K26: .. | L26: 2.04575 | M26: 3.1466583 | N26: 2.8133977 | O26: 1.1871167 | P26: 0.92756737 | Q26: 1.4182171 | R26: 1.2155303 | S26: 418.5 | T26: .. | U26: .. | V26: 712.83333 | W26: 406.53417 | X26: .. | Y26: 231.16667 | Z26: 438.33333 | AA26: 200 | AB26: 55.79403 | AC26: 112.37167 | AD26: 105.21333 | AE26: 234.68083 | AF26: .. | AG26: .. | AH26: .. | AI26: .. | AJ26: 132.92 | AK26: .. | AL26: 0.25858333 | AM26: 0.216 | AN26: 1.581 | AO26: 0.61029467 | AP26: 1.5660833 | AQ26: 8.3114174 | AR26: 0.29521699 | AS26: 0.29343492 | AT26: 0.254825 | AU26: 2186.715 | AV26: 142.33917 | AW26: 92.0175 | AX26: .. | AY26: 263.54774 | AZ26: .. | BA26: 1.7475083 | BB26: .. | BC26: 0.77373333 | BD26: 35.833333 | BE26: 119.91667 | BF26: 90.916667 | BG26: 82 | BH26: 55.5 | BI26: 889.93164 | BJ26: 22.72 | BK26: 1400.75 | BL26: 446.41667 | BM26: 7585.5417 | BN26: 4973.0833 | BO26: 711.41667 | BP26: 124.81583 | BQ26: 159.6475 | BR26: 4.355625
A27: 1977 | B27: 12.565 | C27: 12.565 | D27: 12.565 | E27: .. | F27: 28.678519 | G27: .. | H27: 0.79 | I27: 1.7916226 | J27: 2.7711629 | K27: 19.988036 | L27: 3.7900667 | M27: 5.1688667 | N27: 4.9328521 | O27: 1.9544417 | P27: 1.6958341 | Q27: 2.0673815 | R27: 2.1001298 | S27: 578.16667 | T27: .. | U27: .. | V27: 852.75 | W27: 530.025 | X27: .. | Y27: 280.16667 | Z27: 580.25 | AA27: 229.83333 | AB27: 47.886441 | AC27: 95.35 | AD27: 88.366667 | AE27: 252.225 | AF27: .. | AG27: .. | AH27: .. | AI27: .. | AJ27: 103.21833 | AK27: .. | AL27: 0.27375 | AM27: 0.254 | AN27: 1.5064667 | AO27: 0.65178392 | AP27: 1.700625 | AQ27: 7.9145858 | AR27: 0.30892238 | AS27: 0.24260006 | AT27: 0.17893333 | AU27: 2253.9258 | AV27: 158.77 | AW27: 92.566667 | AX27: .. | AY27: 264.98375 | AZ27: .. | BA27: 1.6285417 | BB27: .. | BC27: 0.81468333 | BD27: 61.7875 | BE27: 134.08333 | BF27: 97.916667 | BG27: 120.76319 | BH27: 55.29375 | BI27: 1143.8303 | BJ27: 23.06 | BK27: 1308.75 | BL27: 618 | BM27: 10804.45 | BN27: 5118.1667 | BO27: 589.66667 | BP27: 147.72083 | BQ27: 158.32167 | BR27: 4.6360833
A28: 1978 | B28: 12.916667 | C28: 12.916667 | D28: 12.916667 | E28: .. | F28: 29.058657 | G28: .. | H28: 0.90583333 | I28: 2.3022181 | J28: 3.0360808 | K28: 24.00148 | L28: 3.4031583 | M28: 3.5899917 | N28: 3.2512418 | O28: 1.4094833 | P28: 0.74565676 | Q28: 1.8749519 | R28: 1.6077983 | S28: 683.20833 | T28: .. | U28: .. | V28: 1079.1667 | W28: 600.33333 | X28: .. | Y28: 268.33333 | Z28: 607 | AA28: 213.29167 | AB28: 54.960061 | AC28: 100.7425 | AD28: 93.838333 | AE28: 345.6575 | AF28: .. | AG28: .. | AH28: .. | AI28: .. | AJ28: 127.745 | AK28: .. | AL28: 0.28725 | AM28: 0.30015 | AN28: 2.138275 | AO28: 0.69505797 | AP28: 2.1941417 | AQ28: 8.0689092 | AR28: 0.35119597 | AS28: 0.3080589 | AT28: 0.17230833 | AU28: 2268.0175 | AV28: 191.28083 | AW28: 97.358333 | AX28: .. | AY28: 272.28211 | AZ28: .. | BA28: 1.6066667 | BB28: .. | BC28: 0.985625 | BD28: 31.28125 | BE28: 139.83333 | BF28: 98.041667 | BG28: 136.03542 | BH28: 59.010417 | BI28: 1324.9215 | BJ28: 21.45 | BK28: 1364.8333 | BL28: 661.91667 | BM28: 12875.208 | BN28: 4609.25 | BO28: 593.91667 | BP28: 193.23917 | BQ28: 260.65083 | BR28: 5.4187667
A29: 1979 | B29: 30.964583 | C29: 32.1125 | D29: 29.816667 | E29: .. | F29: 30.89 | G29: .. | H29: 1.18 | I29: 3.2594886 | J29: 3.6924229 | K29: 32.326293 | L29: 3.2928333 | M29: 3.8261333 | N29: 3.6519417 | O29: 1.5053917 | P29: 0.78283264 | Q29: 2.1025033 | R29: 1.6308335 | S29: 984.5 | T29: .. | U29: 394.875 | V29: 888.66667 | W29: 653.83333 | X29: .. | Y29: 297.75 | Z29: 662.18333 | AA29: 243.025 | AB29: 65.247045 | AC29: 115.5225 | AD29: 108.10833 | AE29: 313.06917 | AF29: .. | AG29: .. | AH29: .. | AI29: 156.31 | AJ29: 160.29333 | AK29: .. | AL29: 0.32561667 | AM29: 0.39845833 | AN29: 2.8840167 | AO29: 0.74055756 | AP29: 2.3709667 | AQ29: 11.971087 | AR29: 0.42530794 | AS29: 0.34232237 | AT29: 0.21295 | AU29: 2344.4333 | AV29: 211.525 | AW29: 170.04167 | AX29: .. | AY29: 365.93189 | AZ29: 262.5 | BA29: 1.70735 | BB29: .. | BC29: 1.2621 | BD29: 35.479167 | BE29: 193.33333 | BF29: 146.225 | BG29: 153.00208 | BH29: 76.46875 | BI29: 1602.8682 | BJ29: 23.5 | BK29: 1985.2583 | BL29: 1208.25 | BM29: 15447.408 | BN29: 5986 | BO29: 741.66667 | BP29: 306.6675 | BQ29: 442.79833 | BR29: 11.099575
A30: 1980 | B30: 36.86875 | C30: 37.891667 | D30: 35.845833 | E30: .. | F30: 40.140833 | G30: .. | H30: 1.5891667 | I30: 4.22 | J30: 5.6962273 | K30: 43.218767 | L30: 2.6034917 | M30: 3.4662833 | N30: 3.2432167 | O30: 1.6592917 | P30: 1.1113645 | Q30: 2.0493532 | R30: 1.817127 | S30: 673.83333 | T30: 1236.5833 | U30: 504.425 | V30: 858.75 | W30: 583.69167 | X30: .. | Y30: 296.22917 | Z30: 597.60833 | AA30: 262.41667 | AB30: 78.228712 | AC30: 125.2625 | AD30: 128.86083 | AE30: 410.7425 | AF30: .. | AG30: .. | AH30: .. | AI30: 168.30167 | AJ30: 172.72667 | AK30: .. | AL30: 0.37726667 | AM30: 0.400175 | AN30: 2.7599667 | AO30: 0.75712162 | AP30: 2.8794167 | AQ30: 10.141252 | AR30: 0.48689033 | AS30: 0.66208413 | AT30: 0.63160833 | AU30: 2275.86 | AV30: 251.69167 | AW30: 195.51333 | AX30: 396 | AY30: 396.20134 | AZ30: 273.78333 | BA30: 2.0618417 | BB30: .. | BC30: 1.4245417 | BD30: 44.666667 | BE30: 222.20833 | BF30: 180.25 | BG30: 200.5625 | BH30: 106.5 | BI30: 1774.9128 | BJ30: 28.09 | BK30: 2182.0917 | BL30: 905.75 | BM30: 16774.883 | BN30: 6518.675 | BO30: 761.21667 | BP30: 607.86417 | BQ30: 679.1 | BR30: 20.804367
A31: 1981 | B31: 35.485 | C31: 36.675833 | D31: 34.294166 | E31: .. | F31: 53.62 | G31: .. | H31: 1.9833333 | I31: 4.6 | J31: 6.0303414 | K31: 50.03815 | L31: 2.07955 | M31: 2.86855 | N31: 2.2402167 | O31: 1.4702 | P31: 0.97327289 | Q31: 1.8130887 | R31: 1.6242095 | S31: 569.91667 | T31: 1257.4167 | U31: 467.48333 | V31: 1042.75 | W31: 570.66667 | X31: .. | Y31: 288.41667 | Z31: 506.85 | AA31: 252.58333 | AB31: 79.725833 | AC31: 130.78083 | AD31: 126.37167 | AE31: 458.98917 | AF31: .. | AG31: .. | AH31: .. | AI31: 154.58667 | AJ31: 174.96 | AK31: .. | AL31: 0.401275 | AM31: 0.4057275 | AN31: 2.4743583 | AO31: 0.77395022 | AP31: 2.7386583 | AQ31: 10.163298 | AR31: 0.41727945 | AS31: 0.43497153 | AT31: 0.37408333 | AU31: 2321.6867 | AV31: 212.79 | AW31: 154.56333 | AX31: .. | AY31: 349.40641 | AZ31: 244.69417 | BA31: 1.8710583 | BB31: .. | BC31: 1.1228333 | BD31: 48.958333 | BE31: 177.625 | BF31: 161.33333 | BG31: 182.5 | BH31: 110.16667 | BI31: 1262.7303 | BJ31: 28.09 | BK31: 1741.95 | BL31: 726.725 | BM31: 14159.125 | BN31: 5953.0833 | BO31: 845.65 | BP31: 459.75417 | BQ31: 447.48167 | BR31: 10.523183
A32: 1982 | B32: 32.647222 | C32: 33.418333 | D32: 31.756667 | E32: 32.766667 | F32: 54.7675 | G32: .. | H32: 2.465 | I32: 4.45 | J32: 6.0516224 | K32: 55.18853 | L32: 1.7356167 | M32: 3.0875583 | N32: 2.42365 | O32: 1.5433 | P32: 1.1449704 | Q32: 1.846399 | R32: 1.6385409 | S32: 464.41667 | T32: 827.5 | U32: 352.91667 | V32: 584.91667 | W32: 445.08333 | X32: .. | Y32: 244.60417 | Z32: 447.25 | AA32: 218.52917 | AB32: 63.7125 | AC32: 109.2625 | AD32: 108.52917 | AE32: 272.48167 | AF32: .. | AG32: .. | AH32: .. | AI32: 132.55167 | AJ32: 160.355 | AK32: .. | AL32: 0.37426667 | AM32: 0.38456667 | AN32: 2.389625 | AO32: 0.75978554 | AP32: 2.3769167 | AQ32: 13.283333 | AR32: 0.39945877 | AS32: 0.43925216 | AT32: 0.18564167 | AU32: 2563.9567 | AV32: 175.9175 | AW32: 146.45417 | AX32: .. | AY32: 339.38348 | AZ32: 232.44667 | BA32: 1.5972667 | BB32: .. | BC32: 0.857675 | BD32: 42.960417 | BE32: 166.625 | BF32: 138.41667 | BG32: 123.95833 | BH32: 83.25 | BI32: 991.56667 | BJ32: 32.5 | BK32: 1480.4417 | BL32: 545.6 | BM32: 12825.8 | BN32: 4837.4917 | BO32: 744.78333 | BP32: 375.79667 | BQ32: 328.29167 | BR32: 7.9298917
A33: 1983 | B33: 29.657778 | C33: 29.829167 | D33: 28.729167 | E33: 30.415 | F33: 38.1875 | G33: .. | H33: 2.5925 | I33: 4.05 | J33: 5.5458157 | K33: 54.49254 | L33: 2.1198667 | M33: 2.9112583 | N33: 2.7316417 | O33: 2.0970917 | P33: 1.8571548 | Q33: 2.5200431 | R33: 1.9140998 | S33: 729.875 | T33: 965.33333 | U33: 452.58333 | V33: 710.91667 | W33: 501.425 | X33: .. | Y33: 281.5875 | Z33: 526.88333 | AA33: 237.83333 | AB33: 70.890833 | AC33: 136.01667 | AD33: 128.755 | AE33: 256.8025 | AF33: .. | AG33: .. | AH33: .. | AI33: 137.30417 | AJ33: 157.415 | AK33: .. | AL33: 0.42880833 | AM33: 0.3732 | AN33: 2.4398917 | AO33: 0.77196606 | AP33: 1.9310333 | AQ33: 13.2075 | AR33: 0.3872415 | AS33: 0.48587988 | AT33: 0.186725 | AU33: 2656.545 | AV33: 160.76833 | AW33: 137.70583 | AX33: .. | AY33: 328.13557 | AZ33: 229.80833 | BA33: 1.8538917 | BB33: .. | BC33: 1.064175 | BD33: 39.802083 | BE33: 169.08333 | BF33: 134.66667 | BG33: 114.54167 | BH33: 74.416667 | BI33: 1438.4333 | BJ33: 29 | BK33: 1591.925 | BL33: 425.34167 | BM33: 12987.967 | BN33: 4672.8 | BO33: 764.33333 | BP33: 422.53 | BQ33: 423.3075 | BR33: 11.426283
A34: 1984 | B34: 28.5575 | C34: 28.801667 | D34: 27.493333 | E34: 29.3775 | F34: 30.958333 | G34: 32.870833 | H34: 2.655 | I34: 3.76 | J34: 5.2376808 | K34: 53.664089 | L34: 2.3959917 | M34: 3.1886583 | N34: 3.0367833 | O34: 2.74155 | P34: 2.5003454 | Q34: 2.9145965 | R34: 2.809678 | S34: 1154.5833 | T34: 836.58333 | U34: 373.16667 | V34: 1016.6667 | W34: 728.83333 | X34: .. | Y34: 282.08333 | Z34: 724 | AA34: 197.16667 | AB34: 78.723333 | AC34: 135.9425 | AD34: 118.18833 | AE34: 232.49917 | AF34: .. | AG34: .. | AH34: .. | AI34: 140.2275 | AJ34: 152.33333 | AK34: .. | AL34: 0.36947833 | AM34: 0.35239333 | AN34: 2.27315 | AO34: 0.87380114 | AP34: 1.9210917 | AQ34: 11.735 | AR34: 0.36269673 | AS34: 0.47928439 | AT34: 0.11466667 | AU34: 2786.3225 | AV34: 175.6425 | AW34: 156.76 | AX34: .. | AY34: 351.63746 | AZ34: 226.98 | BA34: 1.78485 | BB34: .. | BC34: 0.95765 | BD34: 33.066667 | BE34: 175.625 | BF34: 131.25 | BG34: 150.16667 | BH34: 84.125 | BI34: 1251.325 | BJ34: 26.15 | BK34: 1377.3167 | BL34: 442.60833 | BM34: 12233.492 | BN34: 4752.2083 | BO34: 921.93333 | BP34: 360.4775 | BQ34: 357.80833 | BR34: 8.144025
A35: 1985 | B35: 27.183333 | C35: 27.329167 | D35: 26.458333 | E35: 27.7625 | F35: 33.75 | G35: 34.9175 | H35: 2.5108333 | I35: 3.65 | J35: 5.23 | K35: 51.385279 | L35: 2.25445 | M35: 3.2307917 | N35: 2.6486333 | O35: 1.749475 | P35: 1.456686 | Q35: 2.2032507 | R35: 1.5885042 | S35: 590.16667 | T35: 675.75 | U35: 280.08333 | V35: 904.91667 | W35: 500.58333 | X35: .. | Y35: 224.41667 | Z35: 572 | AA35: 157.16667 | AB35: 58.816667 | AC35: 112.23333 | AD35: 103.00917 | AE35: 196.92917 | AF35: .. | AG35: .. | AH35: .. | AI35: 128.66 | AJ35: 135.82833 | AK35: .. | AL35: 0.37807083 | AM35: 0.39840833 | AN35: 2.1541417 | AO35: 0.83799443 | AP35: 1.8446917 | AQ35: 10.491667 | AR35: 0.35038761 | AS35: 0.44871366 | AT35: 0.089466667 | AU35: 2611.8167 | AV35: 173.88333 | AW35: 121.73417 | AX35: 307 | AY35: 307.13237 | AZ35: 210.87833 | BA35: 1.3182833 | BB35: .. | BC35: 0.75870833 | BD35: 36 | BE35: 157.16667 | BF35: 121.375 | BG35: 111.625 | BH35: 83.208333 | BI35: 1040.725 | BJ35: 26.56 | BK35: 1417.3833 | BL35: 390.85833 | BM35: 11539.042 | BN35: 4899.0417 | BO35: 783.44167 | BP35: 317.9075 | BQ35: 292.49917 | BR35: 6.1152333
A36: 1986 | B36: 14.35 | C36: 14.770833 | D36: 13.195833 | E36: 15.083333 | F36: 31.125 | G36: 30.37 | H36: 1.935 | I36: 3.65 | J36: 4.1 | K36: 43.627152 | L36: 2.0696167 | M36: 4.2925833 | N36: 3.2447583 | O36: 1.6595667 | P36: 1.1085275 | Q36: 2.1629677 | R36: 1.7072463 | S36: 296.5 | T36: 993.58333 | U36: 320.58333 | V36: 569.41667 | W36: 257 | X36: .. | Y36: 208.41667 | Z36: 342.41667 | AA36: 184.75 | AB36: 47.56 | AC36: 87.558333 | AD36: 82.413333 | AE36: 186.245 | AF36: 104.12088 | AG36: 104.25 | AH36: .. | AI36: 118.38917 | AJ36: 114.91667 | AK36: .. | AL36: 0.381725 | AM36: 0.39373083 | AN36: 2.09215 | AO36: 0.92551785 | AP36: 2.1532833 | AQ36: 12.885833 | AR36: 0.41016955 | AS36: 0.46030628 | AT36: 0.133375 | AU36: 2659.1783 | AV36: 221.64417 | AW36: 138.57667 | AX36: .. | AY36: 329.34244 | AZ36: 273.7175 | BA36: 1.056275 | BB36: .. | BC36: 0.80654167 | BD36: 36 | BE36: 138.16667 | BF36: 121.16667 | BG36: 70.75 | BH36: 72.958333 | BI36: 1149.935 | BJ36: 26.26 | BK36: 1373.7817 | BL36: 406.075 | BM36: 6161.3667 | BN36: 3881.2417 | BO36: 754.03333 | BP36: 367.69417 | BQ36: 465.04 | BR36: 5.4391917
A37: 1987 | B37: 18.145833 | C37: 18.341667 | D37: 16.9375 | E37: 19.158333 | F37: 27.5 | G37: 26.495 | H37: 1.6625 | I37: 2.59 | J37: 3.35 | K37: 34.770751 | L37: 1.9942167 | M37: 2.5049833 | N37: 2.2483417 | O37: 1.651225 | P37: 1.3489572 | Q37: 2.2945339 | R37: 1.310175 | S37: 442.25 | T37: 758.5 | U37: 383.41667 | V37: 499.75 | W37: 342.58333 | X37: .. | Y37: 215.75 | Z37: 334.25 | AA37: 203.25 | AB37: 55.001667 | AC37: 75.696667 | AD37: 72.763333 | AE37: 214.60833 | AF37: 191 | AG37: 153.91667 | AH37: .. | AI37: 112.10167 | AJ37: 112.89583 | AK37: .. | AL37: 0.39306667 | AM37: 0.45598417 | AN37: 2.3859417 | AO37: 0.90834018 | AP37: 2.1624583 | AQ37: 11.44 | AR37: 0.47262712 | AS37: 0.48130528 | AT37: 0.14895833 | AU37: 2745.5458 | AV37: 258.91583 | AW37: 201.7725 | AX37: .. | AY37: 401.29657 | AZ37: 399.40667 | BA37: 1.6484333 | BB37: .. | BC37: 0.98465 | BD37: 34.145833 | BE37: 160 | BF37: 138 | BG37: 82.5 | BH37: 67.291667 | BI37: 1565.3608 | BJ37: 25.3 | BK37: 1782.5033 | BL37: 596.84167 | BM37: 6664.8333 | BN37: 4872.2167 | BO37: 798.79167 | BP37: 446.4725 | BQ37: 555.72333 | BR37: 7.0100917
A38: 1988 | B38: 14.718056 | C38: 14.970833 | D38: 13.216667 | E38: 15.966667 | F38: 34.875 | G38: 28.104167 | H38: 1.6816667 | I38: 2.36 | J38: 3.34 | K38: 33.903311 | L38: 1.5846 | M38: 3.0337083 | N38: 2.0791833 | O38: 1.5780167 | P38: 1.3618249 | Q38: 2.0126899 | R38: 1.3594907 | S38: 564.83333 | T38: 935.75 | U38: 544.41667 | V38: 590.33333 | W38: 437.16667 | X38: .. | Y38: 303.5 | Z38: 463.41667 | AA38: 267.5 | AB38: 70.333333 | AC38: 106.89083 | AD38: 98.459167 | AE38: 277.47083 | AF38: .. | AG38: 219.75 | AH38: .. | AI38: 140.7225 | AJ38: 145.19917 | AK38: .. | AL38: 0.47813333 | AM38: 0.45340667 | AN38: 2.517075 | AO38: 1.0029 | AP38: 2.4107833 | AQ38: 12.44 | AR38: 0.52504125 | AS38: 0.48768033 | AT38: 0.22466667 | AU38: 2467.8958 | AV38: 271.32 | AW38: 200.86083 | AX38: .. | AY38: 402.32643 | AZ38: 358.83583 | BA38: 1.3994 | BB38: .. | BC38: 1.18495 | BD38: 31.6 | BE38: 180.16667 | BF38: 158.375 | BG38: 113.54167 | BH38: 86.833333 | BI38: 2550.4558 | BJ38: 24.3 | BK38: 2601.6717 | BL38: 656.225 | BM38: 7051.6333 | BN38: 13778.317 | BO38: 1241.5083 | BP38: 437.04833 | BQ38: 530.34333 | BR38: 6.5304583
A39: 1989 | B39: 17.838889 | C39: 18.216667 | D39: 15.704167 | E39: 19.595833 | F39: 38 | G39: 31 | H39: 1.6966667 | I39: 2.09 | J39: 3.28 | K39: 32.761239 | L39: 1.2410333 | M39: 2.3873083 | N39: 1.6556167 | O39: 1.8248417 | P39: 1.5292939 | Q39: 2.4274834 | R39: 1.5177699 | S39: 516.83333 | T39: 817.5 | U39: 408.41667 | V39: 774.75 | W39: 350.41667 | X39: .. | Y39: 275 | Z39: 431.5 | AA39: 247.58333 | AB39: 75.1375 | AC39: 111.52417 | AD39: 105.9375 | AE39: 299.1625 | AF39: .. | AG39: 218.58333 | AH39: .. | AI39: 161.26167 | AJ39: 169.235 | AK39: .. | AL39: 0.54679167 | AM39: 0.44542583 | AN39: 2.5690583 | AO39: 1.0995359 | AP39: 2.321025 | AQ39: 11.155 | AR39: 0.50160794 | AS39: 0.5027636 | AT39: 0.28205833 | AU39: 3167.5725 | AV39: 273.76167 | AW39: 190.58833 | AX39: .. | AY39: 485.27891 | AZ39: 350.32 | BA39: 1.674225 | BB39: .. | BC39: 0.9699 | BD39: 31 | BE39: 155.29167 | BF39: 144 | BG39: 102.95833 | BH39: 98.333333 | BI39: 1951.2567 | BJ39: 27.83 | BK39: 2848.41 | BL39: 673.475 | BM39: 8534.4333 | BN39: 13308.175 | BO39: 1658.7667 | BP39: 381.43167 | BQ39: 509.6425 | BR39: 5.5070917
A40: 1990 | B40: 22.879167 | C40: 23.683333 | D40: 20.4625 | E40: 24.491667 | F40: 39.666667 | G40: 32.875 | H40: 1.6983333 | I40: 2.82 | J40: 3.64 | K40: 36.495776 | L40: 1.2666667 | M40: 1.9722 | N40: 1.181725 | O40: 2.0575083 | P40: 1.8772818 | Q40: 2.8088912 | R40: 1.4863511 | S40: 336.5 | T40: 1325.5 | U40: 412.16667 | V40: 963.66667 | W40: 289.75 | X40: .. | Y40: 246.75 | Z40: 447.33333 | AA40: 200.16667 | AB40: 79.925 | AC40: 109.27583 | AD40: 103.93917 | AE40: 270.85417 | AF40: .. | AG40: 156.16667 | AH40: .. | AI40: 129.08917 | AJ40: 135.5225 | AK40: .. | AL40: 0.54085 | AM40: 0.53106083 | AN40: 2.5632333 | AO40: 1.082101 | AP40: 2.6566167 | AQ40: 10.7925 | AR40: 0.58318449 | AS40: 0.51262927 | AT40: 0.276675 | AU40: 3392.1858 | AV40: 343.46167 | AW40: 177.1925 | AX40: 533 | AY40: 533.08225 | AZ40: 354.86833 | BA40: 1.8191417 | BB40: .. | BC40: 0.86468333 | BD40: 31.291667 | BE40: 154.675 | BF40: 131.82083 | BG40: 115.64583 | BH40: 94.63125 | BI40: 1639.445 | BJ40: 32.5 | BK40: 2661.4825 | BL40: 810.54167 | BM40: 6085.3833 | BN40: 8864.1 | BO40: 1513.4583 | BP40: 383.46667 | BQ40: 471.58917 | BR40: 4.833225
A41: 1991 | B41: 19.370833 | C41: 20.066667 | D41: 16.5625 | E41: 21.483333 | F41: 39.666667 | G41: 31.5 | H41: 1.4866667 | I41: 3.1141667 | J41: 3.99 | K41: 35.561012 | L41: 1.1950583 | M41: 1.8733917 | N41: 1.071925 | O41: 1.6740083 | P41: 1.4298198 | Q41: 2.1631457 | R41: 1.4290689 | S41: 433 | T41: 1237.8333 | U41: 477.83333 | V41: 894.83333 | W41: 339 | X41: .. | Y41: 239.58333 | Z41: 453.83333 | AA41: 197.08333 | AB41: 78.286667 | AC41: 107.42 | AD41: 105.11167 | AE41: 293.27917 | AF41: 239.5 | AG41: 179.16667 | AH41: .. | AI41: 126.11333 | AJ41: 128.665 | AK41: .. | AL41: 0.55946167 | AM41: 0.52095083 | AN41: 2.6633583 | AO41: 1.0560865 | AP41: 2.331175 | AQ41: 11.54475 | AR41: 0.61210207 | AS41: 0.47515087 | AT41: 0.19759167 | AU41: 3500.0683 | AV41: 316.04583 | AW41: 191.48417 | AX41: .. | AY41: 552.51986 | AZ41: 372.37667 | BA41: 1.6774083 | BB41: .. | BC41: 0.82576667 | BD41: 31.5 | BE41: 158.25 | BF41: 133.12083 | BG41: 138.39583 | BH41: 106.42917 | BI41: 1302.1883 | BJ41: 34.76 | BK41: 2338.7825 | BL41: 557.61667 | BM41: 5595.0417 | BN41: 8155.6167 | BO41: 1116.9917 | BP41: 362.1825 | BQ41: 375.81667 | BR41: 4.0513583
A42: 1992 | B42: 19.020833 | C42: 19.3125 | D42: 17.1875 | E42: 20.5625 | F42: 38.5625 | G42: 28.833333 | H42: 1.7716667 | I42: 2.5583333 | J42: 3.5951126 | K42: 36.111923 | L42: 1.0995667 | M42: 1.4119167 | N42: 0.940425 | O42: 1.6042333 | P42: 1.4443061 | Q42: 1.6903467 | R42: 1.6780448 | S42: 577.58333 | T42: 799.13167 | U42: 481.5 | V42: 609.91667 | W42: 393.5 | X42: .. | Y42: 235.5 | Z42: 428.91667 | AA42: 204.41667 | AB42: 78.675 | AC42: 104.24583 | AD42: 102.75 | AE42: 268.22083 | AF42: 228.33333 | AG42: 177.91667 | AH42: .. | AI42: 145.14167 | AJ42: 151.2 | AK42: .. | AL42: 0.47308333 | AM42: 0.48924083 | AN42: 2.454575 | AO42: 1.057446 | AP42: 2.6514083 | AQ42: 10.953333 | AR42: 0.62776368 | AS42: 0.46958937 | AT42: 0.19959167 | AU42: 3439.5392 | AV42: 331.27833 | AW42: 209.50833 | AX42: .. | AY42: 607.21694 | AZ42: 380.76167 | BA42: 1.2783 | BB42: .. | BC42: 0.86158333 | BD42: 31.5 | BE42: 137.87292 | BF42: 120.73583 | BG42: 117.60417 | BH42: 111.75833 | BI42: 1254.2833 | BJ42: 33.1 | BK42: 2281.1575 | BL42: 541.36667 | BM42: 6101.025 | BN42: 7001.2292 | BO42: 1239.775 | BP42: 343.73333 | BQ42: 359.68583 | BR42: 3.9460083
A43: 1993 | B43: 16.841667 | C43: 17.020833 | D43: 14.941667 | E43: 18.5625 | F43: 31.333333 | G43: 26.958333 | H43: 2.1208333 | I43: 2.6716667 | J43: 3.5065988 | K43: 40.8308 | L43: 1.116925 | M43: 1.5602 | N43: 1.157375 | O43: 1.6148417 | P43: 1.4423389 | Q43: 1.8446903 | R43: 1.5575 | S43: 450.25 | T43: 1092.1458 | U43: 364.75 | V43: 739.08333 | W43: 377.75 | X43: .. | Y43: 255.08333 | Z43: 480.41667 | AA43: 208.16667 | AB43: 71.376667 | AC43: 102.09 | AD43: 99.026667 | AE43: 235.4125 | AF43: 202.41667 | AG43: 157.58333 | AH43: .. | AI43: 134.77417 | AJ43: 140.23833 | AK43: .. | AL43: 0.44302583 | AM43: 0.43249417 | AN43: 2.6175417 | AO43: 1.2053944 | AP43: 2.9072417 | AQ43: 11.390125 | AR43: 0.61948333 | AS43: 0.476475 | AT43: 0.220975 | AU43: 2695.3367 | AV43: 310.32 | AW43: 389.8075 | AX43: .. | AY43: 758.25006 | AZ43: 661.42667 | BA43: 1.2802667 | BB43: .. | BC43: 0.83128333 | BD43: 31.5 | BE43: 121.99583 | BF43: 111.94417 | BG43: 85.541667 | BH43: 112.54167 | BI43: 1139.0492 | BJ43: 29.09 | BK43: 1913.0767 | BL43: 406.35833 | BM43: 5161.1417 | BN43: 5293.4192 | BO43: 961.98333 | BP43: 359.77 | BQ43: 374.02583 | BR43: 4.3084
A44: 1994 | B44: 15.886667 | C44: 15.83 | D44: 14.666667 | E44: 17.163333 | F44: 32.3 | G44: 28.5625 | H44: 1.92 | I44: 2.4433333 | J44: 3.18 | K44: 37.085247 | L44: 1.3959667 | M44: 3.3076417 | N44: 2.6196833 | O44: 1.4921917 | P44: 1.3309512 | Q44: 1.5748128 | R44: 1.5708333 | S44: 607.5 | T44: 954.79833 | U44: 376.33333 | V44: 1022.75 | W44: 528.41667 | X44: .. | Y44: 251.83333 | Z44: 615.58333 | AA44: 192.41667 | AB44: 72.648333 | AC44: 107.55 | AD44: 103.86917 | AE44: 267.59167 | AF44: 229.91667 | AG44: 182.3 | AH44: .. | AI44: 138.555 | AJ44: 149.72917 | AK44: .. | AL44: 0.43979083 | AM44: 0.41134 | AN44: 2.33285 | AO44: 1.2188242 | AP44: 2.9751917 | AQ44: 13.075417 | AR44: 0.62166667 | AS44: 0.485675 | AT44: 0.26698333 | AU44: 2641.6608 | AV44: 330.26 | AW44: 307.54917 | AX44: .. | AY44: 821.03602 | AZ44: 601.16333 | BA44: 1.762775 | BB44: .. | BC44: 1.1258 | BD44: 31.833333 | BE44: 160.42431 | BF44: 132.105 | BG44: 93.885417 | BH44: 112.5 | BI44: 1476.7825 | BJ44: 26.47 | BK44: 2307.4175 | BL44: 547.76667 | BM44: 5463.85 | BN44: 6339.82 | BO44: 997.725 | BP44: 384.01167 | BQ44: 405.26167 | BR44: 5.2847
A45: 1995 | B45: 17.183333 | C45: 17.065833 | D45: 16.115 | E45: 18.369167 | F45: 39.371667 | G45: 35.229167 | H45: 1.7225 | I45: 2.7275 | J45: 3.4491667 | K45: 36.22021 | L45: 1.432425 | M45: 3.332325 | N45: 2.7707083 | O45: 1.4886333 | P45: 1.4221497 | Q45: 1.7423925 | R45: 1.3014167 | S45: 669.58333 | T45: 909.91667 | U45: 495 | V45: 990.91667 | W45: 628.25 | X45: .. | Y45: 259.25 | Z45: 625.08333 | AA45: 196.91667 | AB45: 104.01083 | AC45: 123.4875 | AD45: 118.97167 | AE45: 320.95833 | AF45: 297.66667 | AG45: 262.87083 | AH45: .. | AI45: 167.35833 | AJ45: 176.9825 | AK45: .. | AL45: 0.4451025 | AM45: 0.53146667 | AN45: 1.8686543 | AO45: 1.2231967 | AP45: 2.620925 | AQ45: 13.537308 | AR45: 0.68798333 | AS45: 0.50819167 | AT45: 0.29278333 | AU45: 2643.44 | AV45: 339.50833 | AW45: 255.62 | AX45: 596.13246 | AY45: 739.9511 | AZ45: 584.43583 | BA45: 2.1279 | BB45: .. | BC45: 1.5800417 | BD45: 32.666667 | BE45: 199.77222 | BF45: 149.63167 | BG45: 126.8625 | BH45: 112.5 | BI45: 1805.6575 | BJ45: 28.38 | BK45: 2935.6058 | BL45: 630.95 | BM45: 6213.8083 | BN45: 8228.0392 | BO45: 1031.1167 | BP45: 384.16417 | BQ45: 424.33667 | BR45: 5.2002417
A46: 1996 | B46: 20.42 | C46: 20.65 | D46: 18.54 | E46: 22.07 | F46: 38.074167 | G46: 33.5175 | H46: 2.7341667 | I46: 2.8441667 | J46: 3.6675 | K46: 49.207805 | L46: 1.4555667 | M46: 2.6942083 | N46: 1.8059417 | O46: 1.66055 | P46: 1.8891193 | Q46: 1.6695755 | R46: 1.42295 | S46: 751.58333 | T46: 962 | U46: 586 | V46: 897.25 | W46: 530.91667 | X46: 728 | Y46: 304.83333 | Z46: 551.5 | AA46: 267.5 | AB46: 119.66583 | AC46: 165.80917 | AD46: 150.02917 | AE46: 338.875 | AF46: 286.08333 | AG46: 232.70417 | AH46: .. | AI46: 187.41917 | AJ46: 207.6 | AK46: .. | AL46: 0.46958417 | AM46: 0.4916675 | AN46: 1.7499539 | AO46: 1.3737355 | AP46: 3.294575 | AQ46: 13.119317 | AR46: 0.68313333 | AS46: 0.49291667 | AT46: 0.263575 | AU46: 3055.3733 | AV46: 284.32 | AW46: 252.10083 | AX46: 512.40709 | AY46: 741.34855 | AZ46: 529.52833 | BA46: 1.7733333 | BB46: .. | BC46: 1.3937583 | BD46: 33.033333 | BE46: 198.10417 | BF46: 175.83 | BG46: 153.69167 | BH46: 112.5 | BI46: 1505.6608 | BJ46: 30 | BK46: 2294.8567 | BL46: 774.325 | BM46: 6165.075 | BN46: 7500.8167 | BO46: 1025.1417 | BP46: 387.69583 | BQ46: 397.1125 | BR46: 5.2013
A47: 1997 | B47: 19.171043 | C47: 19.090208 | D47: 18.097083 | E47: 20.325837 | F47: 35.099167 | G47: 31.349167 | H47: 2.48175 | I47: 2.7383333 | J47: 3.9083333 | K47: 45.80265 | L47: 1.6187333 | M47: 4.1679417 | N47: 1.736075 | O47: 2.0601083 | P47: 2.0201191 | Q47: 2.1449734 | R47: 2.0152639 | S47: 656.83333 | T47: 988.42 | U47: 606.25 | V47: 1010.4167 | W47: 545.83333 | X47: 651.83333 | Y47: 295.41667 | Z47: 564.75 | AA47: 275.75 | AB47: 97.238333 | AC47: 117.09167 | AD47: 109.62167 | AE47: 303.51 | AF47: 257.08333 | AG47: 210.38194 | AH47: .. | AI47: 143.64833 | AJ47: 159.48417 | AK47: 0.96801833 | AL47: 0.51705333 | AM47: 0.45896333 | AN47: 1.8481513 | AO47: 1.3445794 | AP47: 3.3934 | AQ47: 14.762858 | AR47: 0.62723333 | AS47: 0.48364167 | AT47: 0.25065 | AU47: 3531.5458 | AV47: 284.75417 | AW47: 238.2525 | AX47: 563.57585 | AY47: 664.52616 | AZ47: 484.95833 | BA47: 1.7475833 | BB47: .. | BC47: 1.0175167 | BD47: 32.5 | BE47: 186.98958 | BF47: 171.90917 | BG47: 117.49375 | BH47: 112.5 | BI47: 1599.33 | BJ47: 30.15 | BK47: 2276.7667 | BL47: 624.175 | BM47: 5646.7667 | BN47: 6927.3858 | BO47: 1316.125 | BP47: 331.09583 | BQ47: 394.915 | BR47: 4.9060333
A48: 1998 | B48: 13.064442 | C48: 12.716542 | D48: 12.127583 | E48: 14.3492 | F48: 29.230833 | G48: 26.839167 | H48: 2.0869167 | I48: 2.4158333 | J48: 3.0191667 | K48: 38.87248 | L48: 1.6763833 | M48: 2.9813167 | N48: 1.8225833 | O48: 2.0460583 | P48: 2.0746423 | Q48: 2.1646417 | R48: 1.8989277 | S48: 657.91667 | T48: 988.75 | U48: 661.91667 | V48: 909.41667 | W48: 671.08333 | X48: 686.66667 | Y48: 243.25 | Z48: 625.91667 | AA48: 170.33333 | AB48: 85.053333 | AC48: 101.98667 | AD48: 98.0375 | AE48: 304.15833 | AF48: 259.85833 | AG48: 213.02083 | AH48: .. | AI48: 111.515 | AJ48: 126.12667 | AK48: 1.0049575 | AL48: 0.489505 | AM48: 0.44240083 | AN48: 1.716113 | AO48: 1.3923461 | AP48: 2.7503 | AQ48: 14.239667 | AR48: 0.59748333 | AS48: 0.48641667 | AT48: 0.196725 | AU48: 3336.1217 | AV48: 286.4025 | AW48: 162.42583 | AX48: 526.32652 | AY48: 484.1479 | AZ48: 376.05333 | BA48: 1.4447167 | BB48: .. | BC48: 0.721575 | BD48: 32.5 | BE48: 186.86319 | BF48: 173.04917 | BG48: 83.216667 | BH48: 112.5 | BI48: 1357.4692 | BJ48: 31 | BK48: 1654.0583 | BL48: 528.64167 | BM48: 5540.3333 | BN48: 4629.5233 | BO48: 1024.4667 | BP48: 294.16083 | BQ48: 372.27833 | BR48: 5.5507917
A49: 1999 | B49: 18.071389 | C49: 17.808333 | D49: 17.165 | E49: 19.240833 | F49: 25.891667 | G49: 24.273333 | H49: 2.2666667 | I49: 2.1308333 | J49: 3.1375 | K49: 39.780539 | L49: 1.1353167 | M49: 2.2905833 | N49: 1.4887583 | O49: 1.8391 | P49: 1.649325 | Q49: 2.0679 | R49: 1.8002 | S49: 737.08333 | T49: 863.63417 | U49: 407.87917 | V49: 832.84167 | W49: 436 | X49: 694.08333 | Y49: 201.66667 | Z49: 426.46833 | AA49: 165.1675 | AB49: 75.938333 | AC49: 90.216667 | AD49: 84.389167 | AE49: 248.41667 | AF49: 216.29167 | AG49: 192.61667 | AH49: .. | AI49: 96.278333 | AJ49: 112.0425 | AK49: 0.85044083 | AL49: 0.37383083 | AM49: 0.43822667 | AN49: 1.8102502 | AO49: 1.3220004 | AP49: 2.6099917 | AQ49: 12.345872 | AR49: 0.59173333 | AS49: 0.46598333 | AT49: 0.13809167 | AU49: 3041.1825 | AV49: 269.27333 | AW49: 187.11 | AX49: 455.17111 | AY49: 600.81585 | AZ49: 440.54917 | BA49: 1.171075 | BB49: 0.591075 | BC49: 0.628475 | BD49: 42.802083 | BE49: 171.1 | BF49: 154.49083 | BG49: 65.942361 | BH49: 112.5 | BI49: 1361.09 | BJ49: 27.59 | BK49: 1572.8608 | BL49: 502.61667 | BM49: 5403.6167 | BN49: 6011.2275 | BO49: 1076.3417 | BP49: 278.76833 | BQ49: 376.94917 | BR49: 5.2154583
A50: 2000 | B50: 28.229719 | C50: 28.272916 | D50: 26.084117 | E50: 30.332125 | F50: 26.25 | G50: 26.57 | H50: 4.3083333 | I50: 3.8583333 | J50: 4.7125 | K50: 73.8528 | L50: 0.90579167 | M50: 1.9196667 | N50: 0.913025 | O50: 1.8762417 | P50: 1.7933417 | Q50: 1.8060167 | R50: 2.0285667 | S50: 450.33333 | T50: 870.68 | U50: 407.87917 | V50: 756.7625 | W50: 310.25 | X50: 443.5 | Y50: 211.83333 | Z50: 338.14 | AA50: 203.69583 | AB50: 77.234167 | AC50: 88.534167 | AD50: 88.003333 | AE50: 202.39583 | AF50: 172.8125 | AG50: 143.47361 | AH50: .. | AI50: 98.914167 | AJ50: 114.0875 | AK50: 0.712425 | AL50: 0.42399833 | AM50: 0.3632125 | AN50: 1.9254784 | AO50: 1.3106466 | AP50: 2.618475 | AQ50: 14.017709 | AR50: 0.55515813 | AS50: 0.42759167 | AT50: 0.18035833 | AU50: 2976.2133 | AV50: 275.425 | AW50: 189.94667 | AX50: 489.05069 | AY50: 594.69697 | AZ50: 448.24 | BA50: 1.30215 | BB50: 0.62921667 | BC50: 0.66718333 | BD50: 44 | BE50: 147.66875 | BF50: 137.70833 | BG50: 100.92292 | BH50: 112.5 | BI50: 1549.1408 | BJ50: 28.79 | BK50: 1813.4692 | BL50: 453.94167 | BM50: 5435.7083 | BN50: 8637.7392 | BO50: 1128.1333 | BP50: 279.03167 | BQ50: 544.63083 | BR50: 4.9532417
A51: 2001 | B51: 24.351825 | C51: 24.421572 | D51: 22.714821 | E51: 25.919083 | F51: 32.3125 | G51: 33.864167 | H51: 3.9558333 | I51: 4.0575 | J51: 4.6341667 | K51: 70.466023 | L51: 1.0687333 | M51: 1.3731167 | N51: 0.607175 | O51: 1.5981417 | P51: 1.6166083 | Q51: 1.66115 | R51: 1.5166667 | S51: 318.08333 | T51: 866.42167 | U51: 465.32417 | V51: 759.23417 | W51: 287.45833 | X51: 305.30083 | Y51: 195.83333 | Z51: 353.235 | AA51: 204.63417 | AB51: 93.936667 | AC51: 89.640833 | AD51: 95.233333 | AE51: 172.83833 | AF51: 153.06 | AG51: 134.10556 | AH51: .. | AI51: 107.72417 | AJ51: 126.80833 | AK51: 0.777235 | AL51: 0.58324833 | AM51: 0.59549729 | AN51: 2.1063858 | AO51: 1.402763 | AP51: 2.9118 | AQ51: 13.67783 | AR51: 0.52865079 | AS51: 0.47035833 | AT51: 0.19039167 | AU51: 3004.615 | AV51: 266.0525 | AW51: 159.0525 | AX51: 471.93373 | AY51: 481.35198 | AZ51: 409.8075 | BA51: 1.058075 | BB51: 0.51526667 | BC51: 0.575125 | BD51: 44 | BE51: 143.50972 | BF51: 126.87583 | BG51: 96.453472 | BH51: 112.5 | BI51: 1443.6342 | BJ51: 30.03 | BK51: 1578.2883 | BL51: 476.15833 | BM51: 4484.4417 | BN51: 5944.7267 | BO51: 885.76667 | BP51: 270.98917 | BQ51: 529.52917 | BR51: 4.376
A52: 2002 | B52: 24.927748 | C52: 24.969478 | D52: 23.7206 | E52: 26.093168 | F52: 25.309375 | G52: 26.024167 | H52: 3.355 | I52: 3.0516667 | J52: 4.2816667 | K52: 58.149359 | L52: 1.7778583 | M52: 1.3566083 | N52: 0.66178333 | O52: 1.506 | P52: 1.5620167 | Q52: 1.4638917 | R52: 1.4920833 | S52: 421 | T52: 723.3475 | U52: 638.83333 | V52: 719.4325 | W52: 410.895 | X52: 412.51417 | Y52: 212.66667 | Z52: 461.71 | AA52: 195.70417 | AB52: 108.9675 | AC52: 99.270833 | AD52: 101.74167 | AE52: 191.87333 | AF52: 174.97583 | AG52: 150.18194 | AH52: .. | AI52: 129.9575 | AJ52: 148.0775 | AK52: 0.75942417 | AL52: 0.52857583 | AM52: 0.56453208 | AN52: 2.1085904 | AO52: 1.3907294 | AP52: 3.3034167 | AQ52: 10.389272 | AR52: 0.54917213 | AS52: 0.461375 | AT52: 0.151825 | AU52: 2744.4733 | AV52: 236.02576 | AW52: 163.40583 | AX52: 486.34424 | AY52: 526.81177 | AZ52: 402.73 | BA52: 1.019225 | BB52: 0.75153333 | BC52: 0.7649 | BD52: 44 | BE52: 152.19375 | BF52: 133.06333 | BG52: 94.41875 | BH52: 112.5 | BI52: 1349.915 | BJ52: 29.31 | BK52: 1559.4775 | BL52: 452.68333 | BM52: 4060.5 | BN52: 6771.7508 | BO52: 778.75 | BP52: 309.97167 | BQ52: 539.51417 | BR52: 4.60105
A53: 2003 | B53: 28.898903 | C53: 28.851391 | D53: 26.738141 | E53: 31.107178 | F53: 26.090625 | G53: 30.235417 | H53: 5.4919827 | I53: 3.9066667 | J53: 4.7308333 | K53: 88.468491 | L53: 1.7508772 | M53: 1.4153853 | N53: 0.81449685 | O53: 1.5166419 | P53: 1.5410882 | Q53: 1.4652122 | R53: 1.543625 | S53: 467.33333 | T53: 997.18545 | U53: 640.33607 | V53: 1209.4475 | W53: 476.70333 | X53: 457.03917 | Y53: 264 | Z53: 558.585 | AA53: 232.64 | AB53: 104.74049 | AC53: 105.37008 | AD53: 106.5346 | AE53: 197.61667 | AF53: 181.71667 | AG53: 151.46667 | AH53: .. | AI53: 138.57684 | AJ53: 146.1431 | AK53: 0.79039951 | AL53: 0.37478708 | AM53: 0.68077301 | AN53: 2.1266683 | AO53: 1.4597544 | AP53: 3.8837791 | AQ53: 10.77753 | AR53: 0.59714496 | AS53: 0.47371148 | AT53: 0.15630197 | AU53: 2646.1022 | AV53: 279.48537 | AW53: 187.16374 | AX53: 551.62958 | AY53: 550.99068 | AZ53: 431.87835 | BA53: 1.3991114 | BB53: 1.004075 | BC53: 1.0827103 | BD53: 44 | BE53: 171.66563 | BF53: 149.33333 | BG53: 138.18542 | BH53: 112.5 | BI53: 1431.2938 | BJ53: 31.95 | BK53: 1779.1448 | BL53: 515.02942 | BM53: 4894.8969 | BN53: 9629.4682 | BO53: 827.69542 | BP53: 363.50917 | BQ53: 691.71417 | BR53: 4.8762417
A54: 2004 | B54: 37.733388 | C54: 38.30068 | D54: 33.455866 | E54: 41.443617 | F54: 52.947917 | G54: 54.684375 | H54: 5.8948671 | I54: 4.2775 | J54: 5.1275 | K54: 95.392538 | L54: 1.5498486 | M54: 1.7739842 | N54: 0.79303856 | O54: 1.6856025 | P54: 1.7809365 | Q54: 1.7216211 | R54: 1.55425 | S54: 660.75 | T54: 988.1425 | U54: 648.58333 | V54: 1291.6283 | W54: 499.28083 | X54: 657.45 | Y54: 306.5 | Z54: 618.22583 | AA54: 259.88667 | AB54: 98.988548 | AC54: 111.80348 | AD54: 109.77574 | AE54: 237.66667 | AF54: 225.425 | AG54: 205.14167 | AH54: 226.32171 | AI54: 144.44396 | AJ54: 156.88168 | AK54: 0.89199256 | AL54: 0.52458277 | AM54: 0.85752322 | AN54: 2.6730834 | AO54: 1.6691825 | AP54: 4.5988931 | AQ54: 10.117369 | AR54: 0.6696875 | AS54: 0.45467869 | AT54: 0.15798608 | AU54: 2740.215 | AV54: 331.30375 | AW54: 197.25557 | AX54: 586.40105 | AY54: 581.29371 | AZ54: 464.82048 | BA54: 1.3657212 | BB54: 1.2066 | BC54: 1.280375 | BD54: 44 | BE54: 204.74375 | BF54: 186.3125 | BG54: 174.91458 | BH54: 125.55 | BI54: 1715.541 | BJ54: 37.9 | BK54: 2865.8849 | BL54: 886.545 | BM54: 8512.7334 | BN54: 13823.241 | BO54: 1047.7532 | BP54: 409.21158 | BQ54: 845.35 | BR54: 6.6578667
A55: 2005 | B55: 53.391025 | C55: 54.43413 | D55: 49.294159 | E55: 56.444784 | F55: 47.620903 | G55: 46.196944 | H55: 8.9156728 | I55: 6.3266667 | J55: 5.99 | K55: 142.40133 | L55: 1.5381196 | M55: 2.5321714 | N55: 1.1145089 | O55: 1.6470805 | P55: 1.8429193 | Q55: 1.6208222 | R55: 1.4775 | S55: 616.97917 | T55: 874.22167 | U55: 676.59494 | V55: 1170.9817 | W55: 450.56417 | X55: 630.82167 | Y55: 274.6875 | Z55: 544.59333 | AA55: 236.76167 | AB55: 95.077129 | AC55: 98.671791 | AD55: 96.215435 | AE55: 286.27083 | AF55: 265.37917 | AG55: 217.81667 | AH55: .. | AI55: 135.72002 | AJ55: 152.35059 | AK55: 1.1725796 | AL55: 0.60284246 | AM55: 0.87467397 | AN55: 2.7346106 | AO55: 1.6293734 | AP55: 4.4384745 | AQ55: 9.7060233 | AR55: 0.66542205 | AS55: 0.46926529 | AT55: 0.21792669 | AU55: 2789.6515 | AV55: 334.36862 | AW55: 203.12028 | AX55: 559.13646 | AY55: 659.38228 | AZ55: 508.60911 | BA55: 1.216967 | BB55: 1.3863583 | BC55: 1.488 | BD55: 44 | BE55: 226.78542 | BF55: 201.47917 | BG55: 217.35208 | BH55: 155 | BI55: 1898.3081 | BJ55: 65 | BK55: 3678.8764 | BL55: 976.36817 | BM55: 7379.8279 | BN55: 14743.959 | BO55: 1381.3059 | BP55: 444.84258 | BQ55: 896.52833 | BR55: 7.3083667
A56: 2006 | B56: 64.288259 | C56: 65.391381 | D56: 61.430812 | E56: 66.042584 | F56: 49.089583 | G56: 50.694167 | H56: 6.7195431 | I56: 8.4708333 | J56: 7.075 | K56: 126.6613 | L56: 1.5919022 | M56: 2.5221037 | N56: 1.4893127 | O56: 1.8720771 | P56: 1.9097188 | Q56: 1.754207 | R56: 1.9523056 | S56: 606.90972 | T56: 875.26228 | U56: 755.35209 | V56: 1019.4783 | W56: 508.29917 | X56: 578.5675 | Y56: 268.64583 | Z56: 599.335 | AA56: 227.36167 | AB56: 116.6151 | AC56: 121.85102 | AD56: 122.93926 | AE56: 304.87639 | AF56: 277.12361 | AG56: 219.5125 | AH56: .. | AI56: 158.96785 | AJ56: 192.04336 | AK56: 0.89702574 | AL56: 0.67724399 | AM56: 0.82918481 | AN56: 2.649843 | AO56: 1.526141 | AP56: 4.0359058 | AQ56: 9.6040596 | AR56: 0.64564119 | AS56: 0.48764578 | AT56: 0.32587239 | AU56: 2969.1955 | AV56: 318.47839 | AW56: 239.42915 | AX56: 622.86583 | AY56: 749.34344 | AZ56: 595.56384 | BA56: 1.2665542 | BB56: 1.9460667 | BC56: 2.07875 | BD56: 44 | BE56: 229.87153 | BF56: 201.63333 | BG56: 222.13889 | BH56: 178.33333 | BI56: 2569.8987 | BJ56: 69.333333 | BK56: 6722.1345 | BL56: 1289.7221 | BM56: 8780.8253 | BN56: 24254.409 | BO56: 3275.2917 | BP56: 604.33583 | BQ56: 1140.78 | BR56: 11.559233
A57: 2007 | B57: 71.116559 | C57: 72.696171 | D57: 68.369054 | E57: 72.284453 | F57: 65.733125 | G57: 62.650833 | H57: 6.9819507 | I57: 8.555 | J57: 7.6833333 | K57: 130.66008 | L57: 1.9522692 | M57: 2.7236978 | N57: 1.9091825 | O57: 2.0361013 | P57: 2.5221221 | Q57: 1.9212374 | R57: 1.6649444 | S57: 918.875 | T57: 1247.5528 | U57: 1166.49 | V57: 1375.1392 | W57: 816.68667 | X57: 888.405 | Y57: 383.10333 | Z57: 886.05667 | AA57: 321.9375 | AB57: 172.38122 | AC57: 163.66491 | AD57: 162.69361 | AE57: 326.43194 | AF57: 306.50139 | AG57: 272.31667 | AH57: .. | AI57: 238.58767 | AJ57: 255.20611 | AK57: 1.0370083 | AL57: 0.67581164 | AM57: 0.95668085 | AN57: 2.6953684 | AO57: 1.7235895 | AP57: 4.1196086 | AQ57: 9.6795678 | AR57: 0.68091299 | AS57: 0.45774555 | AT57: 0.22215221 | AU57: 3315.0567 | AV57: 381.32151 | AW57: 267.98066 | AX57: 759.83871 | AY57: 806.29677 | AZ57: 640.71774 | BA57: 1.395157 | BB57: 2.1556583 | BC57: 2.2630583 | BD57: 52.020833 | BE57: 391.9625 | BF57: 339.05417 | BG57: 307.10764 | BH57: 195.41667 | BI57: 2638.1792 | BJ57: 122.9875 | BK57: 7118.226 | BL57: 2579.9854 | BM57: 14536.835 | BN57: 37229.807 | BO57: 3242.3576 | BP57: 696.72025 | BQ57: 1304.94 | BR57: 13.391975
A58: 2008 | B58: 96.990454 | C58: 97.636484 | D58: 93.777133 | E58: 99.557744 | F58: 127.10417 | G58: 120.59833 | H58: 8.8572024 | I58: 13.406667 | J58: 12.526667 | K58: 179.77798 | L58: 2.5771163 | M58: 3.0815995 | N58: 2.3209137 | O58: 2.4204736 | P58: 2.7892556 | Q58: 2.254568 | R58: 2.2175972 | S58: 1224 | T58: 1600.9933 | U58: 1203.5308 | V58: 2144.74 | W58: 1042.9233 | X58: 1124.8808 | Y58: 521.87 | Z58: 1260.8108 | AA58: 442.13833 | AB58: 200.51553 | AC58: 223.11683 | AD58: 207.8307 | AE58: 650.1875 | AF58: .. | AG58: 482.27639 | AH58: .. | AI58: 271.52033 | AJ58: 326.03005 | AK58: 1.1877105 | AL58: 0.84421255 | AM58: 1.107307 | AN58: 3.2354085 | AO58: 1.8654511 | AP58: 4.5850681 | AQ58: 10.512179 | AR58: 0.69692697 | AS58: 0.4685823 | AT58: 0.28213624 | AU58: 3588.7408 | AV58: 526.88664 | AW58: 292.29698 | AX58: 958.27847 | AY58: 889.09163 | AZ58: 645.45483 | BA58: 1.5739062 | BB58: 2.5299917 | BC58: 2.5862583 | BD58: 242.73958 | BE58: 861.61875 | BF58: 879.38125 | BG58: 514.97917 | BH58: 455.96875 | BI58: 2572.7892 | BJ58: 155.99333 | BK58: 6955.8798 | BL58: 2090.6634 | BM58: 18510.091 | BN58: 21110.645 | BO58: 1874.7087 | BP58: 871.70725 | BQ58: 1574.4992 | BR58: 14.996533
A59: 2009 | B59: 61.756922 | C59: 61.862207 | D59: 61.75492 | E59: 61.65364 | F59: 71.844167 | G59: 64.683333 | H59: 3.9502917 | I59: 8.71 | J59: 8.9358333 | K59: 95.430939 | L59: 2.8887503 | M59: 3.1711429 | N59: 1.6441615 | O59: 2.7240133 | P59: 3.1372094 | Q59: 2.5152749 | R59: 2.5195556 | S59: 725.375 | T59: 1130.0158 | U59: 1191.1042 | V59: 1352.5967 | W59: 741.14583 | X59: 699.02167 | Y59: 423.6225 | Z59: 853.065 | AA59: 423.57583 | AB59: 128.32219 | AC59: 165.50963 | AD59: 151.05413 | AE59: 554.99306 | AF59: 458.06667 | AG59: 326.35972 | AH59: .. | AI59: 185.95359 | AJ59: 224.06988 | AK59: 1.1449028 | AL59: 0.84714065 | AM59: 0.90903947 | AN59: 2.7297237 | AO59: 1.8877883 | AP59: 4.2764964 | AQ59: 8.9182391 | AR59: 0.52435188 | AS59: 0.54875122 | AT59: 0.4000283 | AU59: 4235.1986 | AV59: 421.4721 | AW59: 287.20279 | AX59: 748.91833 | AY59: 805.52444 | AZ59: 564.62352 | BA59: 1.3820212 | BB59: 1.8001854 | BC59: 1.9206859 | BD59: 222.75 | BE59: 288.46875 | BF59: 257.41667 | BG59: 251.07917 | BH59: 558.47917 | BI59: 1664.8295 | BJ59: 79.979167 | BK59: 5149.7386 | BL59: 1719.2665 | BM59: 13573.877 | BN59: 14654.629 | BO59: 1655.1144 | BP59: 972.96592 | BQ59: 1203.4008 | BR59: 14.643533
A60: 2010 | B60: 79.040772 | C60: 79.63563 | D60: 78.061155 | E60: 79.425531 | F60: 98.966042 | G60: 91.622708 | H60: 4.3852538 | I60: 8.2875 | J60: 10.848333 | K60: 100 | L60: 3.1330039 | M60: 4.3200999 | N60: 1.7359362 | O60: 2.8849353 | P60: 3.2896455 | Q60: 2.8051187 | R60: 2.5600417 | S60: 1123.5833 | T60: 1240.6574 | U60: 1138.9596 | V60: 1400.9917 | W60: 933.02333 | X60: 1187.405 | Y60: 447.10167 | Z60: 1000.8558 | AA60: 398.34583 | AB60: 158.38667 | AC60: 185.91421 | AD60: 165.4039 | AE60: 488.90694 | AF60: 441.50833 | AG60: 383.65833 | AH60: 429.18633 | AI60: 229.6771 | AJ60: 223.58211 | AK60: 1.0022412 | AL60: 0.8683206 | AM60: 1.0332033 | AN60: 3.4189063 | AO60: 1.8922913 | AP60: 5.3143171 | AQ60: 10.635638 | AR60: 0.44179146 | AS60: 0.79248467 | AT60: 0.4693469 | AU60: 4333.225 | AV60: 428.5608 | AW60: 278.17199 | AX60: 812.69368 | AY60: 848.27196 | AZ60: 569.08783 | BA60: 2.2833805 | BB60: 3.3807708 | BC60: 3.6538649 | BD60: 105.3125 | BE60: 456.42708 | BF60: 381.88958 | BG60: 288.90417 | BH60: 332.14583 | BI60: 2173.117 | BJ60: 145.86319 | BK60: 7534.7796 | BL60: 2148.4493 | BM60: 20405.623 | BN60: 21808.852 | BO60: 2160.7432 | BP60: 1224.6643 | BQ60: 1609.7542 | BR60: 20.152958
A61: 2011 | B61: 104.0094 | C61: 110.93993 | D61: 106.03394 | E61: 95.054329 | F61: 121.44833 | G61: 116.29667 | H61: 3.9985786 | I61: 10.515 | J61: 14.655833 | K61: 108.47349 | L61: 2.9800767 | M61: 5.9761369 | N61: 2.407592 | O61: 2.9205489 | P61: 3.2641364 | Q61: 2.7785519 | R61: 2.7189583 | S61: 1730.0833 | T61: 1883.8294 | U61: 1442.0583 | V61: 1866.09 | W61: 1193.37 | X61: 1653.645 | Y61: 537.51917 | Z61: 1297.66 | AA61: 408.67167 | AB61: 207.19692 | AC61: 291.68407 | AD61: 268.74794 | AE61: 543.02917 | AF61: 506.0375 | AG61: 458.55833 | AH61: 513.63971 | AI61: 285.91335 | AJ61: 316.26413 | AK61: 1.1247368 | AL61: 0.96799467 | AM61: 0.8911005 | AN61: 4.0773528 | AO61: 1.9263298 | AP61: 6.6307269 | AQ61: 12.111815 | AR61: 0.45461721 | AS61: 0.83915666 | AT61: 0.57316446 | AU61: 4485.0507 | AV61: 484.80996 | AW61: 390.5122 | AX61: 825.75143 | AY61: 939.44698 | AZ61: 607.54112 | BA61: 3.3285062 | BB61: 4.5190091 | BC61: 4.823157 | BD61: 163.55208 | BE61: 516.2875 | BF61: 538.26042 | BG61: 398.92292 | BH61: 392.82292 | BI61: 2401.3867 | BJ61: 167.75417 | BK61: 8828.1875 | BL61: 2400.8121 | BM61: 26053.675 | BN61: 22910.357 | BO61: 2193.9004 | BP61: 1569.2108 | BQ61: 1719.4817 | BR61: 35.224117
A62: 2012 | B62: 105.00963 | C62: 111.96556 | D62: 108.90445 | E62: 94.158878 | F62: 96.364167 | G62: 92.92 | H62: 2.7520417 | I62: 11.473333 | J62: 16.553333 | K62: 99.177764 | L62: 2.3918691 | M62: 4.1109571 | N62: 2.2668286 | O62: 2.8977862 | P62: 3.0626098 | Q62: 2.7502351 | R62: 2.8805139 | S62: 1110.8333 | T62: 2442.8094 | U62: 1527.7717 | V62: 2359.0583 | W62: 1043.3975 | X62: 1107.3783 | Y62: 595.5075 | Z62: 1225.6025 | AA62: 531.69583 | AB62: 240.28064 | AC62: 298.41696 | AD62: 271.93008 | AE62: 562.98333 | AF62: 543.79722 | AG62: 525.07083 | AH62: 434.44 | AI62: 295.36619 | AJ62: 313.24227 | AK62: 1.099727 | AL62: 0.98398391 | AM62: 0.867958 | AN62: 4.2060659 | AO62: 2.079023 | AP62: 6.0911359 | AQ62: 11.464391 | AR62: 0.42013525 | AS62: 0.6356396 | AT62: 0.47494541 | AU62: 4302.3535 | AV62: 451.38709 | AW62: 360.5103 | AX62: 759.32139 | AY62: 876.34202 | AZ62: 610.34222 | BA62: 1.9671165 | BB62: 3.155761 | BC62: 3.3772607 | BD62: 184.92708 | BE62: 480.23819 | BF62: 462 | BG62: 398.60069 | BH62: 465.375 | BI62: 2023.2832 | BJ62: 128.49593 | BK62: 7962.3471 | BL62: 2064.6383 | BM62: 21125.994 | BN62: 17547.546 | BO62: 1950.4135 | BP62: 1669.5177 | BQ62: 1550.8358 | BR62: 31.137408
A63: 2013 | B63: 104.0775 | C63: 108.85637 | D63: 105.43335 | E63: 97.942766 | F63: 84.562169 | G63: 80.238559 | H63: 3.7239833 | I63: 11.785833 | J63: 15.955833 | K63: 112.06123 | L63: 2.4388467 | M63: 3.0759898 | N63: 2.0758545 | O63: 2.8619951 | P63: 3.4530546 | Q63: 2.7340973 | R63: 2.3988333 | S63: 939.46917 | T63: 1514.2992 | U63: 1750.815 | V63: 1820.6217 | W63: 870.72583 | X63: 896.91917 | Y63: 551.38917 | Z63: 1055.3933 | AA63: 543.4625 | AB63: 203.00876 | AC63: 259.38922 | AD63: 243.28292 | AE63: 505.89167 | AF63: 472.95972 | AG63: 473.98941 | AH63: 392.40208 | AI63: 276.73346 | AJ63: 312.24787 | AK63: 1.021979 | AL63: 0.92407451 | AM63: 0.96731982 | AN63: 4.1283163 | AO63: 2.173688 | AP63: 5.1732068 | AQ63: 14.174604 | AR63: 0.43382929 | AS63: 0.45050058 | AT63: 0.39004471 | AU63: 4588.8194 | AV63: 463.52885 | AW63: 305.43418 | AX63: 749.16983 | AY63: 852.79773 | AZ63: 560.23496 | BA63: 1.9926963 | BB63: 2.5169333 | BC63: 2.79455 | BD63: 126.32292 | BE63: 410.97292 | BF63: 380.75 | BG63: 339.61458 | BH63: 395 | BI63: 1846.669 | BJ63: 135.36119 | BK63: 7332.1005 | BL63: 2139.7901 | BM63: 22282.797 | BN63: 15031.797 | BO63: 1910.2565 | BP63: 1411.4623 | BQ63: 1486.5451 | BR63: 23.849686
A64: 2014 | B64: 96.235 | C64: 98.9375 | D64: 96.655 | E64: 93.1125 | F64: 70.13 | G64: 72.338333 | H64: 4.3694917 | I64: 10.051667 | J64: 16.035736 | K64: 111.70983 | L64: 3.06224 | M64: 4.4237905 | N64: 2.2164515 | O64: 2.7204779 | P64: 3.5354067 | Q64: 2.5809715 | R64: 2.0450556 | S64: 1281.1242 | T64: 1258.3175 | U64: 1680.645 | V64: 1394.985 | W64: 837.46917 | X64: 1119.6917 | Y64: 484.8575 | Z64: 905.96917 | AA64: 522.4675 | AB64: 145.90298 | AC64: 192.88122 | AD64: 210.39424 | AE64: 422.83333 | AF64: 382.16667 | AG64: 425.14833 | AH64: 407.20917 | AI64: 245.21164 | AJ64: 284.88592 | AK64: 1.0425702 | AL64: 0.92778907 | AM64: 0.78355016 | AN64: 5.0504537 | AO64: 2.3224215 | AP64: 6.3895877 | AQ64: 17.794407 | AR64: 0.43401232 | AS64: 0.53250759 | AT64: 0.37498749 | AU64: 4990.7722 | AV64: 465.16509 | AW64: 282.04118 | AX64: 789.45189 | AY64: 897.942 | AZ64: 517.32693 | BA64: 1.8319474 | BB64: 1.7139167 | BC64: 1.9514917 | BD64: 110.45833 | BE64: 429.58646 | BF64: 382 | BG64: 308.4375 | BH64: 296.625 | BI64: 1867.42 | BJ64: 96.952462 | BK64: 6863.3975 | BL64: 2095.4583 | BM64: 21898.872 | BN64: 16893.376 | BO64: 2160.9708 | BP64: 1265.5775 | BQ64: 1383.5708 | BR64: 19.0715
A65: 2015 | B65: 50.752778 | C65: 52.37 | D65: 51.179167 | E65: 48.709167 | F65: 58.939167 | G65: 56.708333 | H65: 2.6137083 | I65: 6.8211831 | J65: 10.934687 | K65: 71.575137 | L65: 3.135045 | M65: 3.5260692 | N65: 1.9411679 | O65: 2.7771496 | P65: 2.975 | Q65: 2.3917681 | R65: 2.9646806 | S65: 1103.5117 | T65: 1304.8724 | U65: 1554.185 | V65: 1377.9592 | W65: 663.39083 | X65: 903.34917 | Y65: 392.1225 | Z65: 755.6325 | AA65: 389.455 | AB65: 121.33065 | AC65: 169.75022 | AD65: 201.63087 | AE65: 386 | AF65: 372.58333 | AG65: 386.03333 | AH65: 351.83583 | AI65: 206.37664 | AJ65: 204.44913 | AK65: 0.9033957 | AL65: 0.95691416 | AM65: 0.67567492 | AN65: 4.5591542 | AO65: 1.99094 | AP65: 5.220405 | AQ65: 13.215227 | AR65: 0.36255508 | AS65: 0.5467825 | AT65: 0.29626418 | AU65: 4908.2951 | AV65: 388.57875 | AW65: 246.01583 | AX65: 732.57647 | AY65: 833.2505 | AZ65: 451.24835 | BA65: 1.5524199 | BB65: 1.3658167 | BC65: 1.571325 | BD65: 120.31458 | BE65: 416.62396 | BF65: 377.6 | BG65: 277.9375 | BH65: 296.06458 | BI65: 1664.6808 | BJ65: 55.854167 | BK65: 5510.4567 | BL65: 1787.8192 | BM65: 16066.632 | BN65: 11862.635 | BO65: 1931.6783 | BP65: 1160.6633 | BQ65: 1053.2033 | BR65: 15.720667
A66: 2016 | B66: 42.811944 | C66: 44.0475 | D66: 41.200833 | E66: 43.1875 | F66: 66.123333 | G66: 63.946667 | H66: 2.4922167 | I66: 4.5634228 | J66: 7.372444 | K66: 56.95309 | L66: 2.8907617 | M66: 3.6110757 | N66: 1.953128 | O66: 2.6849336 | P66: 3.3016667 | Q66: 2.3317314 | R66: 2.4214028 | S66: 1481.7767 | T66: 1392.862 | U66: 1490.6367 | V66: 1380.6308 | W66: 735.70333 | X66: 1301.3192 | Y66: 405.4475 | Z66: 814.99417 | AA66: 374.66167 | AB66: 103.91568 | AC66: 159.16089 | AD66: 155.59106 | AE66: 396.16667 | AF66: 385.33333 | AG66: 380.335 | AH66: 356.09667 | AI66: 176.30378 | AJ66: 166.63254 | AK66: 0.90527511 | AL66: 1.0011501 | AM66: 0.88967978 | AN66: 4.06091 | AO66: 1.8525576 | AP66: 4.6942286 | AQ66: 11.216372 | AR66: 0.3614611 | AS66: 0.60924674 | AT66: 0.39806251 | AU66: 4790.4965 | AV66: 387.40625 | AW66: 274.37688 | AX66: 649.6072 | AY66: 738.87921 | AZ66: 503.26889 | BA66: 1.636122 | BB66: 1.381125 | BC66: 1.6051833 | BD66: 110.45625 | BE66: 315.81354 | BF66: 290.27083 | BG66: 194.12917 | BH66: 260.33333 | BI66: 1604.1817 | BJ66: 58.424167 | BK66: 4867.8975 | BL66: 1866.6533 | BM66: 17933.762 | BN66: 9595.1792 | BO66: 2089.975 | BP66: 1248.9883 | BQ66: 987.08667 | BR66: 17.14675
A67: 2017 | B67: 52.805 | C67: 54.3925 | D67: 53.115833 | E67: 50.906667 | F67: 88.518333 | G67: 85.149167 | H67: 2.961075 | I67: 5.7170433 | J67: 8.6061242 | K67: 68.966702 | L67: 2.0294108 | M67: 3.3232074 | N67: 2.2255271 | O67: 3.1484792 | P67: 4.0516667 | Q67: 2.4232155 | R67: 2.9705556 | S67: 1650.65 | T67: 1486.6825 | U67: 1366.9667 | V67: 1460.7925 | W67: 750.81333 | X67: 1288.4633 | Y67: 393.37811 | Z67: 850.39667 | AA67: 350.24167 | AB67: 97.638639 | AC67: 154.53154 | AD67: 163.02246 | AE67: 398.91667 | AF67: 384.66667 | AG67: 379.90083 | AH67: 363.24667 | AI67: 178.18261 | AJ67: 174.19562 | AK67: 0.89910526 | AL67: 1.0758821 | AM67: 0.81203536 | AN67: 4.3872489 | AO67: 2.1244774 | AP67: 5.4194936 | AQ67: 13.318293 | AR67: 0.36875427 | AS67: 0.61554828 | AT67: 0.35312501 | AU67: 4627.3646 | AV67: 395.22292 | AW67: 265.42852 | AX67: 617.28036 | AY67: 702.10987 | AZ67: 486.85559 | BA67: 1.8429888 | BB67: 1.6668583 | BC67: 1.9954417 | BD67: 89.6875 | BE67: 323.02708 | BF67: 283.20417 | BG67: 213.875 | BH67: 218.22917 | BI67: 1967.6542 | BJ67: 71.76 | BK67: 6169.94 | BL67: 2314.665 | BM67: 20061.169 | BN67: 10409.635 | BO67: 2890.8667 | BP67: 1257.5592 | BQ67: 948.45333 | BR67: 17.066167
